Workbook
Name \0: #N/A
Name \c: #REF!
Name \s: #REF!
Name \T: '[1]Q144A-02'!#REF!
Name ___INT1: INT(FINANZIARIO!DUEPER)
Name ___INT1: INT('FINANZIARIO (2)'!DUEPER)
Name ___INT1: INT([0]!DUEPER)
Name __cap1: #REF!
Name __cap2: #REF!
Name __cap3: #REF!
Name __TOT1: #REF!
Name __TOT10: #REF!
Name __TOT11: #REF!
Name __tot12: #REF!
Name __TOT2: #REF!
Name __TOT3: #REF!
Name __TOT4: #REF!
Name __TOT5: #REF!
Name __TOT6: #REF!
Name __TOT7: #REF!
Name __TOT8: #REF!
Name __TOT9: #REF!
Name _1Excel_BuiltIn_Print_Titles_1_1_1: [2]Riassunto!#REF!
Name _20500: #REF!
Name _21300: #REF!
Name _21400: #REF!
Name _21600: #REF!
Name _21601: #REF!
Name _23400: #REF!
Name _24000: #REF!
Name _25100: #REF!
Name _25200: #REF!
Name _25700: #REF!
Name _26008: #REF!
Name _26300: #REF!
Name _27500: #REF!
Name _cap1: #REF!
Name _cap2: #REF!
Name _cap3: #REF!
Name _INT1: INT(FINANZIARIO!DUEPER)
Name _INT1: INT('FINANZIARIO (2)'!DUEPER)
Name _INT1: INT(DUEPER)
Name _T: [1]Q144A_02!#REF!
Name _Toc328203711_1: #REF!
Name _Toc328276670_1: #REF!
Name _TOT1: #REF!
Name _TOT10: #REF!
Name _TOT11: #REF!
Name _tot12: #REF!
Name _TOT2: #REF!
Name _TOT3: #REF!
Name _TOT4: #REF!
Name _TOT5: #REF!
Name _TOT6: #REF!
Name _TOT7: #REF!
Name _TOT8: #REF!
Name _TOT9: #REF!
Name _WBS2: #REF!
Name a: '[3]Costi singoli'!#REF!
Name A100_INTERVENTIPREL: #REF!

Sheet OFFERTA
A2: Suburban S.r.l. a Socio Unico | F2: Spett.le
A3: P.IVA: 12352270966 | F3: =[37]ANACO!C7 -> VASTINT ITALY s.r.l.
A4: REA: MB - 2656311 | F4: Via A. Manzoni 38
A5: Sede Legale: | F5: 20121 Milano, Italy
A6: CORNATE D'ADDA (MB) - VIA | F6: P.IVA: 08218800962
A7: BERLINGUER 17/A CAP 20872 | F7: C.a. | G7: =[37]ANACO!C8 -> Mr.Marco Mor/Ing. Esposito
A9: Cornate | B9: d'Adda | E9: =ANACO!C6 -> 45908
A11: Ns. Preventivo | E11: =ANACO!C5 -> P1002_25_CON_REV03_P1 E EI ALLUMINIO
A13: Oggetto: | E13: =ANACO!C9 -> FPO SERRAMENTI E RACCORDO - EX STAZIONE SUSA
A15: Immobile:
A17: RingraziandoVi per la fiducia riservataci nell’averci interpellati, Vi inviamo, per il cantiere in oggetto, nostra offerta per quanto di nostra competenza.
A18: L'offerta è stata redatta analizzando la documentazione ricevuta e potrà subire variazioni al ricevimento di documentazione più precisa. Dalla presente offerta risultano esclusi i ponteggi e la gru di cantiere.
A21: OFFERTA
A22: ITEM | B22: CODICE | C22: LARGH | D22: ALT. | E22: DESCRIZIONE | F22: U.M. | G22: Q.TA' | H22: PREZZO | I22: IMPORTO TOTALE
E24: =ANACO!C12 -> SERRAMENTI SERIE F
A25: =ANACO!B13 -> F1 | B25: =ANACO!$C$5 -> P1002_25_CON_REV03_P1 E EI ALLUMINIO | C25: =ANACO!D13 -> 1100 | D25: =ANACO!F13 -> 1970 | E25: =ANACO!C13 -> Serramento in legno doppia anta battente apertura interna e sopraluce curvo con apertura vasistas fissato solidamente ad un controtelaio in profili di legno adeguatamente trattato e isolato. Compreso controtelaio costituito da profili in legno sagomato a L, adeguatamente trattato per evitare formazione di muffe o deformazioni geometriche, ancorato alla struttura principale mediante adeguate zanche annegate nel muro o viti di fissaggio. Vetro: 66.2 COOL-LITE 70-33#2 INDURITI / 20mm (aria-argon 90%) / 55.2 int. RICOTTI Comprese lamiere di raccordo, memebrane e isolanti. | F25: cad. | G25: =ANACO!H13 -> 10 | H25: =ANACO!BS13 -> 4443.0585 | I25: =G25*H25 -> 44430.585
A26: =ANACO!B14 -> F1a | B26: =ANACO!$C$5 -> P1002_25_CON_REV03_P1 E EI ALLUMINIO | C26: =ANACO!D14 -> 1100 | D26: =ANACO!F14 -> 1970 | E26: =ANACO!C14 -> Serramento in legno doppia anta battente apertura interna e sopraluce curvo con apertura vasistas fissato solidamente ad un controtelaio in profili di legno adeguatamente trattato e isolato. Compreso controtelaio costituito da profili in legno sagomato a L, adeguatamente trattato per evitare formazione di muffe o deformazioni geometriche, ancorato alla struttura principale mediante adeguate zanche annegate nel muro o viti di fissaggio. Vetro: 66.2 COOL-LITE 70-33#2 INDURITI / 20mm (aria-argon 90%) / 55.2 int. RICOTTI Comprese lamiere di raccordo, memebrane e isolanti. | F26: cad. | G26: =ANACO!H14 -> 1 | H26: =ANACO!BS14 -> 4443.0585 | I26: =G26*H26 -> 4443.0585
A27: =ANACO!B15 -> F2 | B27: =ANACO!$C$5 -> P1002_25_CON_REV03_P1 E EI ALLUMINIO | C27: =ANACO!D15 -> 1720 | D27: =ANACO!F15 -> 3710 | E27: =ANACO!C15 -> Serramento in legno doppia anta battente apertura interna e sopraluce curvo fisso. Specchiature fisse laterali e superiori, fissato solidamente ad un controtelaio in profili di legno adeguatamente trattato e isolato e persiane a lamelle fisse esterne. Compreso controtelaio costituito da profili in legno sagomato a L, adeguatamente trattato per evitare formazione di muffe o deformazioni geometriche, ancorato alla struttura principale mediante adeguate zanche annegate nel muro o viti di fissaggio. Vetro: 66.2 COOL-LITE 70-33#2 INDURITI / 20mm (aria-argon 90%) / 55.2 int. RICOTTI Comprese lamiere di raccordo, memebrane e isolanti. | F27: cad. | G27: =ANACO!H15 -> 5 | H27: =ANACO!BS15 -> 9861.8457 | I27: =G27*H27 -> 49309.228
A28: =ANACO!B16 -> F3 - EI60 Serramento in acciaio EI60 tipo Secco EBE85 | B28: =ANACO!$C$5 -> P1002_25_CON_REV03_P1 E EI ALLUMINIO | C28: =ANACO!D16 -> 1200 | D28: =ANACO!F16 -> 3000 | E28: =ANACO!C16 -> Serramento in legno fissa, serramento fissato solidamente ad un controtelaio in profili di legno adeguatamente trattato e isolato. Per questo serramento è richiesta una prestazione di resistenza all’incendio pari a EI60. SOSTITUITO CON ALLUMINIO Reynaers ConceptSystem 77-FP EI 60 (CS 77-FPEI60) Compreso controtelaio costituito da profili in legno sagomato a L, adeguatamente trattato per evitare formazione di muffe o deformazioni geometriche, ancorato alla struttura principale mediante adeguate zanche annegate nel muro o viti di fissaggio. Vetro: 66.2 COOL-LITE 70-33#2 / 14mm (aria-argon 90%) / 27 CF60-3. Comprese lamiere di raccordo, memebrane e isolanti. | F28: cad. | G28: =ANACO!H16 -> 3 | H28: =ANACO!BS16 -> 8821.1292 | I28: =G28*H28 -> 26463.388
A29: =ANACO!B17 -> F3a | B29: =ANACO!$C$5 -> P1002_25_CON_REV03_P1 E EI ALLUMINIO | C29: =ANACO!D17 -> 1200 | D29: =ANACO!F17 -> 3000 | E29: =ANACO!C17 -> Porta a doppio battente apertura interno dell’edificio con pushbar esterno e chiudiporta, presenza di sopraluce fisso è presente un ulteriore sopraluce curvo con presenza di lamelle di areazione. Il serramento presente una prestazione EI60 escluso la parte lamellata. SOSTITUITO CON ALLUMINIO Reynaers ConceptSystem 77-FP EI 60 (CS 77-FPEI60) Compreso controtelaio costituito da profili in legno sagomato a L, adeguatamente trattato per evitare formazione di muffe o deformazioni geometriche, ancorato alla struttura principale mediante adeguate zanche annegate nel muro o viti di fissaggio. Vetro: 66.2 COOL-LITE 70-33#2 / 14mm (aria-argon 90%) / 27 CF60-3. Comprese lamiere di raccordo, memebrane e isolanti. | F29: cad. | G29: =ANACO!H17 -> 1 | H29: =ANACO!BS17 -> 6217.2576 | I29: =G29*H29 -> 6217.2576
A30: =ANACO!B18 -> F3b | B30: =ANACO!$C$5 -> P1002_25_CON_REV03_P1 E EI ALLUMINIO | E30: =ANACO!C18 -> Serramento con specchiature vision fisse è presente un ulteriore sopraluce curvo con presenza di lamelle di areazione. Il serramento presenta una prestazione EI60 escluso la parte lamellata.SOSTITUITO CON ALLUMINIO Reynaers ConceptSystem 77-FP EI 60 (CS 77-FPEI60) Compreso controtelaio costituito da profili in legno sagomato a L, adeguatamente trattato per evitare formazione di muffe o deformazioni geometriche, ancorato alla struttura principale mediante adeguate zanche annegate nel muro o viti di fissaggio. Vetro: 66.2 COOL-LITE 70-33#2 / 14mm (aria-argon 90%) / 27 CF60-3. Comprese lamiere di raccordo, memebrane e isolanti. | F30: cad. | G30: =ANACO!H18 -> 2 | H30: =ANACO!BS18 -> 6217.2576 | I30: =G30*H30 -> 12434.515
A31: =ANACO!B19 -> F4a | B31: =ANACO!$C$5 -> P1002_25_CON_REV03_P1 E EI ALLUMINIO | E31: =ANACO!C19 -> Serramento in acciaio con volta circolare apribile a vasistas meccanizzato e automatico specchiatura inferiore con porta a doppio battente apertura esterna, sopraluce rettangolare fisso. SOSTITUITO CON ALLUMINIO Reynaers ConceptSystem 77-FP EI 60 (CS 77-FPEI60) Controtelaio composto da tubi rettangolari ancorato alla struttura principale mediante adeguate zanche annegate nel muro o viti di fissaggio, il telaio deve essere correttamente isolato e zincato per proteggerlo dalla corrosione. Vetro: 66.2 COOL-LITE 70-33#2 / 14mm (aria-argon 90%) / 27 CF60-3. Comprese lamiere di raccordo, memebrane e isolanti. | F31: cad. | G31: =ANACO!H19 -> 1 | H31: =ANACO!BS19 -> 5827.2489 | I31: =G31*H31 -> 5827.2489
A32: =ANACO!B20 -> F4b | B32: =ANACO!$C$5 -> P1002_25_CON_REV03_P1 E EI ALLUMINIO | E32: =ANACO!C20 -> Porta a doppio battente vetrata, apertura doppia anta verso l’esterno, sopraluce fisso. Compreso controtelaio costituito da profili in legno sagomato a L, adeguatamente trattato per evitare formazione di muffe o deformazioni geometriche, ancorato alla struttura principale mediante adeguate zanche annegate nel muro o viti di fissaggio. Vetro: 66.2 COOL-LITE 70-33#2 INDURITI / 20mm (aria-argon 90%) / 55.2 int. RICOTTI Comprese lamiere di raccordo, memebrane e isolanti. | F32: cad. | G32: =ANACO!H20 -> 1 | H32: =ANACO!BS20 -> 8033.6889 | I32: =G32*H32 -> 8033.6889
A33: =ANACO!B21 -> F5a - EI60 Serramento in acciaio EI60 tipo Secco EBE85 | B33: =ANACO!$C$5 -> P1002_25_CON_REV03_P1 E EI ALLUMINIO | E33: =ANACO!C21 -> Porta a doppio battente apertura interno dell’edificio con pushbar esterno e chiudiporta, presenza di sopraluce fisso è presente un ulteriore sopraluce curvo con presenza di lamelle di areazione. Il serramento presente una prestazione EI60 escluso la parte lamellata. SOSTITUITO CON ALLUMINIO Reynaers ConceptSystem 77-FP EI 60 (CS 77-FPEI60) Compreso controtelaio costituito da profili in legno sagomato a L, adeguatamente trattato per evitare formazione di muffe o deformazioni geometriche, ancorato alla struttura principale mediante adeguate zanche annegate nel muro o viti di fissaggio. Vetro: 66.2 COOL-LITE 70-33#2 / 14mm (aria-argon 90%) / 27 CF60-3. Comprese lamiere di raccordo, memebrane e isolanti. | F33: cad. | G33: =ANACO!H21 -> 1 | H33: =ANACO!BS21 -> 20012.035 | I33: =G33*H33 -> 20012.035
A34: =ANACO!B22 -> F5b - EI60 Serramento in acciaio EI60 tipo Secco EBE85 | B34: =ANACO!$C$5 -> P1002_25_CON_REV03_P1 E EI ALLUMINIO | E34: =ANACO!C22 -> Serramento con specchiature vision fisse è presente un ulteriore sopraluce curvo con presenza di lamelle di areazione. Il serramento presenta una prestazione EI60 escluso la parte lamellata.SOSTITUITO CON ALLUMINIO Reynaers ConceptSystem 77-FP EI 60 (CS 77-FPEI60) Compreso controtelaio costituito da profili in legno sagomato a L, adeguatamente trattato per evitare formazione di muffe o deformazioni geometriche, ancorato alla struttura principale mediante adeguate zanche annegate nel muro o viti di fissaggio. Vetro: 66.2 COOL-LITE 70-33#2 / 14mm (aria-argon 90%) / 27 CF60-3. Comprese lamiere di raccordo, memebrane e isolanti. | F34: cad. | G34: =ANACO!H22 -> 1 | H34: =ANACO!BS22 -> 15793.921 | I34: =G34*H34 -> 15793.921
A35: =ANACO!B23 -> F6 | B35: =ANACO!$C$5 -> P1002_25_CON_REV03_P1 E EI ALLUMINIO | E35: =ANACO!C23 -> Serramento portafinestra in legno doppia anta battente apertura interna fissato solidamente ad un controtelaio in profili di legno adeguatamente trattato e isolato. Compreso controtelaio costituito da profili in legno sagomato a L, adeguatamente trattato per evitare formazione di muffe o deformazioni geometriche, ancorato alla struttura principale mediante adeguate zanche annegate nel muro o viti di fissaggio. Vetro: 66.2 COOL-LITE 70-33#2 INDURITI / 20mm (aria-argon 90%) / 55.2 int. RICOTTI Comprese lamiere di raccordo, memebrane e isolanti. | F35: cad. | G35: =ANACO!H23 -> 11 | H35: =ANACO!BS23 -> 6480.5492 | I35: =G35*H35 -> 71286.041
A36: =ANACO!B24 -> F6a | B36: =ANACO!$C$5 -> P1002_25_CON_REV03_P1 E EI ALLUMINIO | E36: =ANACO!C24 -> Serramento portafinestra in legno doppia anta battente apertura interna fissato solidamente ad un controtelaio in profili di legno adeguatamente trattato e isolato. SERRAMENTO A TENUTA FUMI. Compreso controtelaio costituito da profili in legno sagomato a L, adeguatamente trattato per evitare formazione di muffe o deformazioni geometriche, ancorato alla struttura principale mediante adeguate zanche annegate nel muro o viti di fissaggio. Vetro: 66.2 COOL-LITE 70-33#2 INDURITI / 20mm (aria-argon 90%) / 55.2 int. RICOTTI Comprese lamiere di raccordo, memebrane e isolanti. | F36: cad. | G36: =ANACO!H24 -> 3 | H36: =ANACO!BS24 -> 6353.2022 | I36: =G36*H36 -> 19059.607
A37: =ANACO!B25 -> F6b | B37: =ANACO!$C$5 -> P1002_25_CON_REV03_P1 E EI ALLUMINIO | E37: =ANACO!C25 -> Serramento portafinestra in legno doppia anta battente apertura esterna fissato solidamente ad un controtelaio in profili di legno adeguatamente trattato e isolato. SERRAMENTO A TENUTA FUMI. Compreso controtelaio costituito da profili in legno sagomato a L, adeguatamente trattato per evitare formazione di muffe o deformazioni geometriche, ancorato alla struttura principale mediante adeguate zanche annegate nel muro o viti di fissaggio. Vetro: 66.2 COOL-LITE 70-33#2 INDURITI / 20mm (aria-argon 90%) / 55.2 int. RICOTTI Comprese lamiere di raccordo, memebrane e isolanti. | F37: cad. | G37: =ANACO!H25 -> 1 | H37: =ANACO!BS25 -> 6353.2022 | I37: =G37*H37 -> 6353.2022
A38: =ANACO!B26 -> F7 | B38: =ANACO!$C$5 -> P1002_25_CON_REV03_P1 E EI ALLUMINIO | E38: =ANACO!C26 -> Serramento finestra in legno doppia anta battente apertura interna fissato solidamente ad un controtelaio in profili di legno adeguatamente trattato e isolato. Compreso controtelaio costituito da profili in legno sagomato a L, adeguatamente trattato per evitare formazione di muffe o deformazioni geometriche, ancorato alla struttura principale mediante adeguate zanche annegate nel muro o viti di fissaggio. Vetro: 66.2 COOL-LITE 70-33#2 INDURITI / 20mm (aria-argon 90%) / 55.2 int. RICOTTI Comprese lamiere di raccordo, memebrane e isolanti. | F38: cad. | G38: =ANACO!H26 -> 3 | H38: =ANACO!BS26 -> 4250.9382 | I38: =G38*H38 -> 12752.815
A39: =ANACO!B27 -> F7a | B39: =ANACO!$C$5 -> P1002_25_CON_REV03_P1 E EI ALLUMINIO | E39: =ANACO!C27 -> Serramento finestra in legno doppia anta battente apertura interna fissato solidamente ad un controtelaio in profili di legno adeguatamente trattato e isolato. Compreso controtelaio costituito da profili in legno sagomato a L, adeguatamente trattato per evitare formazione di muffe o deformazioni geometriche, ancorato alla struttura principale mediante adeguate zanche annegate nel muro o viti di fissaggio. Vetro: 66.2 COOL-LITE 70-33#2 INDURITI / 20mm (aria-argon 90%) / 55.2 int. RICOTTI Comprese lamiere di raccordo, memebrane e isolanti. | F39: cad. | G39: =ANACO!H27 -> 2 | H39: =ANACO!BS27 -> 4250.9382 | I39: =G39*H39 -> 8501.8764
E40: =ANACO!C28 -> SERRAMENTI SERIE S
A41: =ANACO!B29 -> S1a | B41: =ANACO!$C$5 -> P1002_25_CON_REV03_P1 E EI ALLUMINIO | E41: =ANACO!C29 -> Serramento in acciaio con volta circolare fissa specchiatura inferiore con porta a doppio battente apertura esterna, sopraluce rettangolare fisso e apribile vasistas di ventilazione ad apertura meccanizzata. Controtelaio composto da tubi rettangolari ancorato alla struttura principale mediante adeguate zanche annegate nel muro o viti di fissaggio, il telaio deve essere correttamente isolato e zincato per proteggerlo dalla corrosione. Vetro: 66.2 COOL-LITE 70-33#2 INDURITI / 20mm (aria-argon 90%) / 55.2 int. INDURITI Comprese lamiere di raccordo, memebrane e isolanti. | F41: cad. | G41: =ANACO!H29 -> 1 | H41: =ANACO!BS29 -> 31940.78 | I41: =G41*H41 -> 31940.78
A42: =ANACO!B30 -> S1b | B42: =ANACO!$C$5 -> P1002_25_CON_REV03_P1 E EI ALLUMINIO | E42: =ANACO!C30 -> Serramento in acciaio con volta circolare fissa specchiatura inferiore con porta a doppio battente apertura esterna, sopraluci rettangolari fissi. Controtelaio composto da tubi rettangolari ancorato alla struttura principale mediante adeguate zanche annegate nel muro o viti di fissaggio, il telaio deve essere correttamente isolato e zincato per proteggerlo dalla corrosione. Vetro: 66.2 COOL-LITE 70-33#2 INDURITI / 20mm (aria-argon 90%) / 55.2 int. INDURITI Comprese lamiere di raccordo, memebrane e isolanti. | F42: cad. | G42: =ANACO!H30 -> 2 | H42: =ANACO!BS30 -> 31940.78 | I42: =G42*H42 -> 63881.559
A43: =ANACO!B31 -> S1c | B43: =ANACO!$C$5 -> P1002_25_CON_REV03_P1 E EI ALLUMINIO | E43: =ANACO!C31 -> Serramento in acciaio con volta circolare fissa specchiatura inferiore con porta US a doppio battente apertura esterna con pushbar, sopraluci rettangolari fissi. Controtelaio composto da tubi rettangolari ancorato alla struttura principale mediante adeguate zanche annegate nel muro o viti di fissaggio, il telaio deve essere correttamente isolato e zincato per proteggerlo dalla corrosione. Vetro: 66.2 COOL-LITE 70-33#2 INDURITI / 20mm (aria-argon 90%) / 55.2 int. INDURITI Comprese lamiere di raccordo, memebrane e isolanti. | F43: cad. | G43: =ANACO!H31 -> 1 | H43: =ANACO!BS31 -> 31940.78 | I43: =G43*H43 -> 31940.78
A44: =ANACO!B32 -> S2a | B44: =ANACO!$C$5 -> P1002_25_CON_REV03_P1 E EI ALLUMINIO | E44: =ANACO!C32 -> Serramento in acciaio con volta circolare fissa specchiatura inferiore con vetri fissi, sopraluce rettangolare fisso e apribile vasistas di ventilazione apertura meccanizzata. Controtelaio composto da tubi rettangolari ancorato alla struttura principale mediante adeguate zanche annegate nel muro o viti di fissaggio, il telaio deve essere correttamente isolato e zincato per proteggerlo dalla corrosione. Vetro: 66.2 COOL-LITE 70-33#2 INDURITI / 20mm (aria-argon 90%) / 55.2 int. INDURITI Comprese lamiere di raccordo, memebrane e isolanti. | F44: cad. | G44: =ANACO!H32 -> 3 | H44: =ANACO!BS32 -> 31239.35 | I44: =G44*H44 -> 93718.049
A45: =ANACO!B33 -> S2b | B45: =ANACO!$C$5 -> P1002_25_CON_REV03_P1 E EI ALLUMINIO | E45: =ANACO!C33 -> Serramento in acciaio con volta circolare fissa specchiatura inferiore con vetri fissi, sopraluce rettangolari fissi. Controtelaio composto da tubi rettangolari ancorato alla struttura principale mediante adeguate zanche annegate nel muro o viti di fissaggio, il telaio deve essere correttamente isolato e zincato per proteggerlo dalla corrosione. Vetro: 66.2 COOL-LITE 70-33#2 INDURITI / 20mm (aria-argon 90%) / 55.2 int. INDURITI Comprese lamiere di raccordo, memebrane e isolanti. | F45: cad. | G45: =ANACO!H33 -> 4 | H45: =ANACO!BS33 -> 31239.35 | I45: =G45*H45 -> 124957.4
A46: =ANACO!B34 -> S2c | B46: =ANACO!$C$5 -> P1002_25_CON_REV03_P1 E EI ALLUMINIO | E46: =ANACO!C34 -> Serramento in acciaio con volta circolare fissa specchiatura inferiore con vetri fissi, sopraluce rettangolare fisso e apribile vasistas di ventilazione apertura meccanizzata. Controtelaio composto da tubi rettangolari ancorato alla struttura principale mediante adeguate zanche annegate nel muro o viti di fissaggio, il telaio deve essere correttamente isolato e zincato per proteggerlo dalla corrosione. Vetro: 66.2 COOL-LITE 70-33#2 INDURITI / 20mm (aria-argon 90%) / 55.2 int. INDURITI Comprese lamiere di raccordo, memebrane e isolanti. | F46: cad. | G46: =ANACO!H34 -> 1 | H46: =ANACO!BS34 -> 31239.35 | I46: =G46*H46 -> 31239.35
A47: =ANACO!B35 -> S3 | B47: =ANACO!$C$5 -> P1002_25_CON_REV03_P1 E EI ALLUMINIO | E47: =ANACO!C35 -> Serramento in acciaio con volta circolare fissa, specchiatura inferiore con porta scorrevole ad anta e fissi laterali, sopraluce rettangolare fisso e apribile vasistas di ventilazione apertura meccanizzata. Controtelaio composto da tubi rettangolari ancorato alla struttura principale mediante adeguate zanche annegate nel muro o viti di fissaggio, il telaio deve essere correttamente isolato e zincato per proteggerlo dalla corrosione. Vetro: 66.2 COOL-LITE 70-33#2 INDURITI / 20mm (aria-argon 90%) / 55.2 int. INDURITI Comprese lamiere di raccordo, memebrane e isolanti. | F47: cad. | G47: =ANACO!H35 -> 2 | H47: =ANACO!BS35 -> 36551.15 | I47: =G47*H47 -> 73102.299
A48: =ANACO!B36 -> S4 | B48: =ANACO!$C$5 -> P1002_25_CON_REV03_P1 E EI ALLUMINIO | E48: =ANACO!C36 -> Serramento in acciaio con volta circolare apribile a vasistas specchiatura inferiore con porta a doppio battente apertura esterna, sopraluce rettangolare fisso Controtelaio composto da tubi rettangolari ancorato alla struttura principale mediante adeguate zanche annegate nel muro o viti di fissaggio, il telaio deve essere correttamente isolato e zincato per proteggerlo dalla corrosione. Vetro: 66.2 COOL-LITE 70-33#2 INDURITI / 20mm (aria-argon 90%) / 55.2 int. INDURITI Comprese lamiere di raccordo, memebrane e isolanti. | F48: cad. | G48: =ANACO!H36 -> 2 | H48: =ANACO!BS36 -> 16983.554 | I48: =G48*H48 -> 33967.109
A49: =ANACO!B37 -> S4a - EI60 | B49: =ANACO!$C$5 -> P1002_25_CON_REV03_P1 E EI ALLUMINIO | E49: =ANACO!C37 -> Serramento in acciaio con volta circolare apribile a vasistas meccanizzato e automatico specchiatura inferiore con porta a doppio battente apertura esterna, sopraluce rettangolare fisso. SOSTITUITO CON ALLUMINIO Reynaers ConceptSystem 77-FP EI 60 (CS 77-FPEI60) Controtelaio composto da tubi rettangolari ancorato alla struttura principale mediante adeguate zanche annegate nel muro o viti di fissaggio, il telaio deve essere correttamente isolato e zincato per proteggerlo dalla corrosione. Vetro: 66.2 COOL-LITE 70-33#2 / 14mm (aria-argon 90%) / 27 CF60-3. Comprese lamiere di raccordo, memebrane e isolanti. | F49: cad. | G49: =ANACO!H37 -> 1 | H49: =ANACO!BS37 -> 20724.532 | I49: =G49*H49 -> 20724.532
A50: =ANACO!B38 -> S5 | B50: =ANACO!$C$5 -> P1002_25_CON_REV03_P1 E EI ALLUMINIO | E50: =ANACO!C38 -> Serramento in acciaio rettangolare con porta inferiore a doppia anta apertura esterna; tre specchiature sopraluce: inferiore apribile a battente apertura esterna, centrale rettangolare opaca fissa, superiore a vasistas apertura interna. SOSTITUITO CON SERRAMENTO IN ALLUMINIO COMPOSTO DA PIU ELEMENTI ACCOPPIATI Reynaers SlimLine 38 (SL 38) Controtelaio composto da tubi rettangolari ancorato alla struttura principale mediante adeguate zanche annegate nel muro o viti di fissaggio, il telaio deve essere correttamente isolato e zincato per proteggerlo dalla corrosione. Vetro: 66.2 COOL-LITE 70-33#2 INDURITI / 20mm (aria-argon 90%) / 55.2 int. INDURITI Comprese lamiere di raccordo, memebrane e isolanti. | F50: cad. | G50: =ANACO!H38 -> 1 | H50: =ANACO!BS38 -> 14567.898 | I50: =G50*H50 -> 14567.898
A51: =ANACO!B39 -> S5a | B51: =ANACO!$C$5 -> P1002_25_CON_REV03_P1 E EI ALLUMINIO | E51: =ANACO!C39 -> Serramento in acciaio rettangolare con porta inferiore a doppia anta apertura esterna; con tre specchiature sopraluce: inferiore apribile a battente apertura esterna, centrale rettangolare opaca fissa, superiore a vasistas apertura interna.SOSTITUITO CON SERRAMENTO IN ALLUMINIO COMPOSTO DA PIU ELEMENTI ACCOPPIATI Reynaers SlimLine 38 (SL 38) Controtelaio composto da tubi rettangolari ancorato alla struttura principale mediante adeguate zanche annegate nel muro o viti di fissaggio, il telaio deve essere correttamente isolato e zincato per proteggerlo dalla corrosione. Vetro: 66.2 COOL-LITE 70-33#2 INDURITI / 20mm (aria-argon 90%) / 55.2 int. INDURITI Comprese lamiere di raccordo, memebrane e isolanti. | F51: cad. | G51: =ANACO!H39 -> 1 | H51: =ANACO!BS39 -> 14567.898 | I51: =G51*H51 -> 14567.898
A52: =ANACO!B40 -> S6 | B52: =ANACO!$C$5 -> P1002_25_CON_REV03_P1 E EI ALLUMINIO | E52: =ANACO!C40 -> Serramento in acciaio rettangolare con porta inferiore a doppia anta apertura interna; tre specchiature sopraluce: inferiore apribile a vasistas apertura interna, centrale rettangolare opaca fissa, superiore a vasistas apertura interna.SOSTITUITO CON SERRAMENTO IN ALLUMINIO COMPOSTO DA PIU ELEMENTI ACCOPPIATI Reynaers SlimLine 38 (SL 38) Controtelaio composto da tubi rettangolari ancorato alla struttura principale mediante adeguate zanche annegate nel muro o viti di fissaggio, il telaio deve essere correttamente isolato e zincato per proteggerlo dalla corrosione. Vetro: 66.2 COOL-LITE 70-33#2 INDURITI / 20mm (aria-argon 90%) / 55.2 int. INDURITI Comprese lamiere di raccordo, memebrane e isolanti. | F52: cad. | G52: =ANACO!H40 -> 2 | H52: =ANACO!BS40 -> 14555.64 | I52: =G52*H52 -> 29111.279
... A58: =ANACO!B46 -> S9 | B58: =ANACO!$C$5 -> P1002_25_CON_REV03_P1 E EI ALLUMINIO | E58: =ANACO!C46 -> Serramento in acciaio con volta circolare fissa specchiatura inferiore con vetri fissi, sopraluce rettangolare fisso e apribile vasistas di ventilazione apertura meccanizzata. Controtelaio composto da tubi rettangolari ancorato alla struttura principale mediante adeguate zanche annegate nel muro o viti di fissaggio, il telaio deve essere correttamente isolato e zincato per proteggerlo dalla corrosione. Vetro: 66.2 COOL-LITE 70-33#2 INDURITI / 20mm (aria-argon 90%) / 55.2 int. INDURITI Comprese lamiere di raccordo, memebrane e isolanti. | F58: cad. | G58: =ANACO!H46 -> 2 | H58: =ANACO!BS46 -> 31239.35 | I58: =G58*H58 -> 62478.699
A59: =ANACO!B47 -> FW | B59: =ANACO!$C$5 -> P1002_25_CON_REV03_P1 E EI ALLUMINIO | E59: =ANACO!C47 -> CONNECTION - SISTEMA FACCIATA MONTANTI E TRAVERSI CON CARTELLA : Reynaers ConceptWall 50/60 (CW50-CW60) Reynaers SlimLine 38 (SL 38) Reynaers ConceptWall Outward Opening GB Secondo documento di gara Compresi: partizione EI60 FISSA Reynaers ConceptWall 50-FP (CW 50-FP) Vetro: 66.2 COOL-LITE 70-33#2 INDURITI / 20mm (aria-argon 90%) / 55.2 int. INDURITI Comprese lamiere di finitura estern sv. 500mm , isolanti e staffe. | F59: CPO | G59: =ANACO!I47 -> 1 | H59: =ANACO!BS47 -> 129390 | I59: =G59*H59 -> 129390
A60: =ANACO!B48 -> 0 | B60: =ANACO!$C$5 -> P1002_25_CON_REV03_P1 E EI ALLUMINIO | E60: =ANACO!C48 -> 0 | F60: cad. | G60: =ANACO!I48 -> 0 | H60: =ANACO!BS48 -> 0 | I60: =G60*H60 -> 0
A61: =ANACO!B49 -> 0 | B61: =ANACO!$C$5 -> P1002_25_CON_REV03_P1 E EI ALLUMINIO | E61: =ANACO!C49 -> 0 | F61: cad. | G61: =ANACO!I49 -> 0 | H61: =ANACO!BS49 -> 0 | I61: =G61*H61 -> 0
A62: =ANACO!B50 -> 0 | B62: =ANACO!$C$5 -> P1002_25_CON_REV03_P1 E EI ALLUMINIO | E62: =ANACO!C50 -> 0 | F62: cad. | G62: =ANACO!I50 -> 0 | H62: =ANACO!BS50 -> 0 | I62: =G62*H62 -> 0
A63: =ANACO!B51 -> 0 | B63: =ANACO!$C$5 -> P1002_25_CON_REV03_P1 E EI ALLUMINIO | E63: =ANACO!C51 -> 0 | F63: cad. | G63: =ANACO!I51 -> 0 | H63: =ANACO!BS51 -> 0 | I63: =G63*H63 -> 0
A64: =ANACO!B52 -> 0 | B64: =ANACO!$C$5 -> P1002_25_CON_REV03_P1 E EI ALLUMINIO | E64: =ANACO!C52 -> 0 | F64: cad. | G64: =ANACO!I52 -> 0 | H64: =ANACO!BS52 -> 0 | I64: =G64*H64 -> 0
A65: =ANACO!B53 -> 0 | B65: =ANACO!$C$5 -> P1002_25_CON_REV03_P1 E EI ALLUMINIO | E65: =ANACO!C53 -> 0 | F65: cad. | G65: =ANACO!I53 -> 0 | H65: =ANACO!BS53 -> 0 | I65: =G65*H65 -> 0
A66: =ANACO!B54 -> 0 | B66: =ANACO!$C$5 -> P1002_25_CON_REV03_P1 E EI ALLUMINIO | E66: =ANACO!C54 -> 0 | F66: cad. | G66: =ANACO!I54 -> 0 | H66: =ANACO!BS54 -> 0 | I66: =G66*H66 -> 0
A67: =ANACO!B55 -> 0 | B67: =ANACO!$C$5 -> P1002_25_CON_REV03_P1 E EI ALLUMINIO | E67: =ANACO!C55 -> 0 | F67: cad. | G67: =ANACO!I55 -> 0 | H67: =ANACO!BS55 -> 0 | I67: =G67*H67 -> 0
A68: =ANACO!B56 -> 0 | B68: =ANACO!$C$5 -> P1002_25_CON_REV03_P1 E EI ALLUMINIO | E68: =ANACO!C56 -> 0 | F68: cad. | G68: =ANACO!I56 -> 0 | H68: =ANACO!BS56 -> 0 | I68: =G68*H68 -> 0
A69: =ANACO!B57 -> 0 | B69: =ANACO!$C$5 -> P1002_25_CON_REV03_P1 E EI ALLUMINIO | E69: =ANACO!C57 -> 0 | F69: cad. | G69: =ANACO!I57 -> 0 | H69: =ANACO!BS57 -> 0 | I69: =G69*H69 -> 0
A70: =ANACO!B58 -> 0 | B70: =ANACO!$C$5 -> P1002_25_CON_REV03_P1 E EI ALLUMINIO | E70: =ANACO!C58 -> 0 | F70: cad. | G70: =ANACO!I58 -> 0 | H70: =ANACO!BS58 -> 0 | I70: =G70*H70 -> 0
... A156: =ANACO!B144 -> 0 | B156: =ANACO!$C$5 -> P1002_25_CON_REV03_P1 E EI ALLUMINIO | E156: =ANACO!C144 -> 0 | F156: cad. | G156: =ANACO!I144 -> 0 | H156: =ANACO!BS144 -> 0 | I156: =G156*H156 -> 0
A158: TOTALE COMPLESSIVO IN OFFERTA | H158: =SUM(I25:I59) -> 1264104.8
A160: Condizioni generali di fornitura
A162: I prezzi indicati nella ns. offerta sono validi alle seguenti condizioni:
A164: Resa | F164: franco cantiere
A165: Tempi di consegna/planning | F165: Programma Lavori da confermare
A166: Modalità di pagamento | F166: 50% - Acconto all'ordine rimessa diretta
F167: 40% - Firma Esecutivi
F168: 10% SAL MENSILI - Rimessa Diretta
A171: Validità offerta | F171: 15 gg solari dalla presente
A173: Inclusioni/esclusioni
H174: incluso | I174: escluso
A175: Rilievi in cantiere | H175: P
A176: Rilievo topografico o laserscan | I176: O
A177: Modello BIM | I177: O
A178: Analisi della documentazione tecnica ricevuta dal cliente | H178: P
A179: Campionatura a richiesta dei materiali per l'approvazione qualitativa | H179: P
A180: Elaborazione disegni di sistema per approvazione e approvvigionamento materiali | H180: P
A181: Elaborazione disegni esecutivi per approvazione (1 rev inclusa) | H181: P
A182: Relazioni di calcolo (termica e statica) (1 rev inclusa) | H182: P
A183: Relazione di calcolo acustica (1 rev inclusa) | I183: O
A184: Relazione di calcolo allo shock termico (1 rev inclusa) | I184: O
A185: Elaborazione di disegni per produzione e installazione (che non saranno forniti) | H185: P
A186: Elaborazione disegni as-built | H186: P
A187: Certificazione prestazionale dei sistemi commerciali in Cascading | H187: P
A188: Visual mock up (1 sola realizzazione, quantità e dimensioni come da specifica) | I188: O
A189: Performance mock up (quantità e dimensioni come da specifica) | I189: O
A190: Prove e test specifici su serramenti e facciate | I190: O
A191: Prove e test richiesti in cantiere | I191: O
A192: Fornitura dei manufatti oggetto dell'offerta | H192: P
A193: Imballo idoneo alla tipologia di prodotto e di trasporto | H193: P
A194: Trasporto in cantiere | H194: P
A195: Mezzi di sollevamento e scarico dei materiali su nostri automezzi | I195: O
A196: Assistenza allo scarico da nostri automezzi | H196: P
A197: Magazzino e area per lo stoccaggio dei materiali | I197: O
A198: Eventuali oneri per l'occupazione del suolo pubblico | I198: O
A199: Impianto di cantiere (container uso spogliatoio/uso ufficio-colleg. acqua-energia-internet a disposizione) | I199: O
A200: Supervisione durante la fase di installazione | H200: P
A201: Guardiania cantiere | I201: O
A202: Messa in sicurezza area di cantiere | I202: O
A203: Oneri sicurezza e Covid 19 | I203: O
A204: Assistenza al Coordinamento della sicurezza | I204: O
A205: Coordinamento con enti locali di congruità delle normative vigenti | I205: O
H207: incluso | I207: escluso
...

Sheet ANACO
C2: ANALISI COSTO PREVENTIVO | BU2: Comm.
C3: SUBURBAN SRL a Socio Unico ANALISI PREVENTIVA | D3: Dimensioni ESTERNO TELAIO | G3: Mq. | I3: Mq. | BB3: COSTO MATERALE LAVORATO E POSATO CAD: | BC3: COSTO MATERALE LAVORATO E POSATO TOT. | BD3: COSTO MATERALE LAVORATO E POSATO MQ. | BE3: COSTI POST - MATERIALE POSATO | BM3: COSTI INDUSTRIALI DA COSTI MATERIALE | BP3: MOL SU BASE COSTI MATERIALE | BS3: PREZZO CLIENTE CAD. | BT3: PREZZO CLIENTE TOT. | BU3: PREZZO CLIENTE MQ..
B4: Pos. | D4: B | E4: * | F4: H | G4: MQ/Cad. | H4: Qt. | I4: MQ TOTALI | J4: PRODOTTO ACQUISTATO FINITO LEGNO O LEGNO ALLUMINIO | K4: Sc 1 | L4: Sc 2 | M4: Sc 3 | N4: PRODOTTO ACQUISTATO FINITO LEGNO O LEGNO ALLUMINIO Scontato CAD. | O4: PRODOTTO ACQUISTATO FINITO LEGNO O LEGNO ALLUMINIO Scontato TOTALE | P4: ST /LZ - STAFFAME CAD. | Q4: sc 1 | R4: ST /LZ - STAFFAME SCONTATO CAD. | S4: ST /LZ - STAFFAME TOT. | T4: Accessorio Maniglie e Maniglioni Listino CAD. | U4: sc 1 | V4: Accessorio Maniglie e Maniglioni CAD. | W4: Accessorio Maniglie e Maniglioni TOTALE | X4: LA Listino | Y4: Sc 1 | Z4: Sc 2 | AA4: Sc 3 | AB4: LA CAD | AC4: LA TOTALE | AD4: PACCHETTO DI COIBENTAZIONE CAD | AE4: PACCHETTO DI COIBENTAZIONECOIBENTAZIONE TOTALE | AF4: SISTEMA ALLUMINIO E ACCESSORI DI SISTEMA CAD. | AG4: SISTEMA ALLUMINIO E ACCESSORI DI SISTEMA TOTALE | AH4: SISTEMA ACCIAIO E ACCESSORI DI SISTEMA CAD. | AI4: SISTEMA ACCIAIO E ACCESSORI DI SISTEMA TOTALE | AJ4: Trasformazione Acciaio CAD. | AK4: Trasformazione Acciaio TOTALE | AL4: Automatismo CAD. | AM4: Automatismo TOTALE | AN4: Vetro CAD. | AO4: Vetro TOTALE. | AP4: Pannell CAD. | AQ4: Pannell TOTALE | AR4: Controtelaio CAD. | AS4: Controtelaio TOTALE. | AT4: Trasformazione Alluminio CAD. | AU4: Trasformazione Alluminio TOTALE. | AV4: Posa SER e FAC.. CAD | AW4: Posa SER e FAC.. TOTALE | AX4: FW FINITA LIN CAD | AY4: FW FINITA TOTALE | AZ4: NOLO CAD. | BA4: NOLO TOTALE | BE4: Trasporto e Imballo CAD: | BF4: Trasporto e Imballo TOT. | BG4: sviluppo tecnico e PM CAD. | BH4: sviluppo tecnico e PM TOTALE. | BI4: PRESIDIO CANTIERE SITE MNG NOLI CANTIERIZZAZIONE CAD. | BJ4: PRESIDIO CANTIERE SITE MNG NOLI CANTIERIZZAZIONE TOT. | BK4: EXTRA CAD. | BL4: EXTRA TOT. | BM4: % | BN4: EURO | BO4: EURO | BP4: % | BQ4: EURO | BR4: EURO | BV4: Note
B5: COD. | C5: P1002_25_CON_REV03_P1 E EI ALLUMINIO | D5: mm | F5: mm | G5: mq | I5: mq | K5: 1 | L5: 1 | M5: 1 | Q5: 1 | T5: 650 | U5: 1 | X5: 22 | Y5: 1 | Z5: 1 | AA5: 1 | AD5: 15 | AF5: 0 | AH5: =428*0.8 -> 342.4 | AL5: 60 | AN5: 135 | AR5: 35 | AT5: 0 | AV5: 132.5 | AZ5: 360 | BE5: 0.012 | BG5: 0.015 | BI5: 0.005 | BK5: 0.01 | BM5: 0 | BP5: 0.32
B6: DATA | C6: 45908 | P6: 18 | T6: 1930 | AD6: 28 | AH6: =1210*0.8 -> 968 | AN6: 135 | AP6: 0 | AR6: 45 | AT6: 0 | AV6: 23000 | AZ6: 90
B7: CLIENTE RAG.SOCIALE | C7: VASTINT ITALY s.r.l. | P7: 3.9 | AD7: 0 | AH7: 0 | AN7: =AN5*2 -> 270 | AT7: 0 | AV7: 234 | AZ7: =AZ5*AZ6 -> 32400
B8: RIFERIMENTO | C8: Mr.Marco Mor/Ing. Esposito | AH8: 0 | AN8: 595 | AT8: 0 | AV8: 1286 | AZ8: =AZ7/I157*0 -> 0
B9: OGGETTO | C9: FPO SERRAMENTI E RACCORDO - EX STAZIONE SUSA
B11: ITEMS | C11: DESCRIZIONE D'OFFERTA | BN11: CAD. | BO11: TOT. | BQ11: CAD. | BR11: TOT.
C12: SERRAMENTI SERIE F | G12: =(D12*F12)/1000000 -> 0 | I12: =G12*H12 -> 0 | J12: 0 | K12: =J12*$K$5 -> 0 | L12: =K12*$L$5 -> 0 | M12: =L12*$M$5 -> 0 | N12: =M12 -> 0 | O12: =N12*H12 -> 0 | P12: 0 | Q12: =P12*$Q$5 -> 0 | R12: 0 | S12: =R12*H12 -> 0 | T12: 0 | U12: =T12*$U$5 -> 0 | V12: 0 | W12: =V12*H12 -> 0 | X12: 0 | Y12: =X12*$Y$5 -> 0 | Z12: =Y12*$Z$5 -> 0 | AA12: =Z12*$AA$5 -> 0 | AB12: =AA12 -> 0 | AC12: =AB12*H12 -> 0 | AD12: 0 | AE12: =AD12*H12 -> 0 | AF12: 0 | AG12: =AF12*H12 -> 0 | AH12: 0 | AI12: =AH12*H12 -> 0 | AJ12: 0 | AK12: =AJ12*H12 -> 0 | AL12: 0 | AM12: =AL12*H12 -> 0 | AN12: 0 | AO12: =AN12*H12 -> 0 | AP12: 0 | AQ12: =AP12*H12 -> 0 | AR12: 0 | AS12: =AR12*H12 -> 0 | AT12: 0 | AU12: =AT12*H12 -> 0 | AV12: 0 | AW12: =AV12*H12 -> 0 | AX12: 0 | AY12: =AX12*H12 -> 0 | AZ12: 0 | BA12: =AZ12*H12 -> 0 | BB12: =N12+R12+V12+AB12+AD12+AF12+AH12+AJ12+AL12+AN12+AP12+AR12+AT12+AV12+AX12+AZ12 -> 0 | BC12: =O12+S12+W12+AC12+AE12+AG12+AI12+AK12+AM12+AO12+AQ12+AS12+AU12+AW12+AY12+BA12 -> 0 | BD12: =BC12/I12 -> #DIV/0! | BE12: =BB12*$BE$5 -> 0 | BF12: =BC12*$BE$5 -> 0 | BG12: =BB12*$BG$5 -> 0 | BH12: =BC12*$BG$5 -> 0 | BI12: =BB12*$BI$5 -> 0 | BJ12: =BC12*$BI$5 -> 0 | BK12: =BB12*$BK$5 -> 0 | BL12: =BC12*$BK$5 -> 0 | BM12: =$BM$5 -> 0 | BN12: =BB12*BM12 -> 0 | BO12: =BC12*BM$12 -> 0 | BP12: =$BP$5 -> 0.32 | BQ12: =BB12*$BP12 -> 0 | BR12: =BC12*BP12 -> 0 | BS12: =BB12+BE12+BG12+BI12+BK12+BN12+BQ12 -> 0 | BT12: =BC12+BF12+BH12+BJ12+BL12+BO12+BR12 -> 0 | BU12: =BT12/I12 -> #DIV/0!
B13: F1 | C13: Serramento in legno doppia anta battente apertura interna e sopraluce curvo con apertura vasistas fissato solidamente ad un controtelaio in profili di legno adeguatamente trattato e isolato. Compreso controtelaio costituito da profili in legno sagomato a L, adeguatamente trattato per evitare formazione di muffe o deformazioni geometriche, ancorato alla struttura principale mediante adeguate zanche annegate nel muro o viti di fissaggio. Vetro: 66.2 COOL-LITE 70-33#2 INDURITI / 20mm (aria-argon 90%) / 55.2 int. RICOTTI Comprese lamiere di raccordo, memebrane e isolanti. | D13: 1100 | F13: 1970 | G13: =(D13*F13)/1000000 -> 2.167 | H13: 10 | I13: =G13*H13 -> 21.67 | K13: =J13*$K$5 -> 0 | L13: =K13*$L$5 -> 0 | M13: =L13*$M$5 -> 0 | N13: =M13 -> 0 | O13: =N13*H13 -> 0 | P13: 0 | Q13: =P13*$Q$5 -> 0 | R13: 0 | S13: =R13*H13 -> 0 | T13: =$T$5 -> 650 | U13: =T13*$U$5 -> 650 | V13: =U13 -> 650 | W13: =V13*H13 -> 6500 | X13: =($X$5*2*(D13+F13))/1000 -> 135.08 | Y13: =X13*$Y$5 -> 135.08 | Z13: =Y13*$Z$5 -> 135.08 | AA13: =Z13*$AA$5 -> 135.08 | AB13: =AA13 -> 135.08 | AC13: =AB13*H13 -> 1350.8 | AD13: =$AD$5*G13 -> 32.505 | AE13: =AD13*H13 -> 325.05 | AF13: 710 | AG13: =AF13*H13 -> 7100 | AH13: 0 | AI13: =AH13*H13 -> 0 | AJ13: 0 | AK13: =AJ13*H13 -> 0 | AL13: =$AL$5 -> 60 | AM13: =AL13*H13 -> 600 | AN13: =$AN$5*G13 -> 292.545 | AO13: =AN13*H13 -> 2925.45 | AP13: 0 | AQ13: =AP13*H13 -> 0 | AR13: =($AR$5*2*(D13+F13))/1000 -> 214.9 | AS13: =AR13*H13 -> 2149 | AT13: 880 | AU13: =AT13*H13 -> 8800 | AV13: =$AV$5*G13 -> 287.1275 | AW13: =AV13*H13 -> 2871.275 | AX13: 0 | AY13: =AX13*H13 -> 0 | AZ13: =$AZ$8*G13 -> 0 | BA13: =AZ13*H13 -> 0 | BB13: =N13+R13+V13+AB13+AD13+AF13+AH13+AJ13+AL13+AN13+AP13+AR13+AT13+AV13+AX13+AZ13 -> 3262.1575 | BC13: =O13+S13+W13+AC13+AE13+AG13+AI13+AK13+AM13+AO13+AQ13+AS13+AU13+AW13+AY13+BA13 -> 32621.575 | BD13: =BC13/I13 -> 1505.3796 | BE13: =BB13*$BE$5 -> 39.14589 | BF13: =BC13*$BE$5 -> 391.4589 | BG13: =BB13*$BG$5 -> 48.932363 | BH13: =BC13*$BG$5 -> 489.32362 | BI13: =BB13*$BI$5 -> 16.310787 | BJ13: =BC13*$BI$5 -> 163.10788 | BK13: =BB13*$BK$5 -> 32.621575 | BL13: =BC13*$BK$5 -> 326.21575 | BM13: =$BM$5 -> 0 | BN13: =BB13*BM13 -> 0 | BO13: =BC13*BM$12 -> 0 | BP13: =$BP$5 -> 0.32 | BQ13: =BB13*$BP13 -> 1043.8904 | BR13: =BC13*BP13 -> 10438.904 | BS13: =BB13+BE13+BG13+BI13+BK13+BN13+BQ13 -> 4443.0585 | BT13: =BC13+BF13+BH13+BJ13+BL13+BO13+BR13 -> 44430.585 | BU13: =BT13/I13 -> 2050.327
B14: F1a | C14: Serramento in legno doppia anta battente apertura interna e sopraluce curvo con apertura vasistas fissato solidamente ad un controtelaio in profili di legno adeguatamente trattato e isolato. Compreso controtelaio costituito da profili in legno sagomato a L, adeguatamente trattato per evitare formazione di muffe o deformazioni geometriche, ancorato alla struttura principale mediante adeguate zanche annegate nel muro o viti di fissaggio. Vetro: 66.2 COOL-LITE 70-33#2 INDURITI / 20mm (aria-argon 90%) / 55.2 int. RICOTTI Comprese lamiere di raccordo, memebrane e isolanti. | D14: 1100 | F14: 1970 | G14: =(D14*F14)/1000000 -> 2.167 | H14: 1 | I14: =G14*H14 -> 2.167 | K14: =J14*$K$5 -> 0 | L14: =K14*$L$5 -> 0 | M14: =L14*$M$5 -> 0 | N14: =M14 -> 0 | O14: =N14*H14 -> 0 | P14: 0 | Q14: =P14*$Q$5 -> 0 | R14: 0 | S14: =R14*H14 -> 0 | T14: =$T$5 -> 650 | U14: =T14*$U$5 -> 650 | V14: =U14 -> 650 | W14: =V14*H14 -> 650 | X14: =($X$5*2*(D14+F14))/1000 -> 135.08 | Y14: =X14*$Y$5 -> 135.08 | Z14: =Y14*$Z$5 -> 135.08 | AA14: =Z14*$AA$5 -> 135.08 | AB14: =AA14 -> 135.08 | AC14: =AB14*H14 -> 135.08 | AD14: =$AD$5*G14 -> 32.505 | AE14: =AD14*H14 -> 32.505 | AF14: 710 | AG14: =AF14*H14 -> 710 | AH14: 0 | AI14: =AH14*H14 -> 0 | AJ14: 0 | AK14: =AJ14*H14 -> 0 | AL14: =$AL$5 -> 60 | AM14: =AL14*H14 -> 60 | AN14: =$AN$5*G14 -> 292.545 | AO14: =AN14*H14 -> 292.545 | AP14: 0 | AQ14: =AP14*H14 -> 0 | AR14: =($AR$5*2*(D14+F14))/1000 -> 214.9 | AS14: =AR14*H14 -> 214.9 | AT14: 880 | AU14: =AT14*H14 -> 880 | AV14: =$AV$5*G14 -> 287.1275 | AW14: =AV14*H14 -> 287.1275 | AX14: 0 | AY14: =AX14*H14 -> 0 | AZ14: =$AZ$8*G14 -> 0 | BA14: =AZ14*H14 -> 0 | BB14: =N14+R14+V14+AB14+AD14+AF14+AH14+AJ14+AL14+AN14+AP14+AR14+AT14+AV14+AX14+AZ14 -> 3262.1575 | BC14: =O14+S14+W14+AC14+AE14+AG14+AI14+AK14+AM14+AO14+AQ14+AS14+AU14+AW14+AY14+BA14 -> 3262.1575 | BD14: =BC14/I14 -> 1505.3796 | BE14: =BB14*$BE$5 -> 39.14589 | BF14: =BC14*$BE$5 -> 39.14589 | BG14: =BB14*$BG$5 -> 48.932363 | BH14: =BC14*$BG$5 -> 48.932363 | BI14: =BB14*$BI$5 -> 16.310787 | BJ14: =BC14*$BI$5 -> 16.310787 | BK14: =BB14*$BK$5 -> 32.621575 | BL14: =BC14*$BK$5 -> 32.621575 | BM14: =$BM$5 -> 0 | BN14: =BB14*BM14 -> 0 | BO14: =BC14*BM$12 -> 0 | BP14: =$BP$5 -> 0.32 | BQ14: =BB14*$BP14 -> 1043.8904 | BR14: =BC14*BP14 -> 1043.8904 | BS14: =BB14+BE14+BG14+BI14+BK14+BN14+BQ14 -> 4443.0585 | BT14: =BC14+BF14+BH14+BJ14+BL14+BO14+BR14 -> 4443.0585 | BU14: =BT14/I14 -> 2050.327
B15: F2 | C15: Serramento in legno doppia anta battente apertura interna e sopraluce curvo fisso. Specchiature fisse laterali e superiori, fissato solidamente ad un controtelaio in profili di legno adeguatamente trattato e isolato e persiane a lamelle fisse esterne. Compreso controtelaio costituito da profili in legno sagomato a L, adeguatamente trattato per evitare formazione di muffe o deformazioni geometriche, ancorato alla struttura principale mediante adeguate zanche annegate nel muro o viti di fissaggio. Vetro: 66.2 COOL-LITE 70-33#2 INDURITI / 20mm (aria-argon 90%) / 55.2 int. RICOTTI Comprese lamiere di raccordo, memebrane e isolanti. | D15: 1720 | F15: 3710 | G15: =(D15*F15)/1000000 -> 6.3812 | H15: 5 | I15: =G15*H15 -> 31.906 | K15: =J15*$K$5 -> 0 | L15: =K15*$L$5 -> 0 | M15: =L15*$M$5 -> 0 | N15: =M15 -> 0 | O15: =N15*H15 -> 0 | P15: 0 | Q15: =P15*$Q$5 -> 0 | R15: 0 | S15: =R15*H15 -> 0 | T15: =$T$5 -> 650 | U15: =T15*$U$5 -> 650 | V15: =U15 -> 650 | W15: =V15*H15 -> 3250 | X15: =($X$5*2*(D15+F15))/1000 -> 238.92 | Y15: =X15*$Y$5 -> 238.92 | Z15: =Y15*$Z$5 -> 238.92 | AA15: =Z15*$AA$5 -> 238.92 | AB15: =AA15 -> 238.92 | AC15: =AB15*H15 -> 1194.6 | AD15: =$AD$5*G15 -> 95.718 | AE15: =AD15*H15 -> 478.59 | AF15: 1029 | AG15: =AF15*H15 -> 5145 | AH15: 0 | AI15: =AH15*H15 -> 0 | AJ15: 0 | AK15: =AJ15*H15 -> 0 | AL15: =$AL$5 -> 60 | AM15: =AL15*H15 -> 300 | AN15: =$AN$5*G15 -> 861.462 | AO15: =AN15*H15 -> 4307.31 | AP15: 0 | AQ15: =AP15*H15 -> 0 | AR15: =($AR$5*2*(D15+F15))/1000 -> 380.1 | AS15: =AR15*H15 -> 1900.5 | AT15: =15400/5 -> 3080 | AU15: =AT15*H15 -> 15400 | AV15: =$AV$5*G15 -> 845.509 | AW15: =AV15*H15 -> 4227.545 | AX15: 0 | AY15: =AX15*H15 -> 0 | AZ15: =$AZ$8*G15 -> 0 | BA15: =AZ15*H15 -> 0 | BB15: =N15+R15+V15+AB15+AD15+AF15+AH15+AJ15+AL15+AN15+AP15+AR15+AT15+AV15+AX15+AZ15 -> 7240.709 | BC15: =O15+S15+W15+AC15+AE15+AG15+AI15+AK15+AM15+AO15+AQ15+AS15+AU15+AW15+AY15+BA15 -> 36203.545 | BD15: =BC15/I15 -> 1134.6939 | BE15: =BB15*$BE$5 -> 86.888508 | BF15: =BC15*$BE$5 -> 434.44254 | BG15: =BB15*$BG$5 -> 108.61063 | BH15: =BC15*$BG$5 -> 543.05318 | BI15: =BB15*$BI$5 -> 36.203545 | BJ15: =BC15*$BI$5 -> 181.01772 | BK15: =BB15*$BK$5 -> 72.40709 | BL15: =BC15*$BK$5 -> 362.03545 | BM15: =$BM$5 -> 0 | BN15: =BB15*BM15 -> 0 | BO15: =BC15*BM$12 -> 0 | BP15: =$BP$5 -> 0.32 | BQ15: =BB15*$BP15 -> 2317.0269 | BR15: =BC15*BP15 -> 11585.134 | BS15: =BB15+BE15+BG15+BI15+BK15+BN15+BQ15 -> 9861.8457 | BT15: =BC15+BF15+BH15+BJ15+BL15+BO15+BR15 -> 49309.228 | BU15: =BT15/I15 -> 1545.4532
A16: EI | B16: F3 - EI60 Serramento in acciaio EI60 tipo Secco EBE85 | C16: Serramento in legno fissa, serramento fissato solidamente ad un controtelaio in profili di legno adeguatamente trattato e isolato. Per questo serramento è richiesta una prestazione di resistenza all’incendio pari a EI60. SOSTITUITO CON ALLUMINIO Reynaers ConceptSystem 77-FP EI 60 (CS 77-FPEI60) Compreso controtelaio costituito da profili in legno sagomato a L, adeguatamente trattato per evitare formazione di muffe o deformazioni geometriche, ancorato alla struttura principale mediante adeguate zanche annegate nel muro o viti di fissaggio. Vetro: 66.2 COOL-LITE 70-33#2 / 14mm (aria-argon 90%) / 27 CF60-3. Comprese lamiere di raccordo, memebrane e isolanti. | D16: 1200 | F16: 3000 | G16: =(D16*F16)/1000000 -> 3.6 | H16: 3 | I16: =G16*H16 -> 10.8 | K16: =J16*$K$5 -> 0 | L16: =K16*$L$5 -> 0 | M16: =L16*$M$5 -> 0 | N16: =M16 -> 0 | O16: =N16*H16 -> 0 | P16: 0 | Q16: =P16*$Q$5 -> 0 | R16: 0 | S16: =R16*H16 -> 0 | U16: =T16*$U$5 -> 0 | V16: =U16 -> 0 | W16: =V16*H16 -> 0 | X16: =($X$5*2*(D16+F16))/1000 -> 184.8 | Y16: =X16*$Y$5 -> 184.8 | Z16: =Y16*$Z$5 -> 184.8 | AA16: =Z16*$AA$5 -> 184.8 | AB16: =AA16 -> 184.8 | AC16: =AB16*H16 -> 554.4 | AD16: =$AD$6*G16 -> 100.8 | AE16: =AD16*H16 -> 302.4 | AF16: 1650 | AG16: =AF16*H16 -> 4950 | AI16: =AH16*H16 -> 0 | AJ16: 0 | AK16: =AJ16*H16 -> 0 | AL16: 0 | AM16: =AL16*H16 -> 0 | AN16: =$AN$8*G16 -> 2142 | AO16: =AN16*H16 -> 6426 | AP16: 0 | AQ16: =AP16*H16 -> 0 | AR16: =($AR$6*2*(D16+F16))/1000 -> 378 | AS16: =AR16*H16 -> 1134 | AT16: 735 | AU16: =AT16*H16 -> 2205 | AV16: =AV8 -> 1286 | AW16: =AV16*H16 -> 3858 | AX16: 0 | AY16: =AX16*H16 -> 0 | AZ16: =$AZ$8*G16 -> 0 | BA16: =AZ16*H16 -> 0 | BB16: =N16+R16+V16+AB16+AD16+AF16+AH16+AJ16+AL16+AN16+AP16+AR16+AT16+AV16+AX16+AZ16 -> 6476.6 | BC16: =O16+S16+W16+AC16+AE16+AG16+AI16+AK16+AM16+AO16+AQ16+AS16+AU16+AW16+AY16+BA16 -> 19429.8 | BD16: =BC16/I16 -> 1799.0556 | BE16: =BB16*$BE$5 -> 77.7192 | BF16: =BC16*$BE$5 -> 233.1576 | BG16: =BB16*$BG$5 -> 97.149 | BH16: =BC16*$BG$5 -> 291.447 | BI16: =BB16*$BI$5 -> 32.383 | BJ16: =BC16*$BI$5 -> 97.149 | BK16: =BB16*$BK$5 -> 64.766 | BL16: =BC16*$BK$5 -> 194.298 | BM16: =$BM$5 -> 0 | BN16: =BB16*BM16 -> 0 | BO16: =BC16*BM$12 -> 0 | BP16: =$BP$5 -> 0.32 | BQ16: =BB16*$BP16 -> 2072.512 | BR16: =BC16*BP16 -> 6217.536 | BS16: =BB16+BE16+BG16+BI16+BK16+BN16+BQ16 -> 8821.1292 | BT16: =BC16+BF16+BH16+BJ16+BL16+BO16+BR16 -> 26463.388 | BU16: =BT16/I16 -> 2450.3137
B17: F3a | C17: Porta a doppio battente apertura interno dell’edificio con pushbar esterno e chiudiporta, presenza di sopraluce fisso è presente un ulteriore sopraluce curvo con presenza di lamelle di areazione. Il serramento presente una prestazione EI60 escluso la parte lamellata. SOSTITUITO CON ALLUMINIO Reynaers ConceptSystem 77-FP EI 60 (CS 77-FPEI60) Compreso controtelaio costituito da profili in legno sagomato a L, adeguatamente trattato per evitare formazione di muffe o deformazioni geometriche, ancorato alla struttura principale mediante adeguate zanche annegate nel muro o viti di fissaggio. Vetro: 66.2 COOL-LITE 70-33#2 / 14mm (aria-argon 90%) / 27 CF60-3. Comprese lamiere di raccordo, memebrane e isolanti. | D17: 1200 | F17: 3000 | G17: =(D17*F17)/1000000 -> 3.6 | H17: 1 | I17: =G17*H17 -> 3.6 | K17: =J17*$K$5 -> 0 | L17: =K17*$L$5 -> 0 | M17: =L17*$M$5 -> 0 | N17: =M17 -> 0 | O17: =N17*H17 -> 0 | P17: 0 | Q17: =P17*$Q$5 -> 0 | R17: 0 | S17: =R17*H17 -> 0 | T17: =$T$5 -> 650 | U17: =T17*$U$5 -> 650 | V17: =U17 -> 650 | W17: =V17*H17 -> 650 | X17: =($X$5*2*(D17+F17))/1000 -> 184.8 | Y17: =X17*$Y$5 -> 184.8 | Z17: =Y17*$Z$5 -> 184.8 | AA17: =Z17*$AA$5 -> 184.8 | AB17: =AA17 -> 184.8 | AC17: =AB17*H17 -> 184.8 | AD17: =$AD$5*G17 -> 54 | AE17: =AD17*H17 -> 54 | AF17: 938 | AG17: =AF17*H17 -> 938 | AI17: =AH17*H17 -> 0 | AJ17: 0 | AK17: =AJ17*H17 -> 0 | AL17: =$AL$5 -> 60 | AM17: =AL17*H17 -> 60 | AN17: =$AN$7*G17 -> 972 | AO17: =AN17*H17 -> 972 | AP17: 0 | AQ17: =AP17*H17 -> 0 | AR17: =($AR$5*2*(D17+F17))/1000 -> 294 | AS17: =AR17*H17 -> 294 | AT17: 935 | AU17: =AT17*H17 -> 935 | AV17: =$AV$5*G17 -> 477 | AW17: =AV17*H17 -> 477 | AX17: 0 | AY17: =AX17*H17 -> 0 | AZ17: =$AZ$8*G17 -> 0 | BA17: =AZ17*H17 -> 0 | BB17: =N17+R17+V17+AB17+AD17+AF17+AH17+AJ17+AL17+AN17+AP17+AR17+AT17+AV17+AX17+AZ17 -> 4564.8 | BC17: =O17+S17+W17+AC17+AE17+AG17+AI17+AK17+AM17+AO17+AQ17+AS17+AU17+AW17+AY17+BA17 -> 4564.8 | BD17: =BC17/I17 -> 1268 | BE17: =BB17*$BE$5 -> 54.7776 | BF17: =BC17*$BE$5 -> 54.7776 | BG17: =BB17*$BG$5 -> 68.472 | BH17: =BC17*$BG$5 -> 68.472 | BI17: =BB17*$BI$5 -> 22.824 | BJ17: =BC17*$BI$5 -> 22.824 | BK17: =BB17*$BK$5 -> 45.648 | BL17: =BC17*$BK$5 -> 45.648 | BM17: =$BM$5 -> 0 | BN17: =BB17*BM17 -> 0 | BO17: =BC17*BM$12 -> 0 | BP17: =$BP$5 -> 0.32 | BQ17: =BB17*$BP17 -> 1460.736 | BR17: =BC17*BP17 -> 1460.736 | BS17: =BB17+BE17+BG17+BI17+BK17+BN17+BQ17 -> 6217.2576 | BT17: =BC17+BF17+BH17+BJ17+BL17+BO17+BR17 -> 6217.2576 | BU17: =BT17/I17 -> 1727.016
B18: F3b | C18: Serramento con specchiature vision fisse è presente un ulteriore sopraluce curvo con presenza di lamelle di areazione. Il serramento presenta una prestazione EI60 escluso la parte lamellata.SOSTITUITO CON ALLUMINIO Reynaers ConceptSystem 77-FP EI 60 (CS 77-FPEI60) Compreso controtelaio costituito da profili in legno sagomato a L, adeguatamente trattato per evitare formazione di muffe o deformazioni geometriche, ancorato alla struttura principale mediante adeguate zanche annegate nel muro o viti di fissaggio. Vetro: 66.2 COOL-LITE 70-33#2 / 14mm (aria-argon 90%) / 27 CF60-3. Comprese lamiere di raccordo, memebrane e isolanti. | D18: 1200 | F18: 3000 | G18: =(D18*F18)/1000000 -> 3.6 | H18: 2 | I18: =G18*H18 -> 7.2 | K18: =J18*$K$5 -> 0 | L18: =K18*$L$5 -> 0 | M18: =L18*$M$5 -> 0 | N18: =M18 -> 0 | O18: =N18*H18 -> 0 | P18: 0 | Q18: =P18*$Q$5 -> 0 | R18: 0 | S18: =R18*H18 -> 0 | T18: =$T$5 -> 650 | U18: =T18*$U$5 -> 650 | V18: =U18 -> 650 | W18: =V18*H18 -> 1300 | X18: =($X$5*2*(D18+F18))/1000 -> 184.8 | Y18: =X18*$Y$5 -> 184.8 | Z18: =Y18*$Z$5 -> 184.8 | AA18: =Z18*$AA$5 -> 184.8 | AB18: =AA18 -> 184.8 | AC18: =AB18*H18 -> 369.6 | AD18: =$AD$5*G18 -> 54 | AE18: =AD18*H18 -> 108 | AF18: 938 | AG18: =AF18*H18 -> 1876 | AI18: =AH18*H18 -> 0 | AJ18: 0 | AK18: =AJ18*H18 -> 0 | AL18: =$AL$5 -> 60 | AM18: =AL18*H18 -> 120 | AN18: =$AN$7*G18 -> 972 | AO18: =AN18*H18 -> 1944 | AP18: 0 | AQ18: =AP18*H18 -> 0 | AR18: =($AR$5*2*(D18+F18))/1000 -> 294 | AS18: =AR18*H18 -> 588 | AT18: =1870/2 -> 935 | AU18: =AT18*H18 -> 1870 | AV18: =$AV$5*G18 -> 477 | AW18: =AV18*H18 -> 954 | AX18: 0 | AY18: =AX18*H18 -> 0 | AZ18: =$AZ$8*G18 -> 0 | BA18: =AZ18*H18 -> 0 | BB18: =N18+R18+V18+AB18+AD18+AF18+AH18+AJ18+AL18+AN18+AP18+AR18+AT18+AV18+AX18+AZ18 -> 4564.8 | BC18: =O18+S18+W18+AC18+AE18+AG18+AI18+AK18+AM18+AO18+AQ18+AS18+AU18+AW18+AY18+BA18 -> 9129.6 | BD18: =BC18/I18 -> 1268 | BE18: =BB18*$BE$5 -> 54.7776 | BF18: =BC18*$BE$5 -> 109.5552 | BG18: =BB18*$BG$5 -> 68.472 | BH18: =BC18*$BG$5 -> 136.944 | BI18: =BB18*$BI$5 -> 22.824 | BJ18: =BC18*$BI$5 -> 45.648 | BK18: =BB18*$BK$5 -> 45.648 | BL18: =BC18*$BK$5 -> 91.296 | BM18: =$BM$5 -> 0 | BN18: =BB18*BM18 -> 0 | BO18: =BC18*BM$12 -> 0 | BP18: =$BP$5 -> 0.32 | BQ18: =BB18*$BP18 -> 1460.736 | BR18: =BC18*BP18 -> 2921.472 | BS18: =BB18+BE18+BG18+BI18+BK18+BN18+BQ18 -> 6217.2576 | BT18: =BC18+BF18+BH18+BJ18+BL18+BO18+BR18 -> 12434.515 | BU18: =BT18/I18 -> 1727.016
B19: F4a | C19: Serramento in acciaio con volta circolare apribile a vasistas meccanizzato e automatico specchiatura inferiore con porta a doppio battente apertura esterna, sopraluce rettangolare fisso. SOSTITUITO CON ALLUMINIO Reynaers ConceptSystem 77-FP EI 60 (CS 77-FPEI60) Controtelaio composto da tubi rettangolari ancorato alla struttura principale mediante adeguate zanche annegate nel muro o viti di fissaggio, il telaio deve essere correttamente isolato e zincato per proteggerlo dalla corrosione. Vetro: 66.2 COOL-LITE 70-33#2 / 14mm (aria-argon 90%) / 27 CF60-3. Comprese lamiere di raccordo, memebrane e isolanti. | D19: 1300 | F19: 3000 | G19: =(D19*F19)/1000000 -> 3.9 | H19: 1 | I19: =G19*H19 -> 3.9 | K19: =J19*$K$5 -> 0 | L19: =K19*$L$5 -> 0 | M19: =L19*$M$5 -> 0 | N19: =M19 -> 0 | O19: =N19*H19 -> 0 | P19: 0 | Q19: =P19*$Q$5 -> 0 | R19: 0 | S19: =R19*H19 -> 0 | T19: =$T$5 -> 650 | U19: =T19*$U$5 -> 650 | V19: =U19 -> 650 | W19: =V19*H19 -> 650 | X19: =($X$5*2*(D19+F19))/1000 -> 189.2 | Y19: =X19*$Y$5 -> 189.2 | Z19: =Y19*$Z$5 -> 189.2 | AA19: =Z19*$AA$5 -> 189.2 | AB19: =AA19 -> 189.2 | AC19: =AB19*H19 -> 189.2 | AD19: =$AD$5*G19 -> 58.5 | AE19: =AD19*H19 -> 58.5 | AF19: 1450 | AG19: =AF19*H19 -> 1450 | AI19: =AH19*H19 -> 0 | AJ19: 0 | AK19: =AJ19*H19 -> 0 | AL19: =$AL$5 -> 60 | AM19: =AL19*H19 -> 60 | AN19: =$AN$7*G19 -> 1053 | AO19: =AN19*H19 -> 1053 | AP19: 0 | AQ19: =AP19*H19 -> 0 | AR19: =($AR$5*2*(D19+F19))/1000 -> 301 | AS19: =AR19*H19 -> 301 | AT19: 0 | AU19: =AT19*H19 -> 0 | AV19: =$AV$5*G19 -> 516.75 | AW19: =AV19*H19 -> 516.75 | AX19: 0 | AY19: =AX19*H19 -> 0 | AZ19: =$AZ$8*G19 -> 0 | BA19: =AZ19*H19 -> 0 | BB19: =N19+R19+V19+AB19+AD19+AF19+AH19+AJ19+AL19+AN19+AP19+AR19+AT19+AV19+AX19+AZ19 -> 4278.45 | BC19: =O19+S19+W19+AC19+AE19+AG19+AI19+AK19+AM19+AO19+AQ19+AS19+AU19+AW19+AY19+BA19 -> 4278.45 | BD19: =BC19/I19 -> 1097.0385 | BE19: =BB19*$BE$5 -> 51.3414 | BF19: =BC19*$BE$5 -> 51.3414 | BG19: =BB19*$BG$5 -> 64.17675 | BH19: =BC19*$BG$5 -> 64.17675 | BI19: =BB19*$BI$5 -> 21.39225 | BJ19: =BC19*$BI$5 -> 21.39225 | BK19: =BB19*$BK$5 -> 42.7845 | BL19: =BC19*$BK$5 -> 42.7845 | BM19: =$BM$5 -> 0 | BN19: =BB19*BM19 -> 0 | BO19: =BC19*BM$12 -> 0 | BP19: =$BP$5 -> 0.32 | BQ19: =BB19*$BP19 -> 1369.104 | BR19: =BC19*BP19 -> 1369.104 | BS19: =BB19+BE19+BG19+BI19+BK19+BN19+BQ19 -> 5827.2489 | BT19: =BC19+BF19+BH19+BJ19+BL19+BO19+BR19 -> 5827.2489 | BU19: =BT19/I19 -> 1494.1664
B20: F4b | C20: Porta a doppio battente vetrata, apertura doppia anta verso l’esterno, sopraluce fisso. Compreso controtelaio costituito da profili in legno sagomato a L, adeguatamente trattato per evitare formazione di muffe o deformazioni geometriche, ancorato alla struttura principale mediante adeguate zanche annegate nel muro o viti di fissaggio. Vetro: 66.2 COOL-LITE 70-33#2 INDURITI / 20mm (aria-argon 90%) / 55.2 int. RICOTTI Comprese lamiere di raccordo, memebrane e isolanti. | D20: 1300 | F20: 3000 | G20: =(D20*F20)/1000000 -> 3.9 | H20: 1 | I20: =G20*H20 -> 3.9 | K20: =J20*$K$5 -> 0 | L20: =K20*$L$5 -> 0 | M20: =L20*$M$5 -> 0 | N20: =M20 -> 0 | O20: =N20*H20 -> 0 | P20: 0 | Q20: =P20*$Q$5 -> 0 | R20: 0 | S20: =R20*H20 -> 0 | T20: =$T$5 -> 650 | U20: =T20*$U$5 -> 650 | V20: =U20 -> 650 | W20: =V20*H20 -> 650 | X20: =($X$5*2*(D20+F20))/1000 -> 189.2 | Y20: =X20*$Y$5 -> 189.2 | Z20: =Y20*$Z$5 -> 189.2 | AA20: =Z20*$AA$5 -> 189.2 | AB20: =AA20 -> 189.2 | AC20: =AB20*H20 -> 189.2 | AD20: =$AD$5*G20 -> 58.5 | AE20: =AD20*H20 -> 58.5 | AF20: 1420 | AG20: =AF20*H20 -> 1420 | AI20: =AH20*H20 -> 0 | AJ20: 0 | AK20: =AJ20*H20 -> 0 | AL20: =$AL$5 -> 60 | AM20: =AL20*H20 -> 60 | AN20: =$AN$7*G20 -> 1053 | AO20: =AN20*H20 -> 1053 | AP20: 0 | AQ20: =AP20*H20 -> 0 | AR20: =($AR$5*2*(D20+F20))/1000 -> 301 | AS20: =AR20*H20 -> 301 | AT20: 1650 | AU20: =AT20*H20 -> 1650 | AV20: =$AV$5*G20 -> 516.75 | AW20: =AV20*H20 -> 516.75 | AX20: 0 | AY20: =AX20*H20 -> 0 | AZ20: =$AZ$8*G20 -> 0 | BA20: =AZ20*H20 -> 0 | BB20: =N20+R20+V20+AB20+AD20+AF20+AH20+AJ20+AL20+AN20+AP20+AR20+AT20+AV20+AX20+AZ20 -> 5898.45 | BC20: =O20+S20+W20+AC20+AE20+AG20+AI20+AK20+AM20+AO20+AQ20+AS20+AU20+AW20+AY20+BA20 -> 5898.45 | BD20: =BC20/I20 -> 1512.4231 | BE20: =BB20*$BE$5 -> 70.7814 | BF20: =BC20*$BE$5 -> 70.7814 | BG20: =BB20*$BG$5 -> 88.47675 | BH20: =BC20*$BG$5 -> 88.47675 | BI20: =BB20*$BI$5 -> 29.49225 | BJ20: =BC20*$BI$5 -> 29.49225 | BK20: =BB20*$BK$5 -> 58.9845 | BL20: =BC20*$BK$5 -> 58.9845 | BM20: =$BM$5 -> 0 | BN20: =BB20*BM20 -> 0 | BO20: =BC20*BM$12 -> 0 | BP20: =$BP$5 -> 0.32 | BQ20: =BB20*$BP20 -> 1887.504 | BR20: =BC20*BP20 -> 1887.504 | BS20: =BB20+BE20+BG20+BI20+BK20+BN20+BQ20 -> 8033.6889 | BT20: =BC20+BF20+BH20+BJ20+BL20+BO20+BR20 -> 8033.6889 | BU20: =BT20/I20 -> 2059.9202
A21: EI | B21: F5a - EI60 Serramento in acciaio EI60 tipo Secco EBE85 | C21: Porta a doppio battente apertura interno dell’edificio con pushbar esterno e chiudiporta, presenza di sopraluce fisso è presente un ulteriore sopraluce curvo con presenza di lamelle di areazione. Il serramento presente una prestazione EI60 escluso la parte lamellata. SOSTITUITO CON ALLUMINIO Reynaers ConceptSystem 77-FP EI 60 (CS 77-FPEI60) Compreso controtelaio costituito da profili in legno sagomato a L, adeguatamente trattato per evitare formazione di muffe o deformazioni geometriche, ancorato alla struttura principale mediante adeguate zanche annegate nel muro o viti di fissaggio. Vetro: 66.2 COOL-LITE 70-33#2 / 14mm (aria-argon 90%) / 27 CF60-3. Comprese lamiere di raccordo, memebrane e isolanti. | D21: 1600 | F21: 3530 | G21: =(D21*F21)/1000000 -> 5.648 | H21: 1 | I21: =G21*H21 -> 5.648 | K21: =J21*$K$5 -> 0 | L21: =K21*$L$5 -> 0 | M21: =L21*$M$5 -> 0 | N21: =M21 -> 0 | O21: =N21*H21 -> 0 | P21: 0 | Q21: =P21*$Q$5 -> 0 | R21: 0 | S21: =R21*H21 -> 0 | T21: =$T$6 -> 1930 | U21: =T21*$U$5 -> 1930 | V21: =U21 -> 1930 | W21: =V21*H21 -> 1930 | X21: =($X$5*2*(D21+F21))/1000 -> 225.72 | Y21: =X21*$Y$5 -> 225.72 | Z21: =Y21*$Z$5 -> 225.72 | AA21: =Z21*$AA$5 -> 225.72 | AB21: =AA21 -> 225.72 | AC21: =AB21*H21 -> 225.72 | AD21: =$AD$6*G21 -> 158.144 | AE21: =AD21*H21 -> 158.144 | AF21: =3438+748 -> 4186 | AG21: =AF21*H21 -> 4186 | AI21: =AH21*H21 -> 0 | AJ21: 0 | AK21: =AJ21*H21 -> 0 | AL21: =$AL$5 -> 60 | AM21: =AL21*H21 -> 60 | AN21: =$AN$8*G21 -> 3360.56 | AO21: =AN21*H21 -> 3360.56 | AP21: 0 | AQ21: =AP21*H21 -> 0 | AR21: =($AR$6*2*(D21+F21))/1000 -> 461.7 | AS21: =AR21*H21 -> 461.7 | AT21: 3025 | AU21: =AT21*H21 -> 3025 | AV21: =$AV$8 -> 1286 | AW21: =AV21*H21 -> 1286 | AX21: 0 | AY21: =AX21*H21 -> 0 | AZ21: =$AZ$8*G21 -> 0 | BA21: =AZ21*H21 -> 0 | BB21: =N21+R21+V21+AB21+AD21+AF21+AH21+AJ21+AL21+AN21+AP21+AR21+AT21+AV21+AX21+AZ21 -> 14693.124 | BC21: =O21+S21+W21+AC21+AE21+AG21+AI21+AK21+AM21+AO21+AQ21+AS21+AU21+AW21+AY21+BA21 -> 14693.124 | BD21: =BC21/I21 -> 2601.4738 | BE21: =BB21*$BE$5 -> 176.31749 | BF21: =BC21*$BE$5 -> 176.31749 | BG21: =BB21*$BG$5 -> 220.39686 | BH21: =BC21*$BG$5 -> 220.39686 | BI21: =BB21*$BI$5 -> 73.46562 | BJ21: =BC21*$BI$5 -> 73.46562 | BK21: =BB21*$BK$5 -> 146.93124 | BL21: =BC21*$BK$5 -> 146.93124 | BM21: =$BM$5 -> 0 | BN21: =BB21*BM21 -> 0 | BO21: =BC21*BM$12 -> 0 | BP21: =$BP$5 -> 0.32 | BQ21: =BB21*$BP21 -> 4701.7997 | BR21: =BC21*BP21 -> 4701.7997 | BS21: =BB21+BE21+BG21+BI21+BK21+BN21+BQ21 -> 20012.035 | BT21: =BC21+BF21+BH21+BJ21+BL21+BO21+BR21 -> 20012.035 | BU21: =BT21/I21 -> 3543.2073
A22: EI | B22: F5b - EI60 Serramento in acciaio EI60 tipo Secco EBE85 | C22: Serramento con specchiature vision fisse è presente un ulteriore sopraluce curvo con presenza di lamelle di areazione. Il serramento presenta una prestazione EI60 escluso la parte lamellata.SOSTITUITO CON ALLUMINIO Reynaers ConceptSystem 77-FP EI 60 (CS 77-FPEI60) Compreso controtelaio costituito da profili in legno sagomato a L, adeguatamente trattato per evitare formazione di muffe o deformazioni geometriche, ancorato alla struttura principale mediante adeguate zanche annegate nel muro o viti di fissaggio. Vetro: 66.2 COOL-LITE 70-33#2 / 14mm (aria-argon 90%) / 27 CF60-3. Comprese lamiere di raccordo, memebrane e isolanti. | D22: 1600 | F22: 3530 | G22: =(D22*F22)/1000000 -> 5.648 | H22: 1 | I22: =G22*H22 -> 5.648 | K22: =J22*$K$5 -> 0 | L22: =K22*$L$5 -> 0 | M22: =L22*$M$5 -> 0 | N22: =M22 -> 0 | O22: =N22*H22 -> 0 | P22: 0 | Q22: =P22*$Q$5 -> 0 | R22: 0 | S22: =R22*H22 -> 0 | T22: 0 | U22: =T22*$U$5 -> 0 | V22: =U22 -> 0 | W22: =V22*H22 -> 0 | X22: =($X$5*2*(D22+F22))/1000 -> 225.72 | Y22: =X22*$Y$5 -> 225.72 | Z22: =Y22*$Z$5 -> 225.72 | AA22: =Z22*$AA$5 -> 225.72 | AB22: =AA22 -> 225.72 | AC22: =AB22*H22 -> 225.72 | AD22: =$AD$6*G22 -> 158.144 | AE22: =AD22*H22 -> 158.144 | AF22: =1671+1520+818 -> 4009 | AG22: =AF22*H22 -> 4009 | AI22: =AH22*H22 -> 0 | AJ22: 0 | AK22: =AJ22*H22 -> 0 | AL22: =$AL$5 -> 60 | AM22: =AL22*H22 -> 60 | AN22: =$AN$8*G22 -> 3360.56 | AO22: =AN22*H22 -> 3360.56 | AP22: 0 | AQ22: =AP22*H22 -> 0 | AR22: =($AR$6*2*(D22+F22))/1000 -> 461.7 | AS22: =AR22*H22 -> 461.7 | AT22: 2035 | AU22: =AT22*H22 -> 2035 | AV22: =$AV$8 -> 1286 | AW22: =AV22*H22 -> 1286 | AX22: 0 | AY22: =AX22*H22 -> 0 | AZ22: =$AZ$8*G22 -> 0 | BA22: =AZ22*H22 -> 0 | BB22: =N22+R22+V22+AB22+AD22+AF22+AH22+AJ22+AL22+AN22+AP22+AR22+AT22+AV22+AX22+AZ22 -> 11596.124 | BC22: =O22+S22+W22+AC22+AE22+AG22+AI22+AK22+AM22+AO22+AQ22+AS22+AU22+AW22+AY22+BA22 -> 11596.124 | BD22: =BC22/I22 -> 2053.1381 | BE22: =BB22*$BE$5 -> 139.15349 | BF22: =BC22*$BE$5 -> 139.15349 | BG22: =BB22*$BG$5 -> 173.94186 | BH22: =BC22*$BG$5 -> 173.94186 | BI22: =BB22*$BI$5 -> 57.98062 | BJ22: =BC22*$BI$5 -> 57.98062 | BK22: =BB22*$BK$5 -> 115.96124 | BL22: =BC22*$BK$5 -> 115.96124 | BM22: =$BM$5 -> 0 | BN22: =BB22*BM22 -> 0 | BO22: =BC22*BM$12 -> 0 | BP22: =$BP$5 -> 0.32 | BQ22: =BB22*$BP22 -> 3710.7597 | BR22: =BC22*BP22 -> 3710.7597 | BS22: =BB22+BE22+BG22+BI22+BK22+BN22+BQ22 -> 15793.921 | BT22: =BC22+BF22+BH22+BJ22+BL22+BO22+BR22 -> 15793.921 | BU22: =BT22/I22 -> 2796.3741
B23: F6 | C23: Serramento portafinestra in legno doppia anta battente apertura interna fissato solidamente ad un controtelaio in profili di legno adeguatamente trattato e isolato. Compreso controtelaio costituito da profili in legno sagomato a L, adeguatamente trattato per evitare formazione di muffe o deformazioni geometriche, ancorato alla struttura principale mediante adeguate zanche annegate nel muro o viti di fissaggio. Vetro: 66.2 COOL-LITE 70-33#2 INDURITI / 20mm (aria-argon 90%) / 55.2 int. RICOTTI Comprese lamiere di raccordo, memebrane e isolanti. | D23: 1300 | F23: 2950 | G23: =(D23*F23)/1000000 -> 3.835 | H23: 11 | I23: =G23*H23 -> 42.185 | K23: =J23*$K$5 -> 0 | L23: =K23*$L$5 -> 0 | M23: =L23*$M$5 -> 0 | N23: =M23 -> 0 | O23: =N23*H23 -> 0 | P23: 0 | Q23: =P23*$Q$5 -> 0 | R23: 0 | S23: =R23*H23 -> 0 | T23: =$T$5 -> 650 | U23: =T23*$U$5 -> 650 | V23: =U23 -> 650 | W23: =V23*H23 -> 7150 | X23: =($X$5*2*(D23+F23))/1000 -> 187 | Y23: =X23*$Y$5 -> 187 | Z23: =Y23*$Z$5 -> 187 | AA23: =Z23*$AA$5 -> 187 | AB23: =AA23 -> 187 | AC23: =AB23*H23 -> 2057 | AD23: =$AD$5*G23 -> 57.525 | AE23: =AD23*H23 -> 632.775 | AF23: 934 | AG23: =AF23*H23 -> 10274 | AI23: =AH23*H23 -> 0 | AJ23: 0 | AK23: =AJ23*H23 -> 0 | AL23: =$AL$5 -> 60 | AM23: =AL23*H23 -> 660 | AN23: =$AN$7*G23 -> 1035.45 | AO23: =AN23*H23 -> 11389.95 | AP23: 0 | AQ23: =AP23*H23 -> 0 | AR23: =($AR$5*2*(D23+F23))/1000 -> 297.5 | AS23: =AR23*H23 -> 3272.5 | AT23: =10285/10 -> 1028.5 | AU23: =AT23*H23 -> 11313.5 | AV23: =$AV$5*G23 -> 508.1375 | AW23: =AV23*H23 -> 5589.5125 | AX23: 0 | AY23: =AX23*H23 -> 0 | AZ23: =$AZ$8*G23 -> 0 | BA23: =AZ23*H23 -> 0 | BB23: =N23+R23+V23+AB23+AD23+AF23+AH23+AJ23+AL23+AN23+AP23+AR23+AT23+AV23+AX23+AZ23 -> 4758.1125 | BC23: =O23+S23+W23+AC23+AE23+AG23+AI23+AK23+AM23+AO23+AQ23+AS23+AU23+AW23+AY23+BA23 -> 52339.238 | BD23: =BC23/I23 -> 1240.7073 | BE23: =BB23*$BE$5 -> 57.09735 | BF23: =BC23*$BE$5 -> 628.07085 | BG23: =BB23*$BG$5 -> 71.371687 | BH23: =BC23*$BG$5 -> 785.08856 | BI23: =BB23*$BI$5 -> 23.790563 | BJ23: =BC23*$BI$5 -> 261.69619 | BK23: =BB23*$BK$5 -> 47.581125 | BL23: =BC23*$BK$5 -> 523.39238 | BM23: =$BM$5 -> 0 | BN23: =BB23*BM23 -> 0 | BO23: =BC23*BM$12 -> 0 | BP23: =$BP$5 -> 0.32 | BQ23: =BB23*$BP23 -> 1522.596 | BR23: =BC23*BP23 -> 16748.556 | BS23: =BB23+BE23+BG23+BI23+BK23+BN23+BQ23 -> 6480.5492 | BT23: =BC23+BF23+BH23+BJ23+BL23+BO23+BR23 -> 71286.041 | BU23: =BT23/I23 -> 1689.8433
B24: F6a | C24: Serramento portafinestra in legno doppia anta battente apertura interna fissato solidamente ad un controtelaio in profili di legno adeguatamente trattato e isolato. SERRAMENTO A TENUTA FUMI. Compreso controtelaio costituito da profili in legno sagomato a L, adeguatamente trattato per evitare formazione di muffe o deformazioni geometriche, ancorato alla struttura principale mediante adeguate zanche annegate nel muro o viti di fissaggio. Vetro: 66.2 COOL-LITE 70-33#2 INDURITI / 20mm (aria-argon 90%) / 55.2 int. RICOTTI Comprese lamiere di raccordo, memebrane e isolanti. | D24: 1300 | F24: 2950 | G24: =(D24*F24)/1000000 -> 3.835 | H24: 3 | I24: =G24*H24 -> 11.505 | K24: =J24*$K$5 -> 0 | L24: =K24*$L$5 -> 0 | M24: =L24*$M$5 -> 0 | N24: =M24 -> 0 | O24: =N24*H24 -> 0 | P24: 0 | Q24: =P24*$Q$5 -> 0 | R24: 0 | S24: =R24*H24 -> 0 | T24: =$T$5 -> 650 | U24: =T24*$U$5 -> 650 | V24: =U24 -> 650 | W24: =V24*H24 -> 1950 | X24: =($X$5*2*(D24+F24))/1000 -> 187 | Y24: =X24*$Y$5 -> 187 | Z24: =Y24*$Z$5 -> 187 | AA24: =Z24*$AA$5 -> 187 | AB24: =AA24 -> 187 | AC24: =AB24*H24 -> 561 | AD24: =$AD$5*G24 -> 57.525 | AE24: =AD24*H24 -> 172.575 | AF24: 934 | AG24: =AF24*H24 -> 2802 | AI24: =AH24*H24 -> 0 | AJ24: 0 | AK24: =AJ24*H24 -> 0 | AL24: =$AL$5 -> 60 | AM24: =AL24*H24 -> 180 | AN24: =$AN$7*G24 -> 1035.45 | AO24: =AN24*H24 -> 3106.35 | AP24: 0 | AQ24: =AP24*H24 -> 0 | AR24: =($AR$5*2*(D24+F24))/1000 -> 297.5 | AS24: =AR24*H24 -> 892.5 | AT24: =2805/3 -> 935 | AU24: =AT24*H24 -> 2805 | AV24: =$AV$5*G24 -> 508.1375 | AW24: =AV24*H24 -> 1524.4125 | AX24: 0 | AY24: =AX24*H24 -> 0 | AZ24: =$AZ$8*G24 -> 0 | BA24: =AZ24*H24 -> 0 | BB24: =N24+R24+V24+AB24+AD24+AF24+AH24+AJ24+AL24+AN24+AP24+AR24+AT24+AV24+AX24+AZ24 -> 4664.6125 | BC24: =O24+S24+W24+AC24+AE24+AG24+AI24+AK24+AM24+AO24+AQ24+AS24+AU24+AW24+AY24+BA24 -> 13993.837 | BD24: =BC24/I24 -> 1216.3266 | BE24: =BB24*$BE$5 -> 55.97535 | BF24: =BC24*$BE$5 -> 167.92605 | BG24: =BB24*$BG$5 -> 69.969188 | BH24: =BC24*$BG$5 -> 209.90756 | BI24: =BB24*$BI$5 -> 23.323063 | BJ24: =BC24*$BI$5 -> 69.969188 | BK24: =BB24*$BK$5 -> 46.646125 | BL24: =BC24*$BK$5 -> 139.93838 | BM24: =$BM$5 -> 0 | BN24: =BB24*BM24 -> 0 | BO24: =BC24*BM$12 -> 0 | BP24: =$BP$5 -> 0.32 | BQ24: =BB24*$BP24 -> 1492.676 | BR24: =BC24*BP24 -> 4478.028 | BS24: =BB24+BE24+BG24+BI24+BK24+BN24+BQ24 -> 6353.2022 | BT24: =BC24+BF24+BH24+BJ24+BL24+BO24+BR24 -> 19059.607 | BU24: =BT24/I24 -> 1656.6368
B25: F6b | C25: Serramento portafinestra in legno doppia anta battente apertura esterna fissato solidamente ad un controtelaio in profili di legno adeguatamente trattato e isolato. SERRAMENTO A TENUTA FUMI. Compreso controtelaio costituito da profili in legno sagomato a L, adeguatamente trattato per evitare formazione di muffe o deformazioni geometriche, ancorato alla struttura principale mediante adeguate zanche annegate nel muro o viti di fissaggio. Vetro: 66.2 COOL-LITE 70-33#2 INDURITI / 20mm (aria-argon 90%) / 55.2 int. RICOTTI Comprese lamiere di raccordo, memebrane e isolanti. | D25: 1300 | F25: 2950 | G25: =(D25*F25)/1000000 -> 3.835 | H25: 1 | I25: =G25*H25 -> 3.835 | K25: =J25*$K$5 -> 0 | L25: =K25*$L$5 -> 0 | M25: =L25*$M$5 -> 0 | N25: =M25 -> 0 | O25: =N25*H25 -> 0 | P25: 0 | Q25: =P25*$Q$5 -> 0 | R25: 0 | S25: =R25*H25 -> 0 | T25: =$T$5 -> 650 | U25: =T25*$U$5 -> 650 | V25: =U25 -> 650 | W25: =V25*H25 -> 650 | X25: =($X$5*2*(D25+F25))/1000 -> 187 | Y25: =X25*$Y$5 -> 187 | Z25: =Y25*$Z$5 -> 187 | AA25: =Z25*$AA$5 -> 187 | AB25: =AA25 -> 187 | AC25: =AB25*H25 -> 187 | AD25: =$AD$5*G25 -> 57.525 | AE25: =AD25*H25 -> 57.525 | AF25: 934 | AG25: =AF25*H25 -> 934 | AI25: =AH25*H25 -> 0 | AJ25: 0 | AK25: =AJ25*H25 -> 0 | AL25: =$AL$5 -> 60 | AM25: =AL25*H25 -> 60 | AN25: =$AN$7*G25 -> 1035.45 | AO25: =AN25*H25 -> 1035.45 | AP25: 0 | AQ25: =AP25*H25 -> 0 | AR25: =($AR$5*2*(D25+F25))/1000 -> 297.5 | AS25: =AR25*H25 -> 297.5 | AT25: 935 | AU25: =AT25*H25 -> 935 | AV25: =$AV$5*G25 -> 508.1375 | AW25: =AV25*H25 -> 508.1375 | AX25: 0 | AY25: =AX25*H25 -> 0 | AZ25: =$AZ$8*G25 -> 0 | BA25: =AZ25*H25 -> 0 | BB25: =N25+R25+V25+AB25+AD25+AF25+AH25+AJ25+AL25+AN25+AP25+AR25+AT25+AV25+AX25+AZ25 -> 4664.6125 | BC25: =O25+S25+W25+AC25+AE25+AG25+AI25+AK25+AM25+AO25+AQ25+AS25+AU25+AW25+AY25+BA25 -> 4664.6125 | BD25: =BC25/I25 -> 1216.3266 | BE25: =BB25*$BE$5 -> 55.97535 | BF25: =BC25*$BE$5 -> 55.97535 | BG25: =BB25*$BG$5 -> 69.969188 | BH25: =BC25*$BG$5 -> 69.969188 | BI25: =BB25*$BI$5 -> 23.323063 | BJ25: =BC25*$BI$5 -> 23.323063 | BK25: =BB25*$BK$5 -> 46.646125 | BL25: =BC25*$BK$5 -> 46.646125 | BM25: =$BM$5 -> 0 | BN25: =BB25*BM25 -> 0 | BO25: =BC25*BM$12 -> 0 | BP25: =$BP$5 -> 0.32 | BQ25: =BB25*$BP25 -> 1492.676 | BR25: =BC25*BP25 -> 1492.676 | BS25: =BB25+BE25+BG25+BI25+BK25+BN25+BQ25 -> 6353.2022 | BT25: =BC25+BF25+BH25+BJ25+BL25+BO25+BR25 -> 6353.2022 | BU25: =BT25/I25 -> 1656.6368
B26: F7 | C26: Serramento finestra in legno doppia anta battente apertura interna fissato solidamente ad un controtelaio in profili di legno adeguatamente trattato e isolato. Compreso controtelaio costituito da profili in legno sagomato a L, adeguatamente trattato per evitare formazione di muffe o deformazioni geometriche, ancorato alla struttura principale mediante adeguate zanche annegate nel muro o viti di fissaggio. Vetro: 66.2 COOL-LITE 70-33#2 INDURITI / 20mm (aria-argon 90%) / 55.2 int. RICOTTI Comprese lamiere di raccordo, memebrane e isolanti. | D26: 1200 | F26: 1420 | G26: =(D26*F26)/1000000 -> 1.704 | H26: 3 | I26: =G26*H26 -> 5.112 | K26: =J26*$K$5 -> 0 | L26: =K26*$L$5 -> 0 | M26: =L26*$M$5 -> 0 | N26: =M26 -> 0 | O26: =N26*H26 -> 0 | P26: 0 | Q26: =P26*$Q$5 -> 0 | R26: 0 | S26: =R26*H26 -> 0 | T26: =$T$5 -> 650 | U26: =T26*$U$5 -> 650 | V26: =U26 -> 650 | W26: =V26*H26 -> 1950 | X26: =($X$5*2*(D26+F26))/1000 -> 115.28 | Y26: =X26*$Y$5 -> 115.28 | Z26: =Y26*$Z$5 -> 115.28 | AA26: =Z26*$AA$5 -> 115.28 | AB26: =AA26 -> 115.28 | AC26: =AB26*H26 -> 345.84 | AD26: =$AD$5*G26 -> 25.56 | AE26: =AD26*H26 -> 76.68 | AF26: 576 | AG26: =AF26*H26 -> 1728 | AI26: =AH26*H26 -> 0 | AJ26: 0 | AK26: =AJ26*H26 -> 0 | AL26: =$AL$5 -> 60 | AM26: =AL26*H26 -> 180 | AN26: =$AN$7*G26 -> 460.08 | AO26: =AN26*H26 -> 1380.24 | AP26: 0 | AQ26: =AP26*H26 -> 0 | AR26: =($AR$5*2*(D26+F26))/1000 -> 183.4 | AS26: =AR26*H26 -> 550.2 | AT26: =2475/3 -> 825 | AU26: =AT26*H26 -> 2475 | AV26: =$AV$5*G26 -> 225.78 | AW26: =AV26*H26 -> 677.34 | AX26: 0 | AY26: =AX26*H26 -> 0 | AZ26: =$AZ$8*G26 -> 0 | BA26: =AZ26*H26 -> 0 | BB26: =N26+R26+V26+AB26+AD26+AF26+AH26+AJ26+AL26+AN26+AP26+AR26+AT26+AV26+AX26+AZ26 -> 3121.1 | BC26: =O26+S26+W26+AC26+AE26+AG26+AI26+AK26+AM26+AO26+AQ26+AS26+AU26+AW26+AY26+BA26 -> 9363.3 | BD26: =BC26/I26 -> 1831.6315 | BE26: =BB26*$BE$5 -> 37.4532 | BF26: =BC26*$BE$5 -> 112.3596 | BG26: =BB26*$BG$5 -> 46.8165 | BH26: =BC26*$BG$5 -> 140.4495 | BI26: =BB26*$BI$5 -> 15.6055 | BJ26: =BC26*$BI$5 -> 46.8165 | BK26: =BB26*$BK$5 -> 31.211 | BL26: =BC26*$BK$5 -> 93.633 | BM26: =$BM$5 -> 0 | BN26: =BB26*BM26 -> 0 | BO26: =BC26*BM$12 -> 0 | BP26: =$BP$5 -> 0.32 | BQ26: =BB26*$BP26 -> 998.752 | BR26: =BC26*BP26 -> 2996.256 | BS26: =BB26+BE26+BG26+BI26+BK26+BN26+BQ26 -> 4250.9382 | BT26: =BC26+BF26+BH26+BJ26+BL26+BO26+BR26 -> 12752.815 | BU26: =BT26/I26 -> 2494.682
B27: F7a | C27: Serramento finestra in legno doppia anta battente apertura interna fissato solidamente ad un controtelaio in profili di legno adeguatamente trattato e isolato. Compreso controtelaio costituito da profili in legno sagomato a L, adeguatamente trattato per evitare formazione di muffe o deformazioni geometriche, ancorato alla struttura principale mediante adeguate zanche annegate nel muro o viti di fissaggio. Vetro: 66.2 COOL-LITE 70-33#2 INDURITI / 20mm (aria-argon 90%) / 55.2 int. RICOTTI Comprese lamiere di raccordo, memebrane e isolanti. | D27: 1200 | F27: 1420 | G27: =(D27*F27)/1000000 -> 1.704 | H27: 2 | I27: =G27*H27 -> 3.408 | K27: =J27*$K$5 -> 0 | L27: =K27*$L$5 -> 0 | M27: =L27*$M$5 -> 0 | N27: =M27 -> 0 | O27: =N27*H27 -> 0 | P27: 0 | Q27: =P27*$Q$5 -> 0 | R27: 0 | S27: =R27*H27 -> 0 | T27: =$T$5 -> 650 | U27: =T27*$U$5 -> 650 | V27: =U27 -> 650 | W27: =V27*H27 -> 1300 | X27: =($X$5*2*(D27+F27))/1000 -> 115.28 | Y27: =X27*$Y$5 -> 115.28 | Z27: =Y27*$Z$5 -> 115.28 | AA27: =Z27*$AA$5 -> 115.28 | AB27: =AA27 -> 115.28 | AC27: =AB27*H27 -> 230.56 | AD27: =$AD$5*G27 -> 25.56 | AE27: =AD27*H27 -> 51.12 | AF27: 576 | AG27: =AF27*H27 -> 1152 | AI27: =AH27*H27 -> 0 | AJ27: 0 | AK27: =AJ27*H27 -> 0 | AL27: =$AL$5 -> 60 | AM27: =AL27*H27 -> 120 | AN27: =$AN$7*G27 -> 460.08 | AO27: =AN27*H27 -> 920.16 | AP27: 0 | AQ27: =AP27*H27 -> 0 | AR27: =($AR$5*2*(D27+F27))/1000 -> 183.4 | AS27: =AR27*H27 -> 366.8 | AT27: =1650/2 -> 825 | AU27: =AT27*H27 -> 1650 | AV27: =$AV$5*G27 -> 225.78 | AW27: =AV27*H27 -> 451.56 | AX27: 0 | AY27: =AX27*H27 -> 0 | AZ27: =$AZ$8*G27 -> 0 | BA27: =AZ27*H27 -> 0 | BB27: =N27+R27+V27+AB27+AD27+AF27+AH27+AJ27+AL27+AN27+AP27+AR27+AT27+AV27+AX27+AZ27 -> 3121.1 | BC27: =O27+S27+W27+AC27+AE27+AG27+AI27+AK27+AM27+AO27+AQ27+AS27+AU27+AW27+AY27+BA27 -> 6242.2 | BD27: =BC27/I27 -> 1831.6315 | BE27: =BB27*$BE$5 -> 37.4532 | BF27: =BC27*$BE$5 -> 74.9064 | BG27: =BB27*$BG$5 -> 46.8165 | BH27: =BC27*$BG$5 -> 93.633 | BI27: =BB27*$BI$5 -> 15.6055 | BJ27: =BC27*$BI$5 -> 31.211 | BK27: =BB27*$BK$5 -> 31.211 | BL27: =BC27*$BK$5 -> 62.422 | BM27: =$BM$5 -> 0 | BN27: =BB27*BM27 -> 0 | BO27: =BC27*BM$12 -> 0 | BP27: =$BP$5 -> 0.32 | BQ27: =BB27*$BP27 -> 998.752 | BR27: =BC27*BP27 -> 1997.504 | BS27: =BB27+BE27+BG27+BI27+BK27+BN27+BQ27 -> 4250.9382 | BT27: =BC27+BF27+BH27+BJ27+BL27+BO27+BR27 -> 8501.8764 | BU27: =BT27/I27 -> 2494.682
C28: SERRAMENTI SERIE S | G28: =(D28*F28)/1000000 -> 0 | I28: =G28*H28 -> 0 | J28: 0 | K28: =J28*$K$5 -> 0 | L28: =K28*$L$5 -> 0 | M28: =L28*$M$5 -> 0 | N28: =M28 -> 0 | O28: =N28*H28 -> 0 | P28: 0 | Q28: =P28*$Q$5 -> 0 | R28: 0 | S28: =R28*H28 -> 0 | T28: 0 | U28: =T28*$U$5 -> 0 | V28: =U28 -> 0 | W28: =V28*H28 -> 0 | X28: =($X$5*2*(D28+F28))/1000 -> 0 | Y28: =X28*$Y$5 -> 0 | Z28: =Y28*$Z$5 -> 0 | AA28: =Z28*$AA$5 -> 0 | AB28: =AA28 -> 0 | AC28: =AB28*H28 -> 0 | AD28: =$AD$5*G28 -> 0 | AE28: =AD28*H28 -> 0 | AF28: 0 | AG28: =AF28*H28 -> 0 | AI28: =AH28*H28 -> 0 | AJ28: 0 | AK28: =AJ28*H28 -> 0 | AL28: =$AL$5 -> 60 | AM28: =AL28*H28 -> 0 | AN28: 0 | AO28: =AN28*H28 -> 0 | AP28: 0 | AQ28: =AP28*H28 -> 0 | AR28: =($AR$5*2*(D28+F28))/1000 -> 0 | AS28: =AR28*H28 -> 0 | AT28: 0 | AU28: =AT28*H28 -> 0 | AV28: 0 | AW28: =AV28*H28 -> 0 | AX28: 0 | AY28: =AX28*H28 -> 0 | AZ28: =$AZ$8*G28 -> 0 | BA28: =AZ28*H28 -> 0 | BB28: =N28+R28+V28+AB28+AD28+AF28+AH28+AJ28+AL28+AN28+AP28+AR28+AT28+AV28+AX28+AZ28 -> 60 | BC28: =O28+S28+W28+AC28+AE28+AG28+AI28+AK28+AM28+AO28+AQ28+AS28+AU28+AW28+AY28+BA28 -> 0 | BD28: =BC28/I28 -> #DIV/0! | BE28: =BB28*$BE$5 -> 0.72 | BF28: =BC28*$BE$5 -> 0 | BG28: =BB28*$BG$5 -> 0.9 | BH28: =BC28*$BG$5 -> 0 | BI28: =BB28*$BI$5 -> 0.3 | BJ28: =BC28*$BI$5 -> 0 | BK28: =BB28*$BK$5 -> 0.6 | BL28: =BC28*$BK$5 -> 0 | BM28: =$BM$5 -> 0 | BN28: =BB28*BM28 -> 0 | BO28: =BC28*BM$12 -> 0 | BP28: =$BP$5 -> 0.32 | BQ28: =BB28*$BP28 -> 19.2 | BR28: =BC28*BP28 -> 0 | BS28: =BB28+BE28+BG28+BI28+BK28+BN28+BQ28 -> 81.72 | BT28: =BC28+BF28+BH28+BJ28+BL28+BO28+BR28 -> 0 | BU28: =BT28/I28 -> #DIV/0!
B29: S1a | C29: Serramento in acciaio con volta circolare fissa specchiatura inferiore con porta a doppio battente apertura esterna, sopraluce rettangolare fisso e apribile vasistas di ventilazione ad apertura meccanizzata. Controtelaio composto da tubi rettangolari ancorato alla struttura principale mediante adeguate zanche annegate nel muro o viti di fissaggio, il telaio deve essere correttamente isolato e zincato per proteggerlo dalla corrosione. Vetro: 66.2 COOL-LITE 70-33#2 INDURITI / 20mm (aria-argon 90%) / 55.2 int. INDURITI Comprese lamiere di raccordo, memebrane e isolanti. | D29: 3000 | F29: 5900 | G29: =(D29*F29)/1000000 -> 17.7 | H29: 1 | I29: =G29*H29 -> 17.7 | J29: 0 | K29: =J29*$K$5 -> 0 | L29: =K29*$L$5 -> 0 | M29: =L29*$M$5 -> 0 | N29: =M29 -> 0 | O29: =N29*H29 -> 0 | P29: 0 | Q29: =P29*$Q$5 -> 0 | R29: 0 | S29: =R29*H29 -> 0 | T29: =$T$5 -> 650 | U29: =T29*$U$5 -> 650 | V29: =U29 -> 650 | W29: =V29*H29 -> 650 | X29: =($X$5*2*(D29+F29))/1000 -> 391.6 | Y29: =X29*$Y$5 -> 391.6 | Z29: =Y29*$Z$5 -> 391.6 | AA29: =Z29*$AA$5 -> 391.6 | AB29: =AA29 -> 391.6 | AC29: =AB29*H29 -> 391.6 | AD29: =$AD$5*G29 -> 265.5 | AE29: =AD29*H29 -> 265.5 | AF29: 0 | AG29: =AF29*H29 -> 0 | AH29: =$AH$5*G29 -> 6060.48 | AI29: =AH29*H29 -> 6060.48 | AJ29: 6480 | AK29: =AJ29*H29 -> 6480 | AL29: =$AL$5 -> 60 | AM29: =AL29*H29 -> 60 | AN29: =$AN$7*G29 -> 4779 | AO29: =AN29*H29 -> 4779 | AP29: 0 | AQ29: =AP29*H29 -> 0 | AR29: =($AR$5*2*(D29+F29))/1000 -> 623 | AS29: =AR29*H29 -> 623 | AT29: 0 | AU29: =AT29*H29 -> 0 | AV29: =$AV$7*G29 -> 4141.8 | AW29: =AV29*H29 -> 4141.8 | AX29: 0 | AY29: =AX29*H29 -> 0 | AZ29: =$AZ$8*G29 -> 0 | BA29: =AZ29*H29 -> 0 | BB29: =N29+R29+V29+AB29+AD29+AF29+AH29+AJ29+AL29+AN29+AP29+AR29+AT29+AV29+AX29+AZ29 -> 23451.38 | BC29: =O29+S29+W29+AC29+AE29+AG29+AI29+AK29+AM29+AO29+AQ29+AS29+AU29+AW29+AY29+BA29 -> 23451.38 | BD29: =BC29/I29 -> 1324.9367 | BE29: =BB29*$BE$5 -> 281.41656 | BF29: =BC29*$BE$5 -> 281.41656 | BG29: =BB29*$BG$5 -> 351.7707 | BH29: =BC29*$BG$5 -> 351.7707 | BI29: =BB29*$BI$5 -> 117.2569 | BJ29: =BC29*$BI$5 -> 117.2569 | BK29: =BB29*$BK$5 -> 234.5138 | BL29: =BC29*$BK$5 -> 234.5138 | BM29: =$BM$5 -> 0 | BN29: =BB29*BM29 -> 0 | BO29: =BC29*BM$12 -> 0 | BP29: =$BP$5 -> 0.32 | BQ29: =BB29*$BP29 -> 7504.4416 | BR29: =BC29*BP29 -> 7504.4416 | BS29: =BB29+BE29+BG29+BI29+BK29+BN29+BQ29 -> 31940.78 | BT29: =BC29+BF29+BH29+BJ29+BL29+BO29+BR29 -> 31940.78 | BU29: =BT29/I29 -> 1804.5638
B30: S1b | C30: Serramento in acciaio con volta circolare fissa specchiatura inferiore con porta a doppio battente apertura esterna, sopraluci rettangolari fissi. Controtelaio composto da tubi rettangolari ancorato alla struttura principale mediante adeguate zanche annegate nel muro o viti di fissaggio, il telaio deve essere correttamente isolato e zincato per proteggerlo dalla corrosione. Vetro: 66.2 COOL-LITE 70-33#2 INDURITI / 20mm (aria-argon 90%) / 55.2 int. INDURITI Comprese lamiere di raccordo, memebrane e isolanti. | D30: 3000 | F30: 5900 | G30: =(D30*F30)/1000000 -> 17.7 | H30: 2 | I30: =G30*H30 -> 35.4 | J30: 0 | K30: =J30*$K$5 -> 0 | L30: =K30*$L$5 -> 0 | M30: =L30*$M$5 -> 0 | N30: =M30 -> 0 | O30: =N30*H30 -> 0 | P30: 0 | Q30: =P30*$Q$5 -> 0 | R30: 0 | S30: =R30*H30 -> 0 | T30: =$T$5 -> 650 | U30: =T30*$U$5 -> 650 | V30: =U30 -> 650 | W30: =V30*H30 -> 1300 | X30: =($X$5*2*(D30+F30))/1000 -> 391.6 | Y30: =X30*$Y$5 -> 391.6 | Z30: =Y30*$Z$5 -> 391.6 | AA30: =Z30*$AA$5 -> 391.6 | AB30: =AA30 -> 391.6 | AC30: =AB30*H30 -> 783.2 | AD30: =$AD$5*G30 -> 265.5 | AE30: =AD30*H30 -> 531 | AF30: 0 | AG30: =AF30*H30 -> 0 | AH30: =$AH$5*G30 -> 6060.48 | AI30: =AH30*H30 -> 12120.96 | AJ30: 6480 | AK30: =AJ30*H30 -> 12960 | AL30: =$AL$5 -> 60 | AM30: =AL30*H30 -> 120 | AN30: =$AN$7*G30 -> 4779 | AO30: =AN30*H30 -> 9558 | AP30: 0 | AQ30: =AP30*H30 -> 0 | AR30: =($AR$5*2*(D30+F30))/1000 -> 623 | AS30: =AR30*H30 -> 1246 | AT30: 0 | AU30: =AT30*H30 -> 0 | AV30: =$AV$7*G30 -> 4141.8 | AW30: =AV30*H30 -> 8283.6 | AX30: 0 | AY30: =AX30*H30 -> 0 | AZ30: =$AZ$8*G30 -> 0 | BA30: =AZ30*H30 -> 0 | BB30: =N30+R30+V30+AB30+AD30+AF30+AH30+AJ30+AL30+AN30+AP30+AR30+AT30+AV30+AX30+AZ30 -> 23451.38 | BC30: =O30+S30+W30+AC30+AE30+AG30+AI30+AK30+AM30+AO30+AQ30+AS30+AU30+AW30+AY30+BA30 -> 46902.76 | BD30: =BC30/I30 -> 1324.9367 | BE30: =BB30*$BE$5 -> 281.41656 | BF30: =BC30*$BE$5 -> 562.83312 | BG30: =BB30*$BG$5 -> 351.7707 | BH30: =BC30*$BG$5 -> 703.5414 | BI30: =BB30*$BI$5 -> 117.2569 | BJ30: =BC30*$BI$5 -> 234.5138 | BK30: =BB30*$BK$5 -> 234.5138 | BL30: =BC30*$BK$5 -> 469.0276 | BM30: =$BM$5 -> 0 | BN30: =BB30*BM30 -> 0 | BO30: =BC30*BM$12 -> 0 | BP30: =$BP$5 -> 0.32 | BQ30: =BB30*$BP30 -> 7504.4416 | BR30: =BC30*BP30 -> 15008.883 | BS30: =BB30+BE30+BG30+BI30+BK30+BN30+BQ30 -> 31940.78 | BT30: =BC30+BF30+BH30+BJ30+BL30+BO30+BR30 -> 63881.559 | BU30: =BT30/I30 -> 1804.5638
B31: S1c | C31: Serramento in acciaio con volta circolare fissa specchiatura inferiore con porta US a doppio battente apertura esterna con pushbar, sopraluci rettangolari fissi. Controtelaio composto da tubi rettangolari ancorato alla struttura principale mediante adeguate zanche annegate nel muro o viti di fissaggio, il telaio deve essere correttamente isolato e zincato per proteggerlo dalla corrosione. Vetro: 66.2 COOL-LITE 70-33#2 INDURITI / 20mm (aria-argon 90%) / 55.2 int. INDURITI Comprese lamiere di raccordo, memebrane e isolanti. | D31: 3000 | F31: 5900 | G31: =(D31*F31)/1000000 -> 17.7 | H31: 1 | I31: =G31*H31 -> 17.7 | J31: 0 | K31: =J31*$K$5 -> 0 | L31: =K31*$L$5 -> 0 | M31: =L31*$M$5 -> 0 | N31: =M31 -> 0 | O31: =N31*H31 -> 0 | P31: 0 | Q31: =P31*$Q$5 -> 0 | R31: 0 | S31: =R31*H31 -> 0 | T31: =$T$5 -> 650 | U31: =T31*$U$5 -> 650 | V31: =U31 -> 650 | W31: =V31*H31 -> 650 | X31: =($X$5*2*(D31+F31))/1000 -> 391.6 | Y31: =X31*$Y$5 -> 391.6 | Z31: =Y31*$Z$5 -> 391.6 | AA31: =Z31*$AA$5 -> 391.6 | AB31: =AA31 -> 391.6 | AC31: =AB31*H31 -> 391.6 | AD31: =$AD$5*G31 -> 265.5 | AE31: =AD31*H31 -> 265.5 | AF31: 0 | AG31: =AF31*H31 -> 0 | AH31: =$AH$5*G31 -> 6060.48 | AI31: =AH31*H31 -> 6060.48 | AJ31: 6480 | AK31: =AJ31*H31 -> 6480 | AL31: =$AL$5 -> 60 | AM31: =AL31*H31 -> 60 | AN31: =$AN$7*G31 -> 4779 | AO31: =AN31*H31 -> 4779 | AP31: 0 | AQ31: =AP31*H31 -> 0 | AR31: =($AR$5*2*(D31+F31))/1000 -> 623 | AS31: =AR31*H31 -> 623 | AT31: 0 | AU31: =AT31*H31 -> 0 | AV31: =$AV$7*G31 -> 4141.8 | AW31: =AV31*H31 -> 4141.8 | AX31: 0 | AY31: =AX31*H31 -> 0 | AZ31: =$AZ$8*G31 -> 0 | BA31: =AZ31*H31 -> 0 | BB31: =N31+R31+V31+AB31+AD31+AF31+AH31+AJ31+AL31+AN31+AP31+AR31+AT31+AV31+AX31+AZ31 -> 23451.38 | BC31: =O31+S31+W31+AC31+AE31+AG31+AI31+AK31+AM31+AO31+AQ31+AS31+AU31+AW31+AY31+BA31 -> 23451.38 | BD31: =BC31/I31 -> 1324.9367 | BE31: =BB31*$BE$5 -> 281.41656 | BF31: =BC31*$BE$5 -> 281.41656 | BG31: =BB31*$BG$5 -> 351.7707 | BH31: =BC31*$BG$5 -> 351.7707 | BI31: =BB31*$BI$5 -> 117.2569 | BJ31: =BC31*$BI$5 -> 117.2569 | BK31: =BB31*$BK$5 -> 234.5138 | BL31: =BC31*$BK$5 -> 234.5138 | BM31: =$BM$5 -> 0 | BN31: =BB31*BM31 -> 0 | BO31: =BC31*BM$12 -> 0 | BP31: =$BP$5 -> 0.32 | BQ31: =BB31*$BP31 -> 7504.4416 | BR31: =BC31*BP31 -> 7504.4416 | BS31: =BB31+BE31+BG31+BI31+BK31+BN31+BQ31 -> 31940.78 | BT31: =BC31+BF31+BH31+BJ31+BL31+BO31+BR31 -> 31940.78 | BU31: =BT31/I31 -> 1804.5638
B32: S2a | C32: Serramento in acciaio con volta circolare fissa specchiatura inferiore con vetri fissi, sopraluce rettangolare fisso e apribile vasistas di ventilazione apertura meccanizzata. Controtelaio composto da tubi rettangolari ancorato alla struttura principale mediante adeguate zanche annegate nel muro o viti di fissaggio, il telaio deve essere correttamente isolato e zincato per proteggerlo dalla corrosione. Vetro: 66.2 COOL-LITE 70-33#2 INDURITI / 20mm (aria-argon 90%) / 55.2 int. INDURITI Comprese lamiere di raccordo, memebrane e isolanti. | D32: 3000 | F32: 5900 | G32: =(D32*F32)/1000000 -> 17.7 | H32: 3 | I32: =G32*H32 -> 53.1 | J32: 0 | K32: =J32*$K$5 -> 0 | L32: =K32*$L$5 -> 0 | M32: =L32*$M$5 -> 0 | N32: =M32 -> 0 | O32: =N32*H32 -> 0 | P32: 0 | Q32: =P32*$Q$5 -> 0 | R32: 0 | S32: =R32*H32 -> 0 | T32: =$T$5 -> 650 | U32: =T32*$U$5 -> 650 | V32: =U32 -> 650 | W32: =V32*H32 -> 1950 | X32: =($X$5*2*(D32+F32))/1000 -> 391.6 | Y32: =X32*$Y$5 -> 391.6 | Z32: =Y32*$Z$5 -> 391.6 | AA32: =Z32*$AA$5 -> 391.6 | AB32: =AA32 -> 391.6 | AC32: =AB32*H32 -> 1174.8 | AD32: =$AD$5*G32 -> 265.5 | AE32: =AD32*H32 -> 796.5 | AF32: 0 | AG32: =AF32*H32 -> 0 | AH32: =$AH$5*G32 -> 6060.48 | AI32: =AH32*H32 -> 18181.44 | AJ32: 5965 | AK32: =AJ32*H32 -> 17895 | AL32: =$AL$5 -> 60 | AM32: =AL32*H32 -> 180 | AN32: =$AN$7*G32 -> 4779 | AO32: =AN32*H32 -> 14337 | AP32: 0 | AQ32: =AP32*H32 -> 0 | AR32: =($AR$5*2*(D32+F32))/1000 -> 623 | AS32: =AR32*H32 -> 1869 | AT32: 0 | AU32: =AT32*H32 -> 0 | AV32: =$AV$7*G32 -> 4141.8 | AW32: =AV32*H32 -> 12425.4 | AX32: 0 | AY32: =AX32*H32 -> 0 | AZ32: =$AZ$8*G32 -> 0 | BA32: =AZ32*H32 -> 0 | BB32: =N32+R32+V32+AB32+AD32+AF32+AH32+AJ32+AL32+AN32+AP32+AR32+AT32+AV32+AX32+AZ32 -> 22936.38 | BC32: =O32+S32+W32+AC32+AE32+AG32+AI32+AK32+AM32+AO32+AQ32+AS32+AU32+AW32+AY32+BA32 -> 68809.14 | BD32: =BC32/I32 -> 1295.8407 | BE32: =BB32*$BE$5 -> 275.23656 | BF32: =BC32*$BE$5 -> 825.70968 | BG32: =BB32*$BG$5 -> 344.0457 | BH32: =BC32*$BG$5 -> 1032.1371 | BI32: =BB32*$BI$5 -> 114.6819 | BJ32: =BC32*$BI$5 -> 344.0457 | BK32: =BB32*$BK$5 -> 229.3638 | BL32: =BC32*$BK$5 -> 688.0914 | BM32: =$BM$5 -> 0 | BN32: =BB32*BM32 -> 0 | BO32: =BC32*BM$12 -> 0 | BP32: =$BP$5 -> 0.32 | BQ32: =BB32*$BP32 -> 7339.6416 | BR32: =BC32*BP32 -> 22018.925 | BS32: =BB32+BE32+BG32+BI32+BK32+BN32+BQ32 -> 31239.35 | BT32: =BC32+BF32+BH32+BJ32+BL32+BO32+BR32 -> 93718.049 | BU32: =BT32/I32 -> 1764.935
B33: S2b | C33: Serramento in acciaio con volta circolare fissa specchiatura inferiore con vetri fissi, sopraluce rettangolari fissi. Controtelaio composto da tubi rettangolari ancorato alla struttura principale mediante adeguate zanche annegate nel muro o viti di fissaggio, il telaio deve essere correttamente isolato e zincato per proteggerlo dalla corrosione. Vetro: 66.2 COOL-LITE 70-33#2 INDURITI / 20mm (aria-argon 90%) / 55.2 int. INDURITI Comprese lamiere di raccordo, memebrane e isolanti. | D33: 3000 | F33: 5900 | G33: =(D33*F33)/1000000 -> 17.7 | H33: 4 | I33: =G33*H33 -> 70.8 | J33: 0 | K33: =J33*$K$5 -> 0 | L33: =K33*$L$5 -> 0 | M33: =L33*$M$5 -> 0 | N33: =M33 -> 0 | O33: =N33*H33 -> 0 | P33: 0 | Q33: =P33*$Q$5 -> 0 | R33: 0 | S33: =R33*H33 -> 0 | T33: =$T$5 -> 650 | U33: =T33*$U$5 -> 650 | V33: =U33 -> 650 | W33: =V33*H33 -> 2600 | X33: =($X$5*2*(D33+F33))/1000 -> 391.6 | Y33: =X33*$Y$5 -> 391.6 | Z33: =Y33*$Z$5 -> 391.6 | AA33: =Z33*$AA$5 -> 391.6 | AB33: =AA33 -> 391.6 | AC33: =AB33*H33 -> 1566.4 | AD33: =$AD$5*G33 -> 265.5 | AE33: =AD33*H33 -> 1062 | AF33: 0 | AG33: =AF33*H33 -> 0 | AH33: =$AH$5*G33 -> 6060.48 | AI33: =AH33*H33 -> 24241.92 | AJ33: 5965 | AK33: =AJ33*H33 -> 23860 | AL33: =$AL$5 -> 60 | AM33: =AL33*H33 -> 240 | AN33: =$AN$7*G33 -> 4779 | AO33: =AN33*H33 -> 19116 | AP33: 0 | AQ33: =AP33*H33 -> 0 | AR33: =($AR$5*2*(D33+F33))/1000 -> 623 | AS33: =AR33*H33 -> 2492 | AT33: 0 | AU33: =AT33*H33 -> 0 | AV33: =$AV$7*G33 -> 4141.8 | AW33: =AV33*H33 -> 16567.2 | AX33: 0 | AY33: =AX33*H33 -> 0 | AZ33: =$AZ$8*G33 -> 0 | BA33: =AZ33*H33 -> 0 | BB33: =N33+R33+V33+AB33+AD33+AF33+AH33+AJ33+AL33+AN33+AP33+AR33+AT33+AV33+AX33+AZ33 -> 22936.38 | BC33: =O33+S33+W33+AC33+AE33+AG33+AI33+AK33+AM33+AO33+AQ33+AS33+AU33+AW33+AY33+BA33 -> 91745.52 | BD33: =BC33/I33 -> 1295.8407 | BE33: =BB33*$BE$5 -> 275.23656 | BF33: =BC33*$BE$5 -> 1100.9462 | BG33: =BB33*$BG$5 -> 344.0457 | BH33: =BC33*$BG$5 -> 1376.1828 | BI33: =BB33*$BI$5 -> 114.6819 | BJ33: =BC33*$BI$5 -> 458.7276 | BK33: =BB33*$BK$5 -> 229.3638 | BL33: =BC33*$BK$5 -> 917.4552 | BM33: =$BM$5 -> 0 | BN33: =BB33*BM33 -> 0 | BO33: =BC33*BM$12 -> 0 | BP33: =$BP$5 -> 0.32 | BQ33: =BB33*$BP33 -> 7339.6416 | BR33: =BC33*BP33 -> 29358.566 | BS33: =BB33+BE33+BG33+BI33+BK33+BN33+BQ33 -> 31239.35 | BT33: =BC33+BF33+BH33+BJ33+BL33+BO33+BR33 -> 124957.4 | BU33: =BT33/I33 -> 1764.935
B34: S2c | C34: Serramento in acciaio con volta circolare fissa specchiatura inferiore con vetri fissi, sopraluce rettangolare fisso e apribile vasistas di ventilazione apertura meccanizzata. Controtelaio composto da tubi rettangolari ancorato alla struttura principale mediante adeguate zanche annegate nel muro o viti di fissaggio, il telaio deve essere correttamente isolato e zincato per proteggerlo dalla corrosione. Vetro: 66.2 COOL-LITE 70-33#2 INDURITI / 20mm (aria-argon 90%) / 55.2 int. INDURITI Comprese lamiere di raccordo, memebrane e isolanti. | D34: 3000 | F34: 5900 | G34: =(D34*F34)/1000000 -> 17.7 | H34: 1 | I34: =G34*H34 -> 17.7 | J34: 0 | K34: =J34*$K$5 -> 0 | L34: =K34*$L$5 -> 0 | M34: =L34*$M$5 -> 0 | N34: =M34 -> 0 | O34: =N34*H34 -> 0 | P34: 0 | Q34: =P34*$Q$5 -> 0 | R34: 0 | S34: =R34*H34 -> 0 | T34: =$T$5 -> 650 | U34: =T34*$U$5 -> 650 | V34: =U34 -> 650 | W34: =V34*H34 -> 650 | X34: =($X$5*2*(D34+F34))/1000 -> 391.6 | Y34: =X34*$Y$5 -> 391.6 | Z34: =Y34*$Z$5 -> 391.6 | AA34: =Z34*$AA$5 -> 391.6 | AB34: =AA34 -> 391.6 | AC34: =AB34*H34 -> 391.6 | AD34: =$AD$5*G34 -> 265.5 | AE34: =AD34*H34 -> 265.5 | AF34: 0 | AG34: =AF34*H34 -> 0 | AH34: =$AH$5*G34 -> 6060.48 | AI34: =AH34*H34 -> 6060.48 | AJ34: 5965 | AK34: =AJ34*H34 -> 5965 | AL34: =$AL$5 -> 60 | AM34: =AL34*H34 -> 60 | AN34: =$AN$7*G34 -> 4779 | AO34: =AN34*H34 -> 4779 | AP34: 0 | AQ34: =AP34*H34 -> 0 | AR34: =($AR$5*2*(D34+F34))/1000 -> 623 | AS34: =AR34*H34 -> 623 | AT34: 0 | AU34: =AT34*H34 -> 0 | AV34: =$AV$7*G34 -> 4141.8 | AW34: =AV34*H34 -> 4141.8 | AX34: 0 | AY34: =AX34*H34 -> 0 | AZ34: =$AZ$8*G34 -> 0 | BA34: =AZ34*H34 -> 0 | BB34: =N34+R34+V34+AB34+AD34+AF34+AH34+AJ34+AL34+AN34+AP34+AR34+AT34+AV34+AX34+AZ34 -> 22936.38 | BC34: =O34+S34+W34+AC34+AE34+AG34+AI34+AK34+AM34+AO34+AQ34+AS34+AU34+AW34+AY34+BA34 -> 22936.38 | BD34: =BC34/I34 -> 1295.8407 | BE34: =BB34*$BE$5 -> 275.23656 | BF34: =BC34*$BE$5 -> 275.23656 | BG34: =BB34*$BG$5 -> 344.0457 | BH34: =BC34*$BG$5 -> 344.0457 | BI34: =BB34*$BI$5 -> 114.6819 | BJ34: =BC34*$BI$5 -> 114.6819 | BK34: =BB34*$BK$5 -> 229.3638 | BL34: =BC34*$BK$5 -> 229.3638 | BM34: =$BM$5 -> 0 | BN34: =BB34*BM34 -> 0 | BO34: =BC34*BM$12 -> 0 | BP34: =$BP$5 -> 0.32 | BQ34: =BB34*$BP34 -> 7339.6416 | BR34: =BC34*BP34 -> 7339.6416 | BS34: =BB34+BE34+BG34+BI34+BK34+BN34+BQ34 -> 31239.35 | BT34: =BC34+BF34+BH34+BJ34+BL34+BO34+BR34 -> 31239.35 | BU34: =BT34/I34 -> 1764.935
B35: S3 | C35: Serramento in acciaio con volta circolare fissa, specchiatura inferiore con porta scorrevole ad anta e fissi laterali, sopraluce rettangolare fisso e apribile vasistas di ventilazione apertura meccanizzata. Controtelaio composto da tubi rettangolari ancorato alla struttura principale mediante adeguate zanche annegate nel muro o viti di fissaggio, il telaio deve essere correttamente isolato e zincato per proteggerlo dalla corrosione. Vetro: 66.2 COOL-LITE 70-33#2 INDURITI / 20mm (aria-argon 90%) / 55.2 int. INDURITI Comprese lamiere di raccordo, memebrane e isolanti. | D35: 3000 | F35: 5900 | G35: =(D35*F35)/1000000 -> 17.7 | H35: 2 | I35: =G35*H35 -> 35.4 | J35: 0 | K35: =J35*$K$5 -> 0 | L35: =K35*$L$5 -> 0 | M35: =L35*$M$5 -> 0 | N35: =M35 -> 0 | O35: =N35*H35 -> 0 | P35: 0 | Q35: =P35*$Q$5 -> 0 | R35: 0 | S35: =R35*H35 -> 0 | T35: =$T$5 -> 650 | U35: =T35*$U$5 -> 650 | V35: =U35 -> 650 | W35: =V35*H35 -> 1300 | X35: =($X$5*2*(D35+F35))/1000 -> 391.6 | Y35: =X35*$Y$5 -> 391.6 | Z35: =Y35*$Z$5 -> 391.6 | AA35: =Z35*$AA$5 -> 391.6 | AB35: =AA35 -> 391.6 | AC35: =AB35*H35 -> 783.2 | AD35: =$AD$5*G35 -> 265.5 | AE35: =AD35*H35 -> 531 | AF35: 0 | AG35: =AF35*H35 -> 0 | AH35: =$AH$5*G35 -> 6060.48 | AI35: =AH35*H35 -> 12120.96 | AJ35: 6865 | AK35: =AJ35*H35 -> 13730 | AL35: =$AL$5+3000 -> 3060 | AM35: =AL35*H35 -> 6120 | AN35: =$AN$7*G35 -> 4779 | AO35: =AN35*H35 -> 9558 | AP35: 0 | AQ35: =AP35*H35 -> 0 | AR35: =($AR$5*2*(D35+F35))/1000 -> 623 | AS35: =AR35*H35 -> 1246 | AT35: 0 | AU35: =AT35*H35 -> 0 | AV35: =$AV$7*G35 -> 4141.8 | AW35: =AV35*H35 -> 8283.6 | AX35: 0 | AY35: =AX35*H35 -> 0 | AZ35: =$AZ$8*G35 -> 0 | BA35: =AZ35*H35 -> 0 | BB35: =N35+R35+V35+AB35+AD35+AF35+AH35+AJ35+AL35+AN35+AP35+AR35+AT35+AV35+AX35+AZ35 -> 26836.38 | BC35: =O35+S35+W35+AC35+AE35+AG35+AI35+AK35+AM35+AO35+AQ35+AS35+AU35+AW35+AY35+BA35 -> 53672.76 | BD35: =BC35/I35 -> 1516.1797 | BE35: =BB35*$BE$5 -> 322.03656 | BF35: =BC35*$BE$5 -> 644.07312 | BG35: =BB35*$BG$5 -> 402.5457 | BH35: =BC35*$BG$5 -> 805.0914 | BI35: =BB35*$BI$5 -> 134.1819 | BJ35: =BC35*$BI$5 -> 268.3638 | BK35: =BB35*$BK$5 -> 268.3638 | BL35: =BC35*$BK$5 -> 536.7276 | BM35: =$BM$5 -> 0 | BN35: =BB35*BM35 -> 0 | BO35: =BC35*BM$12 -> 0 | BP35: =$BP$5 -> 0.32 | BQ35: =BB35*$BP35 -> 8587.6416 | BR35: =BC35*BP35 -> 17175.283 | BS35: =BB35+BE35+BG35+BI35+BK35+BN35+BQ35 -> 36551.15 | BT35: =BC35+BF35+BH35+BJ35+BL35+BO35+BR35 -> 73102.299 | BU35: =BT35/I35 -> 2065.0367
B36: S4 | C36: Serramento in acciaio con volta circolare apribile a vasistas specchiatura inferiore con porta a doppio battente apertura esterna, sopraluce rettangolare fisso Controtelaio composto da tubi rettangolari ancorato alla struttura principale mediante adeguate zanche annegate nel muro o viti di fissaggio, il telaio deve essere correttamente isolato e zincato per proteggerlo dalla corrosione. Vetro: 66.2 COOL-LITE 70-33#2 INDURITI / 20mm (aria-argon 90%) / 55.2 int. INDURITI Comprese lamiere di raccordo, memebrane e isolanti. | D36: 1900 | F36: 4500 | G36: =(D36*F36)/1000000 -> 8.55 | H36: 2 | I36: =G36*H36 -> 17.1 | J36: 0 | K36: =J36*$K$5 -> 0 | L36: =K36*$L$5 -> 0 | M36: =L36*$M$5 -> 0 | N36: =M36 -> 0 | O36: =N36*H36 -> 0 | P36: 0 | Q36: =P36*$Q$5 -> 0 | R36: 0 | S36: =R36*H36 -> 0 | T36: =$T$5 -> 650 | U36: =T36*$U$5 -> 650 | V36: =U36 -> 650 | W36: =V36*H36 -> 1300 | X36: =($X$5*2*(D36+F36))/1000 -> 281.6 | Y36: =X36*$Y$5 -> 281.6 | Z36: =Y36*$Z$5 -> 281.6 | AA36: =Z36*$AA$5 -> 281.6 | AB36: =AA36 -> 281.6 | AC36: =AB36*H36 -> 563.2 | AD36: =$AD$5*G36 -> 128.25 | AE36: =AD36*H36 -> 256.5 | AF36: 0 | AG36: =AF36*H36 -> 0 | AH36: =$AH$5*G36 -> 2927.52 | AI36: =AH36*H36 -> 5855.04 | AJ36: 3665 | AK36: =AJ36*H36 -> 7330 | AL36: =$AL$5 -> 60 | AM36: =AL36*H36 -> 120 | AN36: =$AN$7*G36 -> 2308.5 | AO36: =AN36*H36 -> 4617 | AP36: 0 | AQ36: =AP36*H36 -> 0 | AR36: =($AR$5*2*(D36+F36))/1000 -> 448 | AS36: =AR36*H36 -> 896 | AT36: 0 | AU36: =AT36*H36 -> 0 | AV36: =$AV$7*G36 -> 2000.7 | AW36: =AV36*H36 -> 4001.4 | AX36: 0 | AY36: =AX36*H36 -> 0 | AZ36: =$AZ$8*G36 -> 0 | BA36: =AZ36*H36 -> 0 | BB36: =N36+R36+V36+AB36+AD36+AF36+AH36+AJ36+AL36+AN36+AP36+AR36+AT36+AV36+AX36+AZ36 -> 12469.57 | BC36: =O36+S36+W36+AC36+AE36+AG36+AI36+AK36+AM36+AO36+AQ36+AS36+AU36+AW36+AY36+BA36 -> 24939.14 | BD36: =BC36/I36 -> 1458.4292 | BE36: =BB36*$BE$5 -> 149.63484 | BF36: =BC36*$BE$5 -> 299.26968 | BG36: =BB36*$BG$5 -> 187.04355 | BH36: =BC36*$BG$5 -> 374.0871 | BI36: =BB36*$BI$5 -> 62.34785 | BJ36: =BC36*$BI$5 -> 124.6957 | BK36: =BB36*$BK$5 -> 124.6957 | BL36: =BC36*$BK$5 -> 249.3914 | BM36: =$BM$5 -> 0 | BN36: =BB36*BM36 -> 0 | BO36: =BC36*BM$12 -> 0 | BP36: =$BP$5 -> 0.32 | BQ36: =BB36*$BP36 -> 3990.2624 | BR36: =BC36*BP36 -> 7980.5248 | BS36: =BB36+BE36+BG36+BI36+BK36+BN36+BQ36 -> 16983.554 | BT36: =BC36+BF36+BH36+BJ36+BL36+BO36+BR36 -> 33967.109 | BU36: =BT36/I36 -> 1986.3806
A37: EI | B37: S4a - EI60 | C37: Serramento in acciaio con volta circolare apribile a vasistas meccanizzato e automatico specchiatura inferiore con porta a doppio battente apertura esterna, sopraluce rettangolare fisso. SOSTITUITO CON ALLUMINIO Reynaers ConceptSystem 77-FP EI 60 (CS 77-FPEI60) Controtelaio composto da tubi rettangolari ancorato alla struttura principale mediante adeguate zanche annegate nel muro o viti di fissaggio, il telaio deve essere correttamente isolato e zincato per proteggerlo dalla corrosione. Vetro: 66.2 COOL-LITE 70-33#2 / 14mm (aria-argon 90%) / 27 CF60-3. Comprese lamiere di raccordo, memebrane e isolanti. | D37: 1900 | F37: 4500 | G37: =(D37*F37)/1000000 -> 8.55 | H37: 1 | I37: =G37*H37 -> 8.55 | K37: =J37*$K$5 -> 0 | L37: =K37*$L$5 -> 0 | M37: =L37*$M$5 -> 0 | N37: =M37 -> 0 | O37: =N37*H37 -> 0 | P37: 0 | Q37: =P37*$Q$5 -> 0 | R37: 0 | S37: =R37*H37 -> 0 | T37: =$T$6 -> 1930 | U37: =T37*$U$5 -> 1930 | V37: =U37 -> 1930 | W37: =V37*H37 -> 1930 | X37: =($X$5*2*(D37+F37))/1000 -> 281.6 | Y37: =X37*$Y$5 -> 281.6 | Z37: =Y37*$Z$5 -> 281.6 | AA37: =Z37*$AA$5 -> 281.6 | AB37: =AA37 -> 281.6 | AC37: =AB37*H37 -> 281.6 | AD37: =$AD$6*G37 -> 239.4 | AE37: =AD37*H37 -> 239.4 | AF37: =3221+720 -> 3941 | AG37: =AF37*H37 -> 3941 | AI37: =AH37*H37 -> 0 | AJ37: 0 | AK37: =AJ37*H37 -> 0 | AL37: =$AL$5 -> 60 | AM37: =AL37*H37 -> 60 | AN37: =$AN$8*G37 -> 5087.25 | AO37: =AN37*H37 -> 5087.25 | AP37: 0 | AQ37: =AP37*H37 -> 0 | AR37: =($AR$6*2*(D37+F37))/1000 -> 576 | AS37: =AR37*H37 -> 576 | AT37: 1815 | AU37: =AT37*H37 -> 1815 | AV37: =$AV$8 -> 1286 | AW37: =AV37*H37 -> 1286 | AX37: 0 | AY37: =AX37*H37 -> 0 | AZ37: =$AZ$8*G37 -> 0 | BA37: =AZ37*H37 -> 0 | BB37: =N37+R37+V37+AB37+AD37+AF37+AH37+AJ37+AL37+AN37+AP37+AR37+AT37+AV37+AX37+AZ37 -> 15216.25 | BC37: =O37+S37+W37+AC37+AE37+AG37+AI37+AK37+AM37+AO37+AQ37+AS37+AU37+AW37+AY37+BA37 -> 15216.25 | BD37: =BC37/I37 -> 1779.6784 | BE37: =BB37*$BE$5 -> 182.595 | BF37: =BC37*$BE$5 -> 182.595 | BG37: =BB37*$BG$5 -> 228.24375 | BH37: =BC37*$BG$5 -> 228.24375 | BI37: =BB37*$BI$5 -> 76.08125 | BJ37: =BC37*$BI$5 -> 76.08125 | BK37: =BB37*$BK$5 -> 152.1625 | BL37: =BC37*$BK$5 -> 152.1625 | BM37: =$BM$5 -> 0 | BN37: =BB37*BM37 -> 0 | BO37: =BC37*BM$12 -> 0 | BP37: =$BP$5 -> 0.32 | BQ37: =BB37*$BP37 -> 4869.2 | BR37: =BC37*BP37 -> 4869.2 | BS37: =BB37+BE37+BG37+BI37+BK37+BN37+BQ37 -> 20724.532 | BT37: =BC37+BF37+BH37+BJ37+BL37+BO37+BR37 -> 20724.532 | BU37: =BT37/I37 -> 2423.9219
A38: AL | B38: S5 | C38: Serramento in acciaio rettangolare con porta inferiore a doppia anta apertura esterna; tre specchiature sopraluce: inferiore apribile a battente apertura esterna, centrale rettangolare opaca fissa, superiore a vasistas apertura interna. SOSTITUITO CON SERRAMENTO IN ALLUMINIO COMPOSTO DA PIU ELEMENTI ACCOPPIATI Reynaers SlimLine 38 (SL 38) Controtelaio composto da tubi rettangolari ancorato alla struttura principale mediante adeguate zanche annegate nel muro o viti di fissaggio, il telaio deve essere correttamente isolato e zincato per proteggerlo dalla corrosione. Vetro: 66.2 COOL-LITE 70-33#2 INDURITI / 20mm (aria-argon 90%) / 55.2 int. INDURITI Comprese lamiere di raccordo, memebrane e isolanti. | D38: 1700 | F38: 6200 | G38: =(D38*F38)/1000000 -> 10.54 | H38: 1 | I38: =G38*H38 -> 10.54 | J38: 0 | K38: =J38*$K$5 -> 0 | L38: =K38*$L$5 -> 0 | M38: =L38*$M$5 -> 0 | N38: =M38 -> 0 | O38: =N38*H38 -> 0 | P38: 0 | Q38: =P38*$Q$5 -> 0 | R38: 0 | S38: =R38*H38 -> 0 | T38: =$T$5 -> 650 | U38: =T38*$U$5 -> 650 | V38: =U38 -> 650 | W38: =V38*H38 -> 650 | X38: =($X$5*2*(D38+F38))/1000 -> 347.6 | Y38: =X38*$Y$5 -> 347.6 | Z38: =Y38*$Z$5 -> 347.6 | AA38: =Z38*$AA$5 -> 347.6 | AB38: =AA38 -> 347.6 | AC38: =AB38*H38 -> 347.6 | AD38: =$AD$5*G38 -> 158.1 | AE38: =AD38*H38 -> 158.1 | AF38: =1185+350+163+340 -> 2038 | AG38: =AF38*H38 -> 2038 | AH38: 0 | AI38: =AH38*H38 -> 0 | AJ38: 0 | AK38: =AJ38*H38 -> 0 | AL38: =$AL$5 -> 60 | AM38: =AL38*H38 -> 60 | AN38: =$AN$5*G38 -> 1422.9 | AO38: =AN38*H38 -> 1422.9 | AP38: 0 | AQ38: =AP38*H38 -> 0 | AR38: =($AR$5*2*(D38+F38))/1000 -> 553 | AS38: =AR38*H38 -> 553 | AT38: 3000 | AU38: =AT38*H38 -> 3000 | AV38: =$AV$7*G38 -> 2466.36 | AW38: =AV38*H38 -> 2466.36 | AX38: 0 | AY38: =AX38*H38 -> 0 | AZ38: =$AZ$8*G38 -> 0 | BA38: =AZ38*H38 -> 0 | BB38: =N38+R38+V38+AB38+AD38+AF38+AH38+AJ38+AL38+AN38+AP38+AR38+AT38+AV38+AX38+AZ38 -> 10695.96 | BC38: =O38+S38+W38+AC38+AE38+AG38+AI38+AK38+AM38+AO38+AQ38+AS38+AU38+AW38+AY38+BA38 -> 10695.96 | BD38: =BC38/I38 -> 1014.797 | BE38: =BB38*$BE$5 -> 128.35152 | BF38: =BC38*$BE$5 -> 128.35152 | BG38: =BB38*$BG$5 -> 160.4394 | BH38: =BC38*$BG$5 -> 160.4394 | BI38: =BB38*$BI$5 -> 53.4798 | BJ38: =BC38*$BI$5 -> 53.4798 | BK38: =BB38*$BK$5 -> 106.9596 | BL38: =BC38*$BK$5 -> 106.9596 | BM38: =$BM$5 -> 0 | BN38: =BB38*BM38 -> 0 | BO38: =BC38*BM$12 -> 0 | BP38: =$BP$5 -> 0.32 | BQ38: =BB38*$BP38 -> 3422.7072 | BR38: =BC38*BP38 -> 3422.7072 | BS38: =BB38+BE38+BG38+BI38+BK38+BN38+BQ38 -> 14567.898 | BT38: =BC38+BF38+BH38+BJ38+BL38+BO38+BR38 -> 14567.898 | BU38: =BT38/I38 -> 1382.1535
A39: AL | B39: S5a | C39: Serramento in acciaio rettangolare con porta inferiore a doppia anta apertura esterna; con tre specchiature sopraluce: inferiore apribile a battente apertura esterna, centrale rettangolare opaca fissa, superiore a vasistas apertura interna.SOSTITUITO CON SERRAMENTO IN ALLUMINIO COMPOSTO DA PIU ELEMENTI ACCOPPIATI Reynaers SlimLine 38 (SL 38) Controtelaio composto da tubi rettangolari ancorato alla struttura principale mediante adeguate zanche annegate nel muro o viti di fissaggio, il telaio deve essere correttamente isolato e zincato per proteggerlo dalla corrosione. Vetro: 66.2 COOL-LITE 70-33#2 INDURITI / 20mm (aria-argon 90%) / 55.2 int. INDURITI Comprese lamiere di raccordo, memebrane e isolanti. | D39: 1700 | F39: 6200 | G39: =(D39*F39)/1000000 -> 10.54 | H39: 1 | I39: =G39*H39 -> 10.54 | J39: 0 | K39: =J39*$K$5 -> 0 | L39: =K39*$L$5 -> 0 | M39: =L39*$M$5 -> 0 | N39: =M39 -> 0 | O39: =N39*H39 -> 0 | P39: 0 | Q39: =P39*$Q$5 -> 0 | R39: 0 | S39: =R39*H39 -> 0 | T39: =$T$5 -> 650 | U39: =T39*$U$5 -> 650 | V39: =U39 -> 650 | W39: =V39*H39 -> 650 | X39: =($X$5*2*(D39+F39))/1000 -> 347.6 | Y39: =X39*$Y$5 -> 347.6 | Z39: =Y39*$Z$5 -> 347.6 | AA39: =Z39*$AA$5 -> 347.6 | AB39: =AA39 -> 347.6 | AC39: =AB39*H39 -> 347.6 | AD39: =$AD$5*G39 -> 158.1 | AE39: =AD39*H39 -> 158.1 | AF39: =1185+350+163+340 -> 2038 | AG39: =AF39*H39 -> 2038 | AH39: 0 | AI39: =AH39*H39 -> 0 | AJ39: 0 | AK39: =AJ39*H39 -> 0 | AL39: =$AL$5 -> 60 | AM39: =AL39*H39 -> 60 | AN39: =$AN$5*G39 -> 1422.9 | AO39: =AN39*H39 -> 1422.9 | AP39: 0 | AQ39: =AP39*H39 -> 0 | AR39: =($AR$5*2*(D39+F39))/1000 -> 553 | AS39: =AR39*H39 -> 553 | AT39: 3000 | AU39: =AT39*H39 -> 3000 | AV39: =$AV$7*G39 -> 2466.36 | AW39: =AV39*H39 -> 2466.36 | AX39: 0 | AY39: =AX39*H39 -> 0 | AZ39: =$AZ$8*G39 -> 0 | BA39: =AZ39*H39 -> 0 | BB39: =N39+R39+V39+AB39+AD39+AF39+AH39+AJ39+AL39+AN39+AP39+AR39+AT39+AV39+AX39+AZ39 -> 10695.96 | BC39: =O39+S39+W39+AC39+AE39+AG39+AI39+AK39+AM39+AO39+AQ39+AS39+AU39+AW39+AY39+BA39 -> 10695.96 | BD39: =BC39/I39 -> 1014.797 | BE39: =BB39*$BE$5 -> 128.35152 | BF39: =BC39*$BE$5 -> 128.35152 | BG39: =BB39*$BG$5 -> 160.4394 | BH39: =BC39*$BG$5 -> 160.4394 | BI39: =BB39*$BI$5 -> 53.4798 | BJ39: =BC39*$BI$5 -> 53.4798 | BK39: =BB39*$BK$5 -> 106.9596 | BL39: =BC39*$BK$5 -> 106.9596 | BM39: =$BM$5 -> 0 | BN39: =BB39*BM39 -> 0 | BO39: =BC39*BM$12 -> 0 | BP39: =$BP$5 -> 0.32 | BQ39: =BB39*$BP39 -> 3422.7072 | BR39: =BC39*BP39 -> 3422.7072 | BS39: =BB39+BE39+BG39+BI39+BK39+BN39+BQ39 -> 14567.898 | BT39: =BC39+BF39+BH39+BJ39+BL39+BO39+BR39 -> 14567.898 | BU39: =BT39/I39 -> 1382.1535
A40: AL | B40: S6 | C40: Serramento in acciaio rettangolare con porta inferiore a doppia anta apertura interna; tre specchiature sopraluce: inferiore apribile a vasistas apertura interna, centrale rettangolare opaca fissa, superiore a vasistas apertura interna.SOSTITUITO CON SERRAMENTO IN ALLUMINIO COMPOSTO DA PIU ELEMENTI ACCOPPIATI Reynaers SlimLine 38 (SL 38) Controtelaio composto da tubi rettangolari ancorato alla struttura principale mediante adeguate zanche annegate nel muro o viti di fissaggio, il telaio deve essere correttamente isolato e zincato per proteggerlo dalla corrosione. Vetro: 66.2 COOL-LITE 70-33#2 INDURITI / 20mm (aria-argon 90%) / 55.2 int. INDURITI Comprese lamiere di raccordo, memebrane e isolanti. | D40: 1700 | F40: 6200 | G40: =(D40*F40)/1000000 -> 10.54 | H40: 2 | I40: =G40*H40 -> 21.08 | J40: 0 | K40: =J40*$K$5 -> 0 | L40: =K40*$L$5 -> 0 | M40: =L40*$M$5 -> 0 | N40: =M40 -> 0 | O40: =N40*H40 -> 0 | P40: 0 | Q40: =P40*$Q$5 -> 0 | R40: 0 | S40: =R40*H40 -> 0 | T40: =$T$5 -> 650 | U40: =T40*$U$5 -> 650 | V40: =U40 -> 650 | W40: =V40*H40 -> 1300 | X40: =($X$5*2*(D40+F40))/1000 -> 347.6 | Y40: =X40*$Y$5 -> 347.6 | Z40: =Y40*$Z$5 -> 347.6 | AA40: =Z40*$AA$5 -> 347.6 | AB40: =AA40 -> 347.6 | AC40: =AB40*H40 -> 695.2 | AD40: =$AD$5*G40 -> 158.1 | AE40: =AD40*H40 -> 316.2 | AF40: =1185+341+163+340 -> 2029 | AG40: =AF40*H40 -> 4058 | AH40: 0 | AI40: =AH40*H40 -> 0 | AJ40: 0 | AK40: =AJ40*H40 -> 0 | AL40: =$AL$5 -> 60 | AM40: =AL40*H40 -> 120 | AN40: =$AN$5*G40 -> 1422.9 | AO40: =AN40*H40 -> 2845.8 | AP40: 0 | AQ40: =AP40*H40 -> 0 | AR40: =($AR$5*2*(D40+F40))/1000 -> 553 | AS40: =AR40*H40 -> 1106 | AT40: 3000 | AU40: =AT40*H40 -> 6000 | AV40: =$AV$7*G40 -> 2466.36 | AW40: =AV40*H40 -> 4932.72 | AX40: 0 | AY40: =AX40*H40 -> 0 | AZ40: =$AZ$8*G40 -> 0 | BA40: =AZ40*H40 -> 0 | BB40: =N40+R40+V40+AB40+AD40+AF40+AH40+AJ40+AL40+AN40+AP40+AR40+AT40+AV40+AX40+AZ40 -> 10686.96 | BC40: =O40+S40+W40+AC40+AE40+AG40+AI40+AK40+AM40+AO40+AQ40+AS40+AU40+AW40+AY40+BA40 -> 21373.92 | BD40: =BC40/I40 -> 1013.9431 | BE40: =BB40*$BE$5 -> 128.24352 | BF40: =BC40*$BE$5 -> 256.48704 | BG40: =BB40*$BG$5 -> 160.3044 | BH40: =BC40*$BG$5 -> 320.6088 | BI40: =BB40*$BI$5 -> 53.4348 | BJ40: =BC40*$BI$5 -> 106.8696 | BK40: =BB40*$BK$5 -> 106.8696 | BL40: =BC40*$BK$5 -> 213.7392 | BM40: =$BM$5 -> 0 | BN40: =BB40*BM40 -> 0 | BO40: =BC40*BM$12 -> 0 | BP40: =$BP$5 -> 0.32 | BQ40: =BB40*$BP40 -> 3419.8272 | BR40: =BC40*BP40 -> 6839.6544 | BS40: =BB40+BE40+BG40+BI40+BK40+BN40+BQ40 -> 14555.64 | BT40: =BC40+BF40+BH40+BJ40+BL40+BO40+BR40 -> 29111.279 | BU40: =BT40/I40 -> 1380.9905
A41: AL | B41: S6a | C41: Serramento in acciaio rettangolare con porta inferiore a doppia anta apertura interna; con tre specchiature sopraluce: inferiore apribile a battente apertura esterna, centrale rettangolare opaca fissa, superiore a vasistas apertura interna.SOSTITUITO CON SERRAMENTO IN ALLUMINIO COMPOSTO DA PIU ELEMENTI ACCOPPIATI Reynaers SlimLine 38 (SL 38) Controtelaio composto da tubi rettangolari ancorato alla struttura principale mediante adeguate zanche annegate nel muro o viti di fissaggio, il telaio deve essere correttamente isolato e zincato per proteggerlo dalla corrosione. Vetro: 66.2 COOL-LITE 70-33#2 INDURITI / 20mm (aria-argon 90%) / 55.2 int. INDURITI Comprese lamiere di raccordo, memebrane e isolanti. | D41: 1700 | F41: 6200 | G41: =(D41*F41)/1000000 -> 10.54 | H41: 4 | I41: =G41*H41 -> 42.16 | J41: 0 | K41: =J41*$K$5 -> 0 | L41: =K41*$L$5 -> 0 | M41: =L41*$M$5 -> 0 | N41: =M41 -> 0 | O41: =N41*H41 -> 0 | P41: 0 | Q41: =P41*$Q$5 -> 0 | R41: 0 | S41: =R41*H41 -> 0 | T41: =$T$5 -> 650 | U41: =T41*$U$5 -> 650 | V41: =U41 -> 650 | W41: =V41*H41 -> 2600 | X41: =($X$5*2*(D41+F41))/1000 -> 347.6 | Y41: =X41*$Y$5 -> 347.6 | Z41: =Y41*$Z$5 -> 347.6 | AA41: =Z41*$AA$5 -> 347.6 | AB41: =AA41 -> 347.6 | AC41: =AB41*H41 -> 1390.4 | AD41: =$AD$5*G41 -> 158.1 | AE41: =AD41*H41 -> 632.4 | AF41: =1185+350+163+340 -> 2038 | AG41: =AF41*H41 -> 8152 | AH41: 0 | AI41: =AH41*H41 -> 0 | AJ41: 0 | AK41: =AJ41*H41 -> 0 | AL41: =$AL$5 -> 60 | AM41: =AL41*H41 -> 240 | AN41: =$AN$5*G41 -> 1422.9 | AO41: =AN41*H41 -> 5691.6 | AP41: 0 | AQ41: =AP41*H41 -> 0 | AR41: =($AR$5*2*(D41+F41))/1000 -> 553 | AS41: =AR41*H41 -> 2212 | AT41: 3000 | AU41: =AT41*H41 -> 12000 | AV41: =$AV$7*G41 -> 2466.36 | AW41: =AV41*H41 -> 9865.44 | AX41: 0 | AY41: =AX41*H41 -> 0 | AZ41: =$AZ$8*G41 -> 0 | BA41: =AZ41*H41 -> 0 | BB41: =N41+R41+V41+AB41+AD41+AF41+AH41+AJ41+AL41+AN41+AP41+AR41+AT41+AV41+AX41+AZ41 -> 10695.96 | BC41: =O41+S41+W41+AC41+AE41+AG41+AI41+AK41+AM41+AO41+AQ41+AS41+AU41+AW41+AY41+BA41 -> 42783.84 | BD41: =BC41/I41 -> 1014.797 | BE41: =BB41*$BE$5 -> 128.35152 | BF41: =BC41*$BE$5 -> 513.40608 | BG41: =BB41*$BG$5 -> 160.4394 | BH41: =BC41*$BG$5 -> 641.7576 | BI41: =BB41*$BI$5 -> 53.4798 | BJ41: =BC41*$BI$5 -> 213.9192 | BK41: =BB41*$BK$5 -> 106.9596 | BL41: =BC41*$BK$5 -> 427.8384 | BM41: =$BM$5 -> 0 | BN41: =BB41*BM41 -> 0 | BO41: =BC41*BM$12 -> 0 | BP41: =$BP$5 -> 0.32 | BQ41: =BB41*$BP41 -> 3422.7072 | BR41: =BC41*BP41 -> 13690.829 | BS41: =BB41+BE41+BG41+BI41+BK41+BN41+BQ41 -> 14567.898 | BT41: =BC41+BF41+BH41+BJ41+BL41+BO41+BR41 -> 58271.59 | BU41: =BT41/I41 -> 1382.1535
A42: AL | B42: S7 | C42: Serramento in acciaio rettangolare con porta inferiore a doppia anta apertura esterna US con pushbar; tre specchiature sopraluce: inferiore apribile a battente e apertura esterna, centrale rettangolare opaca fissa, superiore a vasistas apertura interna.SOSTITUITO CON SERRAMENTO IN ALLUMINIO COMPOSTO DA PIU ELEMENTI ACCOPPIATI Reynaers SlimLine 38 (SL 38) Controtelaio composto da tubi rettangolari ancorato alla struttura principale mediante adeguate zanche annegate nel muro o viti di fissaggio, il telaio deve essere correttamente isolato e zincato per proteggerlo dalla corrosione. Vetro: 66.2 COOL-LITE 70-33#2 INDURITI / 20mm (aria-argon 90%) / 55.2 int. INDURITI Comprese lamiere di raccordo, memebrane e isolanti. | D42: 1700 | F42: 6200 | G42: =(D42*F42)/1000000 -> 10.54 | H42: 1 | I42: =G42*H42 -> 10.54 | J42: 0 | K42: =J42*$K$5 -> 0 | L42: =K42*$L$5 -> 0 | M42: =L42*$M$5 -> 0 | N42: =M42 -> 0 | O42: =N42*H42 -> 0 | P42: 0 | Q42: =P42*$Q$5 -> 0 | R42: 0 | S42: =R42*H42 -> 0 | T42: =$T$5 -> 650 | U42: =T42*$U$5 -> 650 | V42: =U42 -> 650 | W42: =V42*H42 -> 650 | X42: =($X$5*2*(D42+F42))/1000 -> 347.6 | Y42: =X42*$Y$5 -> 347.6 | Z42: =Y42*$Z$5 -> 347.6 | AA42: =Z42*$AA$5 -> 347.6 | AB42: =AA42 -> 347.6 | AC42: =AB42*H42 -> 347.6 | AD42: =$AD$5*G42 -> 158.1 | AE42: =AD42*H42 -> 158.1 | AF42: =1889+350+163+340 -> 2742 | AG42: =AF42*H42 -> 2742 | AH42: =$AH$5*G42 -> 3608.896 | AI42: =AH42*H42 -> 3608.896 | AJ42: 0 | AK42: =AJ42*H42 -> 0 | AL42: =$AL$5 -> 60 | AM42: =AL42*H42 -> 60 | AN42: =$AN$5*G42 -> 1422.9 | AO42: =AN42*H42 -> 1422.9 | AP42: 0 | AQ42: =AP42*H42 -> 0 | AR42: =($AR$5*2*(D42+F42))/1000 -> 553 | AS42: =AR42*H42 -> 553 | AT42: 3000 | AU42: =AT42*H42 -> 3000 | AV42: =$AV$7*G42 -> 2466.36 | AW42: =AV42*H42 -> 2466.36 | AX42: 0 | AY42: =AX42*H42 -> 0 | AZ42: =$AZ$8*G42 -> 0 | BA42: =AZ42*H42 -> 0 | BB42: =N42+R42+V42+AB42+AD42+AF42+AH42+AJ42+AL42+AN42+AP42+AR42+AT42+AV42+AX42+AZ42 -> 15008.856 | BC42: =O42+S42+W42+AC42+AE42+AG42+AI42+AK42+AM42+AO42+AQ42+AS42+AU42+AW42+AY42+BA42 -> 15008.856 | BD42: =BC42/I42 -> 1423.9901 | BE42: =BB42*$BE$5 -> 180.10627 | BF42: =BC42*$BE$5 -> 180.10627 | BG42: =BB42*$BG$5 -> 225.13284 | BH42: =BC42*$BG$5 -> 225.13284 | BI42: =BB42*$BI$5 -> 75.04428 | BJ42: =BC42*$BI$5 -> 75.04428 | BK42: =BB42*$BK$5 -> 150.08856 | BL42: =BC42*$BK$5 -> 150.08856 | BM42: =$BM$5 -> 0 | BN42: =BB42*BM42 -> 0 | BO42: =BC42*BM$12 -> 0 | BP42: =$BP$5 -> 0.32 | BQ42: =BB42*$BP42 -> 4802.8339 | BR42: =BC42*BP42 -> 4802.8339 | BS42: =BB42+BE42+BG42+BI42+BK42+BN42+BQ42 -> 20442.062 | BT42: =BC42+BF42+BH42+BJ42+BL42+BO42+BR42 -> 20442.062 | BU42: =BT42/I42 -> 1939.4746
A43: AL | B43: S7a | C43: Serramento in acciaio rettangolare con porta inferiore a doppia anta apertura esterna US con pushbar; tre specchiature sopraluce: inferiore apribile a battente e apertura esterna, centrale rettangolare opaca fissa, superiore a vasistas apertura interna.SOSTITUITO CON SERRAMENTO IN ALLUMINIO COMPOSTO DA PIU ELEMENTI ACCOPPIATI Reynaers SlimLine 38 (SL 38) Controtelaio composto da tubi rettangolari ancorato alla struttura principale mediante adeguate zanche annegate nel muro o viti di fissaggio, il telaio deve essere correttamente isolato e zincato per proteggerlo dalla corrosione. Vetro: 66.2 COOL-LITE 70-33#2 INDURITI / 20mm (aria-argon 90%) / 55.2 int. INDURITI Comprese lamiere di raccordo, memebrane e isolanti. | D43: 1700 | F43: 6200 | G43: =(D43*F43)/1000000 -> 10.54 | H43: 1 | I43: =G43*H43 -> 10.54 | J43: 0 | K43: =J43*$K$5 -> 0 | L43: =K43*$L$5 -> 0 | M43: =L43*$M$5 -> 0 | N43: =M43 -> 0 | O43: =N43*H43 -> 0 | P43: 0 | Q43: =P43*$Q$5 -> 0 | R43: 0 | S43: =R43*H43 -> 0 | T43: =$T$5 -> 650 | U43: =T43*$U$5 -> 650 | V43: =U43 -> 650 | W43: =V43*H43 -> 650 | X43: =($X$5*2*(D43+F43))/1000 -> 347.6 | Y43: =X43*$Y$5 -> 347.6 | Z43: =Y43*$Z$5 -> 347.6 | AA43: =Z43*$AA$5 -> 347.6 | AB43: =AA43 -> 347.6 | AC43: =AB43*H43 -> 347.6 | AD43: =$AD$5*G43 -> 158.1 | AE43: =AD43*H43 -> 158.1 | AF43: =1889+350+163+340 -> 2742 | AG43: =AF43*H43 -> 2742 | AH43: =$AH$5*G43 -> 3608.896 | AI43: =AH43*H43 -> 3608.896 | AJ43: 0 | AK43: =AJ43*H43 -> 0 | AL43: =$AL$5 -> 60 | AM43: =AL43*H43 -> 60 | AN43: =$AN$5*G43 -> 1422.9 | AO43: =AN43*H43 -> 1422.9 | AP43: 0 | AQ43: =AP43*H43 -> 0 | AR43: =($AR$5*2*(D43+F43))/1000 -> 553 | AS43: =AR43*H43 -> 553 | AT43: 3000 | AU43: =AT43*H43 -> 3000 | AV43: =$AV$7*G43 -> 2466.36 | AW43: =AV43*H43 -> 2466.36 | AX43: 0 | AY43: =AX43*H43 -> 0 | AZ43: =$AZ$8*G43 -> 0 | BA43: =AZ43*H43 -> 0 | BB43: =N43+R43+V43+AB43+AD43+AF43+AH43+AJ43+AL43+AN43+AP43+AR43+AT43+AV43+AX43+AZ43 -> 15008.856 | BC43: =O43+S43+W43+AC43+AE43+AG43+AI43+AK43+AM43+AO43+AQ43+AS43+AU43+AW43+AY43+BA43 -> 15008.856 | BD43: =BC43/I43 -> 1423.9901 | BE43: =BB43*$BE$5 -> 180.10627 | BF43: =BC43*$BE$5 -> 180.10627 | BG43: =BB43*$BG$5 -> 225.13284 | BH43: =BC43*$BG$5 -> 225.13284 | BI43: =BB43*$BI$5 -> 75.04428 | BJ43: =BC43*$BI$5 -> 75.04428 | BK43: =BB43*$BK$5 -> 150.08856 | BL43: =BC43*$BK$5 -> 150.08856 | BM43: =$BM$5 -> 0 | BN43: =BB43*BM43 -> 0 | BO43: =BC43*BM$12 -> 0 | BP43: =$BP$5 -> 0.32 | BQ43: =BB43*$BP43 -> 4802.8339 | BR43: =BC43*BP43 -> 4802.8339 | BS43: =BB43+BE43+BG43+BI43+BK43+BN43+BQ43 -> 20442.062 | BT43: =BC43+BF43+BH43+BJ43+BL43+BO43+BR43 -> 20442.062 | BU43: =BT43/I43 -> 1939.4746
A44: AL | B44: S7b | C44: Serramento in acciaio rettangolare con porta inferiore a doppia anta apertura esterna US con pushbar; tre specchiature sopraluce:; inferiore apribile a battente e apertura esterna, centrale rettangolare opaca fissa, superiore a battente e apertura esterna.SOSTITUITO CON SERRAMENTO IN ALLUMINIO COMPOSTO DA PIU ELEMENTI ACCOPPIATI Reynaers SlimLine 38 (SL 38) Controtelaio composto da tubi rettangolari ancorato alla struttura principale mediante adeguate zanche annegate nel muro o viti di fissaggio, il telaio deve essere correttamente isolato e zincato per proteggerlo dalla corrosione. Vetro: 66.2 COOL-LITE 70-33#2 INDURITI / 20mm (aria-argon 90%) / 55.2 int. INDURITI Comprese lamiere di raccordo, memebrane e isolanti. | D44: 1700 | F44: 6200 | G44: =(D44*F44)/1000000 -> 10.54 | H44: 1 | I44: =G44*H44 -> 10.54 | J44: 0 | K44: =J44*$K$5 -> 0 | L44: =K44*$L$5 -> 0 | M44: =L44*$M$5 -> 0 | N44: =M44 -> 0 | O44: =N44*H44 -> 0 | P44: 0 | Q44: =P44*$Q$5 -> 0 | R44: 0 | S44: =R44*H44 -> 0 | T44: =$T$5 -> 650 | U44: =T44*$U$5 -> 650 | V44: =U44 -> 650 | W44: =V44*H44 -> 650 | X44: =($X$5*2*(D44+F44))/1000 -> 347.6 | Y44: =X44*$Y$5 -> 347.6 | Z44: =Y44*$Z$5 -> 347.6 | AA44: =Z44*$AA$5 -> 347.6 | AB44: =AA44 -> 347.6 | AC44: =AB44*H44 -> 347.6 | AD44: =$AD$5*G44 -> 158.1 | AE44: =AD44*H44 -> 158.1 | AF44: =1889+350+163+350 -> 2752 | AG44: =AF44*H44 -> 2752 | AH44: =$AH$5*G44 -> 3608.896 | AI44: =AH44*H44 -> 3608.896 | AJ44: 0 | AK44: =AJ44*H44 -> 0 | AL44: =$AL$5 -> 60 | AM44: =AL44*H44 -> 60 | AN44: =$AN$5*G44 -> 1422.9 | AO44: =AN44*H44 -> 1422.9 | AP44: 0 | AQ44: =AP44*H44 -> 0 | AR44: =($AR$5*2*(D44+F44))/1000 -> 553 | AS44: =AR44*H44 -> 553 | AT44: 3000 | AU44: =AT44*H44 -> 3000 | AV44: =$AV$7*G44 -> 2466.36 | AW44: =AV44*H44 -> 2466.36 | AX44: 0 | AY44: =AX44*H44 -> 0 | AZ44: =$AZ$8*G44 -> 0 | BA44: =AZ44*H44 -> 0 | BB44: =N44+R44+V44+AB44+AD44+AF44+AH44+AJ44+AL44+AN44+AP44+AR44+AT44+AV44+AX44+AZ44 -> 15018.856 | BC44: =O44+S44+W44+AC44+AE44+AG44+AI44+AK44+AM44+AO44+AQ44+AS44+AU44+AW44+AY44+BA44 -> 15018.856 | BD44: =BC44/I44 -> 1424.9389 | BE44: =BB44*$BE$5 -> 180.22627 | BF44: =BC44*$BE$5 -> 180.22627 | BG44: =BB44*$BG$5 -> 225.28284 | BH44: =BC44*$BG$5 -> 225.28284 | BI44: =BB44*$BI$5 -> 75.09428 | BJ44: =BC44*$BI$5 -> 75.09428 | BK44: =BB44*$BK$5 -> 150.18856 | BL44: =BC44*$BK$5 -> 150.18856 | BM44: =$BM$5 -> 0 | BN44: =BB44*BM44 -> 0 | BO44: =BC44*BM$12 -> 0 | BP44: =$BP$5 -> 0.32 | BQ44: =BB44*$BP44 -> 4806.0339 | BR44: =BC44*BP44 -> 4806.0339 | BS44: =BB44+BE44+BG44+BI44+BK44+BN44+BQ44 -> 20455.682 | BT44: =BC44+BF44+BH44+BJ44+BL44+BO44+BR44 -> 20455.682 | BU44: =BT44/I44 -> 1940.7668
A45: AL | B45: S8 | C45: Serramento in acciaio rettangolare con porta inferiore a doppia anta apertura esterna; tre specchiature sopraluce:; inferiore apribile a battente e apertura esterna, centrale rettangolare opaca fissa, superiore a battente e apertura esterna.SOSTITUITO CON SERRAMENTO IN ALLUMINIO COMPOSTO DA PIU ELEMENTI ACCOPPIATI Reynaers SlimLine 38 (SL 38) Controtelaio composto da tubi rettangolari ancorato alla struttura principale mediante adeguate zanche annegate nel muro o viti di fissaggio, il telaio deve essere correttamente isolato e zincato per proteggerlo dalla corrosione. Vetro: 66.2 COOL-LITE 70-33#2 INDURITI / 20mm (aria-argon 90%) / 55.2 int. INDURITI Comprese lamiere di raccordo, memebrane e isolanti. | D45: 1700 | F45: 6200 | G45: =(D45*F45)/1000000 -> 10.54 | H45: 4 | I45: =G45*H45 -> 42.16 | J45: 0 | K45: =J45*$K$5 -> 0 | L45: =K45*$L$5 -> 0 | M45: =L45*$M$5 -> 0 | N45: =M45 -> 0 | O45: =N45*H45 -> 0 | P45: 0 | Q45: =P45*$Q$5 -> 0 | R45: 0 | S45: =R45*H45 -> 0 | T45: =$T$5 -> 650 | U45: =T45*$U$5 -> 650 | V45: =U45 -> 650 | W45: =V45*H45 -> 2600 | X45: =($X$5*2*(D45+F45))/1000 -> 347.6 | Y45: =X45*$Y$5 -> 347.6 | Z45: =Y45*$Z$5 -> 347.6 | AA45: =Z45*$AA$5 -> 347.6 | AB45: =AA45 -> 347.6 | AC45: =AB45*H45 -> 1390.4 | AD45: =$AD$5*G45 -> 158.1 | AE45: =AD45*H45 -> 632.4 | AF45: =1185+350+163+350 -> 2048 | AG45: =AF45*H45 -> 8192 | AH45: =$AH$5*G45 -> 3608.896 | AI45: =AH45*H45 -> 14435.584 | AJ45: 0 | AK45: =AJ45*H45 -> 0 | AL45: =$AL$5 -> 60 | AM45: =AL45*H45 -> 240 | AN45: =$AN$5*G45 -> 1422.9 | AO45: =AN45*H45 -> 5691.6 | AP45: 0 | AQ45: =AP45*H45 -> 0 | AR45: =($AR$5*2*(D45+F45))/1000 -> 553 | AS45: =AR45*H45 -> 2212 | AT45: 3000 | AU45: =AT45*H45 -> 12000 | AV45: =$AV$7*G45 -> 2466.36 | AW45: =AV45*H45 -> 9865.44 | AX45: 0 | AY45: =AX45*H45 -> 0 | AZ45: =$AZ$8*G45 -> 0 | BA45: =AZ45*H45 -> 0 | BB45: =N45+R45+V45+AB45+AD45+AF45+AH45+AJ45+AL45+AN45+AP45+AR45+AT45+AV45+AX45+AZ45 -> 14314.856 | BC45: =O45+S45+W45+AC45+AE45+AG45+AI45+AK45+AM45+AO45+AQ45+AS45+AU45+AW45+AY45+BA45 -> 57259.424 | BD45: =BC45/I45 -> 1358.1457 | BE45: =BB45*$BE$5 -> 171.77827 | BF45: =BC45*$BE$5 -> 687.11309 | BG45: =BB45*$BG$5 -> 214.72284 | BH45: =BC45*$BG$5 -> 858.89136 | BI45: =BB45*$BI$5 -> 71.57428 | BJ45: =BC45*$BI$5 -> 286.29712 | BK45: =BB45*$BK$5 -> 143.14856 | BL45: =BC45*$BK$5 -> 572.59424 | BM45: =$BM$5 -> 0 | BN45: =BB45*BM45 -> 0 | BO45: =BC45*BM$12 -> 0 | BP45: =$BP$5 -> 0.32 | BQ45: =BB45*$BP45 -> 4580.7539 | BR45: =BC45*BP45 -> 18323.016 | BS45: =BB45+BE45+BG45+BI45+BK45+BN45+BQ45 -> 19496.834 | BT45: =BC45+BF45+BH45+BJ45+BL45+BO45+BR45 -> 77987.335 | BU45: =BT45/I45 -> 1849.7945
B46: S9 | C46: Serramento in acciaio con volta circolare fissa specchiatura inferiore con vetri fissi, sopraluce rettangolare fisso e apribile vasistas di ventilazione apertura meccanizzata. Controtelaio composto da tubi rettangolari ancorato alla struttura principale mediante adeguate zanche annegate nel muro o viti di fissaggio, il telaio deve essere correttamente isolato e zincato per proteggerlo dalla corrosione. Vetro: 66.2 COOL-LITE 70-33#2 INDURITI / 20mm (aria-argon 90%) / 55.2 int. INDURITI Comprese lamiere di raccordo, memebrane e isolanti. | D46: 3000 | F46: 5900 | G46: =(D46*F46)/1000000 -> 17.7 | H46: 2 | I46: =G46*H46 -> 35.4 | J46: 0 | K46: =J46*$K$5 -> 0 | L46: =K46*$L$5 -> 0 | M46: =L46*$M$5 -> 0 | N46: =M46 -> 0 | O46: =N46*H46 -> 0 | P46: 0 | Q46: =P46*$Q$5 -> 0 | R46: 0 | S46: =R46*H46 -> 0 | T46: =$T$5 -> 650 | U46: =T46*$U$5 -> 650 | V46: =U46 -> 650 | W46: =V46*H46 -> 1300 | X46: =($X$5*2*(D46+F46))/1000 -> 391.6 | Y46: =X46*$Y$5 -> 391.6 | Z46: =Y46*$Z$5 -> 391.6 | AA46: =Z46*$AA$5 -> 391.6 | AB46: =AA46 -> 391.6 | AC46: =AB46*H46 -> 783.2 | AD46: =$AD$5*G46 -> 265.5 | AE46: =AD46*H46 -> 531 | AF46: 0 | AG46: =AF46*H46 -> 0 | AH46: =$AH$5*G46 -> 6060.48 | AI46: =AH46*H46 -> 12120.96 | AJ46: 5965 | AK46: =AJ46*H46 -> 11930 | AL46: =$AL$5 -> 60 | AM46: =AL46*H46 -> 120 | AN46: =$AN$7*G46 -> 4779 | AO46: =AN46*H46 -> 9558 | AP46: 0 | AQ46: =AP46*H46 -> 0 | AR46: =($AR$5*2*(D46+F46))/1000 -> 623 | AS46: =AR46*H46 -> 1246 | AT46: 0 | AU46: =AT46*H46 -> 0 | AV46: =$AV$7*G46 -> 4141.8 | AW46: =AV46*H46 -> 8283.6 | AX46: 0 | AY46: =AX46*H46 -> 0 | AZ46: =$AZ$8*G46 -> 0 | BA46: =AZ46*H46 -> 0 | BB46: =N46+R46+V46+AB46+AD46+AF46+AH46+AJ46+AL46+AN46+AP46+AR46+AT46+AV46+AX46+AZ46 -> 22936.38 | BC46: =O46+S46+W46+AC46+AE46+AG46+AI46+AK46+AM46+AO46+AQ46+AS46+AU46+AW46+AY46+BA46 -> 45872.76 | BD46: =BC46/I46 -> 1295.8407 | BE46: =BB46*$BE$5 -> 275.23656 | BF46: =BC46*$BE$5 -> 550.47312 | BG46: =BB46*$BG$5 -> 344.0457 | BH46: =BC46*$BG$5 -> 688.0914 | BI46: =BB46*$BI$5 -> 114.6819 | BJ46: =BC46*$BI$5 -> 229.3638 | BK46: =BB46*$BK$5 -> 229.3638 | BL46: =BC46*$BK$5 -> 458.7276 | BM46: =$BM$5 -> 0 | BN46: =BB46*BM46 -> 0 | BO46: =BC46*BM$12 -> 0 | BP46: =$BP$5 -> 0.32 | BQ46: =BB46*$BP46 -> 7339.6416 | BR46: =BC46*BP46 -> 14679.283 | BS46: =BB46+BE46+BG46+BI46+BK46+BN46+BQ46 -> 31239.35 | BT46: =BC46+BF46+BH46+BJ46+BL46+BO46+BR46 -> 62478.699 | BU46: =BT46/I46 -> 1764.935
B47: FW | C47: CONNECTION - SISTEMA FACCIATA MONTANTI E TRAVERSI CON CARTELLA : Reynaers ConceptWall 50/60 (CW50-CW60) Reynaers SlimLine 38 (SL 38) Reynaers ConceptWall Outward Opening GB Secondo documento di gara Compresi: partizione EI60 FISSA Reynaers ConceptWall 50-FP (CW 50-FP) Vetro: 66.2 COOL-LITE 70-33#2 INDURITI / 20mm (aria-argon 90%) / 55.2 int. INDURITI Comprese lamiere di finitura estern sv. 500mm , isolanti e staffe. | D47: 1000 | F47: 1000 | G47: =(D47*F47)/1000000 -> 1 | H47: 1 | I47: =G47*H47 -> 1 | J47: 0 | K47: =J47*$K$5 -> 0 | L47: =K47*$L$5 -> 0 | M47: =L47*$M$5 -> 0 | N47: =M47 -> 0 | O47: =N47*H47 -> 0 | P47: 0 | Q47: =P47*$Q$5 -> 0 | R47: 0 | S47: =R47*H47 -> 0 | T47: 0 | U47: =T47*$U$5 -> 0 | V47: 0 | W47: =V47*H47 -> 0 | X47: 0 | Y47: =X47*$Y$5 -> 0 | Z47: =Y47*$Z$5 -> 0 | AA47: =Z47*$AA$5 -> 0 | AB47: =AA47 -> 0 | AC47: =AB47*H47 -> 0 | AD47: 0 | AE47: =AD47*H47 -> 0 | AF47: 0 | AG47: =AF47*H47 -> 0 | AH47: 0 | AI47: =AH47*H47 -> 0 | AJ47: 0 | AK47: =AJ47*H47 -> 0 | AL47: 0 | AM47: =AL47*H47 -> 0 | AN47: 0 | AO47: =AN47*H47 -> 0 | AP47: 0 | AQ47: =AP47*H47 -> 0 | AR47: 0 | AS47: =AR47*H47 -> 0 | AT47: 0 | AU47: =AT47*H47 -> 0 | AV47: 0 | AW47: =AV47*H47 -> 0 | AX47: 95000 | AY47: =AX47*H47 -> 95000 | AZ47: 0 | BA47: =AZ47*H47 -> 0 | BB47: =N47+R47+V47+AB47+AD47+AF47+AH47+AJ47+AL47+AN47+AP47+AR47+AT47+AV47+AX47+AZ47 -> 95000 | BC47: =O47+S47+W47+AC47+AE47+AG47+AI47+AK47+AM47+AO47+AQ47+AS47+AU47+AW47+AY47+BA47 -> 95000 | BD47: =BC47/I47 -> 95000 | BE47: =BB47*$BE$5 -> 1140 | BF47: =BC47*$BE$5 -> 1140 | BG47: =BB47*$BG$5 -> 1425 | BH47: =BC47*$BG$5 -> 1425 | BI47: =BB47*$BI$5 -> 475 | BJ47: =BC47*$BI$5 -> 475 | BK47: =BB47*$BK$5 -> 950 | BL47: =BC47*$BK$5 -> 950 | BM47: =$BM$5 -> 0 | BN47: =BB47*BM47 -> 0 | BO47: =BC47*BM$12 -> 0 | BP47: =$BP$5 -> 0.32 | BQ47: =BB47*$BP47 -> 30400 | BR47: =BC47*BP47 -> 30400 | BS47: =BB47+BE47+BG47+BI47+BK47+BN47+BQ47 -> 129390 | BT47: =BC47+BF47+BH47+BJ47+BL47+BO47+BR47 -> 129390 | BU47: =BT47/I47 -> 129390
G48: =(D48*F48)/1000000 -> 0 | I48: =G48*H48 -> 0 | J48: 0 | K48: =J48*$K$5 -> 0 | L48: =K48*$L$5 -> 0 | M48: =L48*$M$5 -> 0 | N48: =M48 -> 0 | O48: =N48*H48 -> 0 | P48: 0 | Q48: =P48*$Q$5 -> 0 | R48: 0 | S48: =R48*H48 -> 0 | T48: 0 | U48: =T48*$U$5 -> 0 | V48: 0 | W48: =V48*H48 -> 0 | X48: 0 | Y48: =X48*$Y$5 -> 0 | Z48: =Y48*$Z$5 -> 0 | AA48: =Z48*$AA$5 -> 0 | AB48: =AA48 -> 0 | AC48: =AB48*H48 -> 0 | AD48: 0 | AE48: =AD48*H48 -> 0 | AF48: 0 | AG48: =AF48*H48 -> 0 | AH48: 0 | AI48: =AH48*H48 -> 0 | AJ48: 0 | AK48: =AJ48*H48 -> 0 | AL48: 0 | AM48: =AL48*H48 -> 0 | AN48: 0 | AO48: =AN48*H48 -> 0 | AP48: 0 | AQ48: =AP48*H48 -> 0 | AR48: 0 | AS48: =AR48*H48 -> 0 | AT48: 0 | AU48: =AT48*H48 -> 0 | AV48: 0 | AW48: =AV48*H48 -> 0 | AX48: 0 | AY48: =AX48*H48 -> 0 | AZ48: 0 | BA48: =AZ48*H48 -> 0 | BB48: =N48+R48+V48+AB48+AD48+AF48+AH48+AJ48+AL48+AN48+AP48+AR48+AT48+AV48+AX48+AZ48 -> 0 | BC48: =O48+S48+W48+AC48+AE48+AG48+AI48+AK48+AM48+AO48+AQ48+AS48+AU48+AW48+AY48+BA48 -> 0 | BD48: =BC48/I48 -> #DIV/0! | BE48: =BB48*$BE$5 -> 0 | BF48: =BC48*$BE$5 -> 0 | BG48: =BB48*$BG$5 -> 0 | BH48: =BC48*$BG$5 -> 0 | BI48: =BB48*$BI$5 -> 0 | BJ48: =BC48*$BI$5 -> 0 | BK48: =BB48*$BK$5 -> 0 | BL48: =BC48*$BK$5 -> 0 | BM48: =$BM$5 -> 0 | BN48: =BB48*BM48 -> 0 | BO48: =BC48*BM$12 -> 0 | BP48: =$BP$5 -> 0.32 | BQ48: =BB48*$BP48 -> 0 | BR48: =BC48*BP48 -> 0 | BS48: =BB48+BE48+BG48+BI48+BK48+BN48+BQ48 -> 0 | BT48: =BC48+BF48+BH48+BJ48+BL48+BO48+BR48 -> 0 | BU48: =BT48/I48 -> #DIV/0!
G49: =(D49*F49)/1000000 -> 0 | I49: =G49*H49 -> 0 | J49: 0 | K49: =J49*$K$5 -> 0 | L49: =K49*$L$5 -> 0 | M49: =L49*$M$5 -> 0 | N49: =M49 -> 0 | O49: =N49*H49 -> 0 | P49: 0 | Q49: =P49*$Q$5 -> 0 | R49: 0 | S49: =R49*H49 -> 0 | T49: 0 | U49: =T49*$U$5 -> 0 | V49: 0 | W49: =V49*H49 -> 0 | X49: 0 | Y49: =X49*$Y$5 -> 0 | Z49: =Y49*$Z$5 -> 0 | AA49: =Z49*$AA$5 -> 0 | AB49: =AA49 -> 0 | AC49: =AB49*H49 -> 0 | AD49: 0 | AE49: =AD49*H49 -> 0 | AF49: 0 | AG49: =AF49*H49 -> 0 | AH49: 0 | AI49: =AH49*H49 -> 0 | AJ49: 0 | AK49: =AJ49*H49 -> 0 | AL49: 0 | AM49: =AL49*H49 -> 0 | AN49: 0 | AO49: =AN49*H49 -> 0 | AP49: 0 | AQ49: =AP49*H49 -> 0 | AR49: 0 | AS49: =AR49*H49 -> 0 | AT49: 0 | AU49: =AT49*H49 -> 0 | AV49: 0 | AW49: =AV49*H49 -> 0 | AX49: 0 | AY49: =AX49*H49 -> 0 | AZ49: 0 | BA49: =AZ49*H49 -> 0 | BB49: =N49+R49+V49+AB49+AD49+AF49+AH49+AJ49+AL49+AN49+AP49+AR49+AT49+AV49+AX49+AZ49 -> 0 | BC49: =O49+S49+W49+AC49+AE49+AG49+AI49+AK49+AM49+AO49+AQ49+AS49+AU49+AW49+AY49+BA49 -> 0 | BD49: =BC49/I49 -> #DIV/0! | BE49: =BB49*$BE$5 -> 0 | BF49: =BC49*$BE$5 -> 0 | BG49: =BB49*$BG$5 -> 0 | BH49: =BC49*$BG$5 -> 0 | BI49: =BB49*$BI$5 -> 0 | BJ49: =BC49*$BI$5 -> 0 | BK49: =BB49*$BK$5 -> 0 | BL49: =BC49*$BK$5 -> 0 | BM49: =$BM$5 -> 0 | BN49: =BB49*BM49 -> 0 | BO49: =BC49*BM$12 -> 0 | BP49: =$BP$5 -> 0.32 | BQ49: =BB49*$BP49 -> 0 | BR49: =BC49*BP49 -> 0 | BS49: =BB49+BE49+BG49+BI49+BK49+BN49+BQ49 -> 0 | BT49: =BC49+BF49+BH49+BJ49+BL49+BO49+BR49 -> 0 | BU49: =BT49/I49 -> #DIV/0!
G50: =(D50*F50)/1000000 -> 0 | I50: =G50*H50 -> 0 | J50: 0 | K50: =J50*$K$5 -> 0 | L50: =K50*$L$5 -> 0 | M50: =L50*$M$5 -> 0 | N50: =M50 -> 0 | O50: =N50*H50 -> 0 | P50: 0 | Q50: =P50*$Q$5 -> 0 | R50: 0 | S50: =R50*H50 -> 0 | T50: 0 | U50: =T50*$U$5 -> 0 | V50: 0 | W50: =V50*H50 -> 0 | X50: 0 | Y50: =X50*$Y$5 -> 0 | Z50: =Y50*$Z$5 -> 0 | AA50: =Z50*$AA$5 -> 0 | AB50: =AA50 -> 0 | AC50: =AB50*H50 -> 0 | AD50: 0 | AE50: =AD50*H50 -> 0 | AF50: 0 | AG50: =AF50*H50 -> 0 | AH50: 0 | AI50: =AH50*H50 -> 0 | AJ50: 0 | AK50: =AJ50*H50 -> 0 | AL50: 0 | AM50: =AL50*H50 -> 0 | AN50: 0 | AO50: =AN50*H50 -> 0 | AP50: 0 | AQ50: =AP50*H50 -> 0 | AR50: 0 | AS50: =AR50*H50 -> 0 | AT50: 0 | AU50: =AT50*H50 -> 0 | AV50: 0 | AW50: =AV50*H50 -> 0 | AX50: 0 | AY50: =AX50*H50 -> 0 | AZ50: 0 | BA50: =AZ50*H50 -> 0 | BB50: =N50+R50+V50+AB50+AD50+AF50+AH50+AJ50+AL50+AN50+AP50+AR50+AT50+AV50+AX50+AZ50 -> 0 | BC50: =O50+S50+W50+AC50+AE50+AG50+AI50+AK50+AM50+AO50+AQ50+AS50+AU50+AW50+AY50+BA50 -> 0 | BD50: =BC50/I50 -> #DIV/0! | BE50: =BB50*$BE$5 -> 0 | BF50: =BC50*$BE$5 -> 0 | BG50: =BB50*$BG$5 -> 0 | BH50: =BC50*$BG$5 -> 0 | BI50: =BB50*$BI$5 -> 0 | BJ50: =BC50*$BI$5 -> 0 | BK50: =BB50*$BK$5 -> 0 | BL50: =BC50*$BK$5 -> 0 | BM50: =$BM$5 -> 0 | BN50: =BB50*BM50 -> 0 | BO50: =BC50*BM$12 -> 0 | BP50: =$BP$5 -> 0.32 | BQ50: =BB50*$BP50 -> 0 | BR50: =BC50*BP50 -> 0 | BS50: =BB50+BE50+BG50+BI50+BK50+BN50+BQ50 -> 0 | BT50: =BC50+BF50+BH50+BJ50+BL50+BO50+BR50 -> 0 | BU50: =BT50/I50 -> #DIV/0!
G51: =(D51*F51)/1000000 -> 0 | I51: =G51*H51 -> 0 | J51: 0 | K51: =J51*$K$5 -> 0 | L51: =K51*$L$5 -> 0 | M51: =L51*$M$5 -> 0 | N51: =M51 -> 0 | O51: =N51*H51 -> 0 | P51: 0 | Q51: =P51*$Q$5 -> 0 | R51: 0 | S51: =R51*H51 -> 0 | T51: 0 | U51: =T51*$U$5 -> 0 | V51: 0 | W51: =V51*H51 -> 0 | X51: 0 | Y51: =X51*$Y$5 -> 0 | Z51: =Y51*$Z$5 -> 0 | AA51: =Z51*$AA$5 -> 0 | AB51: =AA51 -> 0 | AC51: =AB51*H51 -> 0 | AD51: 0 | AE51: =AD51*H51 -> 0 | AF51: 0 | AG51: =AF51*H51 -> 0 | AH51: 0 | AI51: =AH51*H51 -> 0 | AJ51: 0 | AK51: =AJ51*H51 -> 0 | AL51: 0 | AM51: =AL51*H51 -> 0 | AN51: 0 | AO51: =AN51*H51 -> 0 | AP51: 0 | AQ51: =AP51*H51 -> 0 | AR51: 0 | AS51: =AR51*H51 -> 0 | AT51: 0 | AU51: =AT51*H51 -> 0 | AV51: 0 | AW51: =AV51*H51 -> 0 | AX51: 0 | AY51: =AX51*H51 -> 0 | AZ51: 0 | BA51: =AZ51*H51 -> 0 | BB51: =N51+R51+V51+AB51+AD51+AF51+AH51+AJ51+AL51+AN51+AP51+AR51+AT51+AV51+AX51+AZ51 -> 0 | BC51: =O51+S51+W51+AC51+AE51+AG51+AI51+AK51+AM51+AO51+AQ51+AS51+AU51+AW51+AY51+BA51 -> 0 | BD51: =BC51/I51 -> #DIV/0! | BE51: =BB51*$BE$5 -> 0 | BF51: =BC51*$BE$5 -> 0 | BG51: =BB51*$BG$5 -> 0 | BH51: =BC51*$BG$5 -> 0 | BI51: =BB51*$BI$5 -> 0 | BJ51: =BC51*$BI$5 -> 0 | BK51: =BB51*$BK$5 -> 0 | BL51: =BC51*$BK$5 -> 0 | BM51: =$BM$5 -> 0 | BN51: =BB51*BM51 -> 0 | BO51: =BC51*BM$12 -> 0 | BP51: =$BP$5 -> 0.32 | BQ51: =BB51*$BP51 -> 0 | BR51: =BC51*BP51 -> 0 | BS51: =BB51+BE51+BG51+BI51+BK51+BN51+BQ51 -> 0 | BT51: =BC51+BF51+BH51+BJ51+BL51+BO51+BR51 -> 0 | BU51: =BT51/I51 -> #DIV/0!
G52: =(D52*F52)/1000000 -> 0 | I52: =G52*H52 -> 0 | J52: 0 | K52: =J52*$K$5 -> 0 | L52: =K52*$L$5 -> 0 | M52: =L52*$M$5 -> 0 | N52: =M52 -> 0 | O52: =N52*H52 -> 0 | P52: 0 | Q52: =P52*$Q$5 -> 0 | R52: 0 | S52: =R52*H52 -> 0 | T52: 0 | U52: =T52*$U$5 -> 0 | V52: 0 | W52: =V52*H52 -> 0 | X52: 0 | Y52: =X52*$Y$5 -> 0 | Z52: =Y52*$Z$5 -> 0 | AA52: =Z52*$AA$5 -> 0 | AB52: =AA52 -> 0 | AC52: =AB52*H52 -> 0 | AD52: 0 | AE52: =AD52*H52 -> 0 | AF52: 0 | AG52: =AF52*H52 -> 0 | AH52: 0 | AI52: =AH52*H52 -> 0 | AJ52: 0 | AK52: =AJ52*H52 -> 0 | AL52: 0 | AM52: =AL52*H52 -> 0 | AN52: 0 | AO52: =AN52*H52 -> 0 | AP52: 0 | AQ52: =AP52*H52 -> 0 | AR52: 0 | AS52: =AR52*H52 -> 0 | AT52: 0 | AU52: =AT52*H52 -> 0 | AV52: 0 | AW52: =AV52*H52 -> 0 | AX52: 0 | AY52: =AX52*H52 -> 0 | AZ52: 0 | BA52: =AZ52*H52 -> 0 | BB52: =N52+R52+V52+AB52+AD52+AF52+AH52+AJ52+AL52+AN52+AP52+AR52+AT52+AV52+AX52+AZ52 -> 0 | BC52: =O52+S52+W52+AC52+AE52+AG52+AI52+AK52+AM52+AO52+AQ52+AS52+AU52+AW52+AY52+BA52 -> 0 | BD52: =BC52/I52 -> #DIV/0! | BE52: =BB52*$BE$5 -> 0 | BF52: =BC52*$BE$5 -> 0 | BG52: =BB52*$BG$5 -> 0 | BH52: =BC52*$BG$5 -> 0 | BI52: =BB52*$BI$5 -> 0 | BJ52: =BC52*$BI$5 -> 0 | BK52: =BB52*$BK$5 -> 0 | BL52: =BC52*$BK$5 -> 0 | BM52: =$BM$5 -> 0 | BN52: =BB52*BM52 -> 0 | BO52: =BC52*BM$12 -> 0 | BP52: =$BP$5 -> 0.32 | BQ52: =BB52*$BP52 -> 0 | BR52: =BC52*BP52 -> 0 | BS52: =BB52+BE52+BG52+BI52+BK52+BN52+BQ52 -> 0 | BT52: =BC52+BF52+BH52+BJ52+BL52+BO52+BR52 -> 0 | BU52: =BT52/I52 -> #DIV/0!
G53: =(D53*F53)/1000000 -> 0 | I53: =G53*H53 -> 0 | J53: 0 | K53: =J53*$K$5 -> 0 | L53: =K53*$L$5 -> 0 | M53: =L53*$M$5 -> 0 | N53: =M53 -> 0 | O53: =N53*H53 -> 0 | P53: 0 | Q53: =P53*$Q$5 -> 0 | R53: 0 | S53: =R53*H53 -> 0 | T53: 0 | U53: =T53*$U$5 -> 0 | V53: 0 | W53: =V53*H53 -> 0 | X53: 0 | Y53: =X53*$Y$5 -> 0 | Z53: =Y53*$Z$5 -> 0 | AA53: =Z53*$AA$5 -> 0 | AB53: =AA53 -> 0 | AC53: =AB53*H53 -> 0 | AD53: 0 | AE53: =AD53*H53 -> 0 | AF53: 0 | AG53: =AF53*H53 -> 0 | AH53: 0 | AI53: =AH53*H53 -> 0 | AJ53: 0 | AK53: =AJ53*H53 -> 0 | AL53: 0 | AM53: =AL53*H53 -> 0 | AN53: 0 | AO53: =AN53*H53 -> 0 | AP53: 0 | AQ53: =AP53*H53 -> 0 | AR53: 0 | AS53: =AR53*H53 -> 0 | AT53: 0 | AU53: =AT53*H53 -> 0 | AV53: 0 | AW53: =AV53*H53 -> 0 | AX53: 0 | AY53: =AX53*H53 -> 0 | AZ53: 0 | BA53: =AZ53*H53 -> 0 | BB53: =N53+R53+V53+AB53+AD53+AF53+AH53+AJ53+AL53+AN53+AP53+AR53+AT53+AV53+AX53+AZ53 -> 0 | BC53: =O53+S53+W53+AC53+AE53+AG53+AI53+AK53+AM53+AO53+AQ53+AS53+AU53+AW53+AY53+BA53 -> 0 | BD53: =BC53/I53 -> #DIV/0! | BE53: =BB53*$BE$5 -> 0 | BF53: =BC53*$BE$5 -> 0 | BG53: =BB53*$BG$5 -> 0 | BH53: =BC53*$BG$5 -> 0 | BI53: =BB53*$BI$5 -> 0 | BJ53: =BC53*$BI$5 -> 0 | BK53: =BB53*$BK$5 -> 0 | BL53: =BC53*$BK$5 -> 0 | BM53: =$BM$5 -> 0 | BN53: =BB53*BM53 -> 0 | BO53: =BC53*BM$12 -> 0 | BP53: =$BP$5 -> 0.32 | BQ53: =BB53*$BP53 -> 0 | BR53: =BC53*BP53 -> 0 | BS53: =BB53+BE53+BG53+BI53+BK53+BN53+BQ53 -> 0 | BT53: =BC53+BF53+BH53+BJ53+BL53+BO53+BR53 -> 0 | BU53: =BT53/I53 -> #DIV/0!
G54: =(D54*F54)/1000000 -> 0 | I54: =G54*H54 -> 0 | J54: 0 | K54: =J54*$K$5 -> 0 | L54: =K54*$L$5 -> 0 | M54: =L54*$M$5 -> 0 | N54: =M54 -> 0 | O54: =N54*H54 -> 0 | P54: 0 | Q54: =P54*$Q$5 -> 0 | R54: 0 | S54: =R54*H54 -> 0 | T54: 0 | U54: =T54*$U$5 -> 0 | V54: 0 | W54: =V54*H54 -> 0 | X54: 0 | Y54: =X54*$Y$5 -> 0 | Z54: =Y54*$Z$5 -> 0 | AA54: =Z54*$AA$5 -> 0 | AB54: =AA54 -> 0 | AC54: =AB54*H54 -> 0 | AD54: 0 | AE54: =AD54*H54 -> 0 | AF54: 0 | AG54: =AF54*H54 -> 0 | AH54: 0 | AI54: =AH54*H54 -> 0 | AJ54: 0 | AK54: =AJ54*H54 -> 0 | AL54: 0 | AM54: =AL54*H54 -> 0 | AN54: 0 | AO54: =AN54*H54 -> 0 | AP54: 0 | AQ54: =AP54*H54 -> 0 | AR54: 0 | AS54: =AR54*H54 -> 0 | AT54: 0 | AU54: =AT54*H54 -> 0 | AV54: 0 | AW54: =AV54*H54 -> 0 | AX54: 0 | AY54: =AX54*H54 -> 0 | AZ54: 0 | BA54: =AZ54*H54 -> 0 | BB54: =N54+R54+V54+AB54+AD54+AF54+AH54+AJ54+AL54+AN54+AP54+AR54+AT54+AV54+AX54+AZ54 -> 0 | BC54: =O54+S54+W54+AC54+AE54+AG54+AI54+AK54+AM54+AO54+AQ54+AS54+AU54+AW54+AY54+BA54 -> 0 | BD54: =BC54/I54 -> #DIV/0! | BE54: =BB54*$BE$5 -> 0 | BF54: =BC54*$BE$5 -> 0 | BG54: =BB54*$BG$5 -> 0 | BH54: =BC54*$BG$5 -> 0 | BI54: =BB54*$BI$5 -> 0 | BJ54: =BC54*$BI$5 -> 0 | BK54: =BB54*$BK$5 -> 0 | BL54: =BC54*$BK$5 -> 0 | BM54: =$BM$5 -> 0 | BN54: =BB54*BM54 -> 0 | BO54: =BC54*BM$12 -> 0 | BP54: =$BP$5 -> 0.32 | BQ54: =BB54*$BP54 -> 0 | BR54: =BC54*BP54 -> 0 | BS54: =BB54+BE54+BG54+BI54+BK54+BN54+BQ54 -> 0 | BT54: =BC54+BF54+BH54+BJ54+BL54+BO54+BR54 -> 0 | BU54: =BT54/I54 -> #DIV/0!
G55: =(D55*F55)/1000000 -> 0 | I55: =G55*H55 -> 0 | J55: 0 | K55: =J55*$K$5 -> 0 | L55: =K55*$L$5 -> 0 | M55: =L55*$M$5 -> 0 | N55: =M55 -> 0 | O55: =N55*H55 -> 0 | P55: 0 | Q55: =P55*$Q$5 -> 0 | R55: 0 | S55: =R55*H55 -> 0 | T55: 0 | U55: =T55*$U$5 -> 0 | V55: 0 | W55: =V55*H55 -> 0 | X55: 0 | Y55: =X55*$Y$5 -> 0 | Z55: =Y55*$Z$5 -> 0 | AA55: =Z55*$AA$5 -> 0 | AB55: =AA55 -> 0 | AC55: =AB55*H55 -> 0 | AD55: 0 | AE55: =AD55*H55 -> 0 | AF55: 0 | AG55: =AF55*H55 -> 0 | AH55: 0 | AI55: =AH55*H55 -> 0 | AJ55: 0 | AK55: =AJ55*H55 -> 0 | AL55: 0 | AM55: =AL55*H55 -> 0 | AN55: 0 | AO55: =AN55*H55 -> 0 | AP55: 0 | AQ55: =AP55*H55 -> 0 | AR55: 0 | AS55: =AR55*H55 -> 0 | AT55: 0 | AU55: =AT55*H55 -> 0 | AV55: 0 | AW55: =AV55*H55 -> 0 | AX55: 0 | AY55: =AX55*H55 -> 0 | AZ55: 0 | BA55: =AZ55*H55 -> 0 | BB55: =N55+R55+V55+AB55+AD55+AF55+AH55+AJ55+AL55+AN55+AP55+AR55+AT55+AV55+AX55+AZ55 -> 0 | BC55: =O55+S55+W55+AC55+AE55+AG55+AI55+AK55+AM55+AO55+AQ55+AS55+AU55+AW55+AY55+BA55 -> 0 | BD55: =BC55/I55 -> #DIV/0! | BE55: =BB55*$BE$5 -> 0 | BF55: =BC55*$BE$5 -> 0 | BG55: =BB55*$BG$5 -> 0 | BH55: =BC55*$BG$5 -> 0 | BI55: =BB55*$BI$5 -> 0 | BJ55: =BC55*$BI$5 -> 0 | BK55: =BB55*$BK$5 -> 0 | BL55: =BC55*$BK$5 -> 0 | BM55: =$BM$5 -> 0 | BN55: =BB55*BM55 -> 0 | BO55: =BC55*BM$12 -> 0 | BP55: =$BP$5 -> 0.32 | BQ55: =BB55*$BP55 -> 0 | BR55: =BC55*BP55 -> 0 | BS55: =BB55+BE55+BG55+BI55+BK55+BN55+BQ55 -> 0 | BT55: =BC55+BF55+BH55+BJ55+BL55+BO55+BR55 -> 0 | BU55: =BT55/I55 -> #DIV/0!
G56: =(D56*F56)/1000000 -> 0 | I56: =G56*H56 -> 0 | J56: 0 | K56: =J56*$K$5 -> 0 | L56: =K56*$L$5 -> 0 | M56: =L56*$M$5 -> 0 | N56: =M56 -> 0 | O56: =N56*H56 -> 0 | P56: 0 | Q56: =P56*$Q$5 -> 0 | R56: 0 | S56: =R56*H56 -> 0 | T56: 0 | U56: =T56*$U$5 -> 0 | V56: 0 | W56: =V56*H56 -> 0 | X56: 0 | Y56: =X56*$Y$5 -> 0 | Z56: =Y56*$Z$5 -> 0 | AA56: =Z56*$AA$5 -> 0 | AB56: =AA56 -> 0 | AC56: =AB56*H56 -> 0 | AD56: 0 | AE56: =AD56*H56 -> 0 | AF56: 0 | AG56: =AF56*H56 -> 0 | AH56: 0 | AI56: =AH56*H56 -> 0 | AJ56: 0 | AK56: =AJ56*H56 -> 0 | AL56: 0 | AM56: =AL56*H56 -> 0 | AN56: 0 | AO56: =AN56*H56 -> 0 | AP56: 0 | AQ56: =AP56*H56 -> 0 | AR56: 0 | AS56: =AR56*H56 -> 0 | AT56: 0 | AU56: =AT56*H56 -> 0 | AV56: 0 | AW56: =AV56*H56 -> 0 | AX56: 0 | AY56: =AX56*H56 -> 0 | AZ56: 0 | BA56: =AZ56*H56 -> 0 | BB56: =N56+R56+V56+AB56+AD56+AF56+AH56+AJ56+AL56+AN56+AP56+AR56+AT56+AV56+AX56+AZ56 -> 0 | BC56: =O56+S56+W56+AC56+AE56+AG56+AI56+AK56+AM56+AO56+AQ56+AS56+AU56+AW56+AY56+BA56 -> 0 | BD56: =BC56/I56 -> #DIV/0! | BE56: =BB56*$BE$5 -> 0 | BF56: =BC56*$BE$5 -> 0 | BG56: =BB56*$BG$5 -> 0 | BH56: =BC56*$BG$5 -> 0 | BI56: =BB56*$BI$5 -> 0 | BJ56: =BC56*$BI$5 -> 0 | BK56: =BB56*$BK$5 -> 0 | BL56: =BC56*$BK$5 -> 0 | BM56: =$BM$5 -> 0 | BN56: =BB56*BM56 -> 0 | BO56: =BC56*BM$12 -> 0 | BP56: =$BP$5 -> 0.32 | BQ56: =BB56*$BP56 -> 0 | BR56: =BC56*BP56 -> 0 | BS56: =BB56+BE56+BG56+BI56+BK56+BN56+BQ56 -> 0 | BT56: =BC56+BF56+BH56+BJ56+BL56+BO56+BR56 -> 0 | BU56: =BT56/I56 -> #DIV/0!
G57: =(D57*F57)/1000000 -> 0 | I57: =G57*H57 -> 0 | J57: 0 | K57: =J57*$K$5 -> 0 | L57: =K57*$L$5 -> 0 | M57: =L57*$M$5 -> 0 | N57: =M57 -> 0 | O57: =N57*H57 -> 0 | P57: 0 | Q57: =P57*$Q$5 -> 0 | R57: 0 | S57: =R57*H57 -> 0 | T57: 0 | U57: =T57*$U$5 -> 0 | V57: 0 | W57: =V57*H57 -> 0 | X57: 0 | Y57: =X57*$Y$5 -> 0 | Z57: =Y57*$Z$5 -> 0 | AA57: =Z57*$AA$5 -> 0 | AB57: =AA57 -> 0 | AC57: =AB57*H57 -> 0 | AD57: 0 | AE57: =AD57*H57 -> 0 | AF57: 0 | AG57: =AF57*H57 -> 0 | AH57: 0 | AI57: =AH57*H57 -> 0 | AJ57: 0 | AK57: =AJ57*H57 -> 0 | AL57: 0 | AM57: =AL57*H57 -> 0 | AN57: 0 | AO57: =AN57*H57 -> 0 | AP57: 0 | AQ57: =AP57*H57 -> 0 | AR57: 0 | AS57: =AR57*H57 -> 0 | AT57: 0 | AU57: =AT57*H57 -> 0 | AV57: 0 | AW57: =AV57*H57 -> 0 | AX57: 0 | AY57: =AX57*H57 -> 0 | AZ57: 0 | BA57: =AZ57*H57 -> 0 | BB57: =N57+R57+V57+AB57+AD57+AF57+AH57+AJ57+AL57+AN57+AP57+AR57+AT57+AV57+AX57+AZ57 -> 0 | BC57: =O57+S57+W57+AC57+AE57+AG57+AI57+AK57+AM57+AO57+AQ57+AS57+AU57+AW57+AY57+BA57 -> 0 | BD57: =BC57/I57 -> #DIV/0! | BE57: =BB57*$BE$5 -> 0 | BF57: =BC57*$BE$5 -> 0 | BG57: =BB57*$BG$5 -> 0 | BH57: =BC57*$BG$5 -> 0 | BI57: =BB57*$BI$5 -> 0 | BJ57: =BC57*$BI$5 -> 0 | BK57: =BB57*$BK$5 -> 0 | BL57: =BC57*$BK$5 -> 0 | BM57: =$BM$5 -> 0 | BN57: =BB57*BM57 -> 0 | BO57: =BC57*BM$12 -> 0 | BP57: =$BP$5 -> 0.32 | BQ57: =BB57*$BP57 -> 0 | BR57: =BC57*BP57 -> 0 | BS57: =BB57+BE57+BG57+BI57+BK57+BN57+BQ57 -> 0 | BT57: =BC57+BF57+BH57+BJ57+BL57+BO57+BR57 -> 0 | BU57: =BT57/I57 -> #DIV/0!
G58: =(D58*F58)/1000000 -> 0 | I58: =G58*H58 -> 0 | J58: 0 | K58: =J58*$K$5 -> 0 | L58: =K58*$L$5 -> 0 | M58: =L58*$M$5 -> 0 | N58: =M58 -> 0 | O58: =N58*H58 -> 0 | P58: 0 | Q58: =P58*$Q$5 -> 0 | R58: 0 | S58: =R58*H58 -> 0 | T58: 0 | U58: =T58*$U$5 -> 0 | V58: 0 | W58: =V58*H58 -> 0 | X58: 0 | Y58: =X58*$Y$5 -> 0 | Z58: =Y58*$Z$5 -> 0 | AA58: =Z58*$AA$5 -> 0 | AB58: =AA58 -> 0 | AC58: =AB58*H58 -> 0 | AD58: 0 | AE58: =AD58*H58 -> 0 | AF58: 0 | AG58: =AF58*H58 -> 0 | AH58: 0 | AI58: =AH58*H58 -> 0 | AJ58: 0 | AK58: =AJ58*H58 -> 0 | AL58: 0 | AM58: =AL58*H58 -> 0 | AN58: 0 | AO58: =AN58*H58 -> 0 | AP58: 0 | AQ58: =AP58*H58 -> 0 | AR58: 0 | AS58: =AR58*H58 -> 0 | AT58: 0 | AU58: =AT58*H58 -> 0 | AV58: 0 | AW58: =AV58*H58 -> 0 | AX58: 0 | AY58: =AX58*H58 -> 0 | AZ58: 0 | BA58: =AZ58*H58 -> 0 | BB58: =N58+R58+V58+AB58+AD58+AF58+AH58+AJ58+AL58+AN58+AP58+AR58+AT58+AV58+AX58+AZ58 -> 0 | BC58: =O58+S58+W58+AC58+AE58+AG58+AI58+AK58+AM58+AO58+AQ58+AS58+AU58+AW58+AY58+BA58 -> 0 | BD58: =BC58/I58 -> #DIV/0! | BE58: =BB58*$BE$5 -> 0 | BF58: =BC58*$BE$5 -> 0 | BG58: =BB58*$BG$5 -> 0 | BH58: =BC58*$BG$5 -> 0 | BI58: =BB58*$BI$5 -> 0 | BJ58: =BC58*$BI$5 -> 0 | BK58: =BB58*$BK$5 -> 0 | BL58: =BC58*$BK$5 -> 0 | BM58: =$BM$5 -> 0 | BN58: =BB58*BM58 -> 0 | BO58: =BC58*BM$12 -> 0 | BP58: =$BP$5 -> 0.32 | BQ58: =BB58*$BP58 -> 0 | BR58: =BC58*BP58 -> 0 | BS58: =BB58+BE58+BG58+BI58+BK58+BN58+BQ58 -> 0 | BT58: =BC58+BF58+BH58+BJ58+BL58+BO58+BR58 -> 0 | BU58: =BT58/I58 -> #DIV/0!
G59: =(D59*F59)/1000000 -> 0 | I59: =G59*H59 -> 0 | J59: 0 | K59: =J59*$K$5 -> 0 | L59: =K59*$L$5 -> 0 | M59: =L59*$M$5 -> 0 | N59: =M59 -> 0 | O59: =N59*H59 -> 0 | P59: 0 | Q59: =P59*$Q$5 -> 0 | R59: 0 | S59: =R59*H59 -> 0 | T59: 0 | U59: =T59*$U$5 -> 0 | V59: 0 | W59: =V59*H59 -> 0 | X59: 0 | Y59: =X59*$Y$5 -> 0 | Z59: =Y59*$Z$5 -> 0 | AA59: =Z59*$AA$5 -> 0 | AB59: =AA59 -> 0 | AC59: =AB59*H59 -> 0 | AD59: 0 | AE59: =AD59*H59 -> 0 | AF59: 0 | AG59: =AF59*H59 -> 0 | AH59: 0 | AI59: =AH59*H59 -> 0 | AJ59: 0 | AK59: =AJ59*H59 -> 0 | AL59: 0 | AM59: =AL59*H59 -> 0 | AN59: 0 | AO59: =AN59*H59 -> 0 | AP59: 0 | AQ59: =AP59*H59 -> 0 | AR59: 0 | AS59: =AR59*H59 -> 0 | AT59: 0 | AU59: =AT59*H59 -> 0 | AV59: 0 | AW59: =AV59*H59 -> 0 | AX59: 0 | AY59: =AX59*H59 -> 0 | AZ59: 0 | BA59: =AZ59*H59 -> 0 | BB59: =N59+R59+V59+AB59+AD59+AF59+AH59+AJ59+AL59+AN59+AP59+AR59+AT59+AV59+AX59+AZ59 -> 0 | BC59: =O59+S59+W59+AC59+AE59+AG59+AI59+AK59+AM59+AO59+AQ59+AS59+AU59+AW59+AY59+BA59 -> 0 | BD59: =BC59/I59 -> #DIV/0! | BE59: =BB59*$BE$5 -> 0 | BF59: =BC59*$BE$5 -> 0 | BG59: =BB59*$BG$5 -> 0 | BH59: =BC59*$BG$5 -> 0 | BI59: =BB59*$BI$5 -> 0 | BJ59: =BC59*$BI$5 -> 0 | BK59: =BB59*$BK$5 -> 0 | BL59: =BC59*$BK$5 -> 0 | BM59: =$BM$5 -> 0 | BN59: =BB59*BM59 -> 0 | BO59: =BC59*BM$12 -> 0 | BP59: =$BP$5 -> 0.32 | BQ59: =BB59*$BP59 -> 0 | BR59: =BC59*BP59 -> 0 | BS59: =BB59+BE59+BG59+BI59+BK59+BN59+BQ59 -> 0 | BT59: =BC59+BF59+BH59+BJ59+BL59+BO59+BR59 -> 0 | BU59: =BT59/I59 -> #DIV/0!
... G156: =(D156*F156)/1000000 -> 0 | I156: =G156*H156 -> 0 | J156: 0 | K156: =J156*$K$5 -> 0 | L156: =K156*$L$5 -> 0 | M156: =L156*$M$5 -> 0 | N156: =M156 -> 0 | O156: =N156*H156 -> 0 | P156: 0 | Q156: =P156*$Q$5 -> 0 | R156: 0 | S156: =R156*H156 -> 0 | T156: 0 | U156: =T156*$U$5 -> 0 | V156: 0 | W156: =V156*H156 -> 0 | X156: 0 | Y156: =X156*$Y$5 -> 0 | Z156: =Y156*$Z$5 -> 0 | AA156: =Z156*$AA$5 -> 0 | AB156: =AA156 -> 0 | AC156: =AB156*H156 -> 0 | AD156: 0 | AE156: =AD156*H156 -> 0 | AF156: 0 | AG156: =AF156*H156 -> 0 | AH156: 0 | AI156: =AH156*H156 -> 0 | AJ156: 0 | AK156: =AJ156*H156 -> 0 | AL156: 0 | AM156: =AL156*H156 -> 0 | AN156: 0 | AO156: =AN156*H156 -> 0 | AP156: 0 | AQ156: =AP156*H156 -> 0 | AR156: 0 | AS156: =AR156*H156 -> 0 | AT156: 0 | AU156: =AT156*H156 -> 0 | AV156: 0 | AW156: =AV156*H156 -> 0 | AX156: 0 | AY156: =AX156*H156 -> 0 | AZ156: 0 | BA156: =AZ156*H156 -> 0 | BB156: =N156+R156+V156+AB156+AD156+AF156+AH156+AJ156+AL156+AN156+AP156+AR156+AT156+AV156+AX156+AZ156 -> 0 | BC156: =O156+S156+W156+AC156+AE156+AG156+AI156+AK156+AM156+AO156+AQ156+AS156+AU156+AW156+AY156+BA156 -> 0 | BD156: =BC156/I156 -> #DIV/0! | BE156: =BB156*$BE$5 -> 0 | BF156: =BC156*$BE$5 -> 0 | BG156: =BB156*$BG$5 -> 0 | BH156: =BC156*$BG$5 -> 0 | BI156: =BB156*$BI$5 -> 0 | BJ156: =BC156*$BI$5 -> 0 | BK156: =BB156*$BK$5 -> 0 | BL156: =BC156*$BK$5 -> 0 | BM156: =$BM$5 -> 0 | BN156: =BB156*BM156 -> 0 | BO156: =BC156*BM$12 -> 0 | BP156: =$BP$5 -> 0.32 | BQ156: =BB156*$BP156 -> 0 | BR156: =BC156*BP156 -> 0 | BS156: =BB156+BE156+BG156+BI156+BK156+BN156+BQ156 -> 0 | BT156: =BC156+BF156+BH156+BJ156+BL156+BO156+BR156 -> 0 | BU156: =BT156/I156 -> #DIV/0!
H157: =SUM(H7:H156) -> 81 | I157: =SUM(I7:I156) -> 630.434 | M157: =SUM(M7:M156) -> 0 | O157: =SUM(O7:O156) -> 0 | S157: =SUM(S7:S156) -> 0 | W157: =SUM(W7:W156) -> 51960 | AC157: =SUM(AC7:AC156) -> 20324.92 | AE157: =SUM(AE7:AE156) -> 9839.908 | AG157: =SUM(AG7:AG156) -> 85329 | AI157: =SUM(AI7:AI156) -> 128084.99 | AK157: =SUM(AK7:AK156) -> 106630 | AM157: =SUM(AM7:AM156) -> 10620 | AO157: =SUM(AO7:AO156) -> 151038.32 | AQ157: =SUM(AQ7:AQ156) -> 0 | AS157: =SUM(AS7:AS156) -> 32920.3 | AU157: =SUM(AU7:AU156) -> 102793.5 | AW157: =SUM(AW7:AW156) -> 133583.01 | AY157: =SUM(AY7:AY156) -> 95000 | BA157: =SUM(BA7:BA156) -> 0 | BC157: =SUM(BC12:BC47) -> 928123.96 | BF157: =SUM(BF12:BF47) -> 11137.487 | BH157: =SUM(BH12:BH47) -> 13921.859 | BJ157: =SUM(BJ12:BJ47) -> 4640.6198 | BL157: =SUM(BL12:BL47) -> 9281.2396 | BO157: =SUM(BO12:BO47) -> 0 | BR157: =SUM(BR12:BR47) -> 296999.67 | BT157: =SUM(BT12:BT47) -> 1264104.8

Sheet ITEM
A1: COMMESSA : | B1: =ANACO!C5 -> P1002_25_CON_REV03_P1 E EI ALLUMINIO
A2: CANTIERE : | B2: =ANACO!C8 -> Mr.Marco Mor/Ing. Esposito
A3: CLIENTE : | B3: =ANACO!C7 -> VASTINT ITALY s.r.l.
A4: BUDGET ITEM
G5: Ordini emessi | H5: Costi sostenuti | I5: Da evadere | J5: % pagati su ordine | K5: % ORDINE Avanzamento | L5: Disponibilità residua su ordine | N5: % su preventivato | O5: Ipotesi di ordine residuo | P5: CONTROLLO Budget/ordine | Q5: CONTROLLO Ordine/Residuo | R5: CONTROLLO pagamenti | T5: AVANZO SU BUDGET | V5: TOTALE | W5: n° FATTURA | X5: Valore
A6: RIEPILOGO BUDGET | D6: Costi previsti | E6: NOTE
A8: ='SUMMARY COSTI'!B3 -> PRODOTTO ACQUISTATO FINITO LEGNO O LEGNO ALLUMINIO Scontato TOTALE | B8: Totale costi previsti € | D8: ='SUMMARY COSTI'!D3 -> 0 | H8: =V8 -> 0 | I8: =G8-H8 -> 0 | J8: =IF(G8=0,0,H8/G8) -> 0 | K8: 0 | L8: =D8-G8 -> 0 | M8: =IF(L8<0,"-","ok") -> ok | N8: =IF(D8=0,0,IF(G8=0,0,IF(G8/D8<1,G8/D8,1))) -> 0 | O8: =IF(K8<>0,(G8/K8)-G8,D8*(1-K8)) -> 0 | P8: =IF(D8=0,IF(G8=0,"-","ATTENZIONE"),IF(G8<D8,"ok","ATTENZIONE")) -> - | Q8: =IF(D8=0,"-",IF(K8>=N8,"ok","ATTENZIONE")) -> - | R8: =IF(D8=0,"-",IF(K8>=(H8/D8),"ok","ATTENZIONE")) -> - | T8: =IF(K8=1,L8,D8-G8-O8) -> 0 | V8: =SUM(W8:Y8) -> 0 | X8: 0
A9: ='SUMMARY COSTI'!B4 -> ST /LZ - STAFFAME TOT. | B9: Totale costi previsti € | D9: ='SUMMARY COSTI'!D4 -> 0 | H9: =V9 -> 0 | I9: =G9-H9 -> 0 | J9: =IF(G9=0,0,H9/G9) -> 0 | K9: 0 | L9: =D9-G9 -> 0 | M9: =IF(L9<0,"-","ok") -> ok | N9: =IF(D9=0,0,IF(G9=0,0,IF(G9/D9<1,G9/D9,1))) -> 0 | O9: =IF(K9<>0,(G9/K9)-G9,D9*(1-K9)) -> 0 | P9: =IF(D9=0,IF(G9=0,"-","ATTENZIONE"),IF(G9<D9,"ok","ATTENZIONE")) -> - | Q9: =IF(D9=0,"-",IF(K9>=N9,"ok","ATTENZIONE")) -> - | R9: =IF(D9=0,"-",IF(K9>=(H9/D9),"ok","ATTENZIONE")) -> - | T9: =IF(K9=1,L9,D9-G9-O9) -> 0 | V9: =SUM(W9:Y9) -> 0
A10: ='SUMMARY COSTI'!B5 -> Accessorio Maniglie e Maniglioni TOTALE | B10: Totale costi previsti € | D10: ='SUMMARY COSTI'!D5 -> 51960 | H10: =V10 -> 0 | I10: =G10-H10 -> 0 | J10: =IF(G10=0,0,H10/G10) -> 0 | K10: 0 | L10: =D10-G10 -> 51960 | M10: =IF(L10<0,"-","ok") -> ok | N10: =IF(D10=0,0,IF(G10=0,0,IF(G10/D10<1,G10/D10,1))) -> 0 | O10: =IF(K10<>0,(G10/K10)-G10,D10*(1-K10)) -> 51960 | P10: =IF(D10=0,IF(G10=0,"-","ATTENZIONE"),IF(G10<D10,"ok","ATTENZIONE")) -> ok | Q10: =IF(D10=0,"-",IF(K10>=N10,"ok","ATTENZIONE")) -> ok | R10: =IF(D10=0,"-",IF(K10>=(H10/D10),"ok","ATTENZIONE")) -> ok | T10: =IF(K10=1,L10,D10-G10-O10) -> 0 | V10: =SUM(W10:Y10) -> 0
A11: ='SUMMARY COSTI'!B6 -> LA TOTALE | B11: Totale costi previsti € | D11: ='SUMMARY COSTI'!D6 -> 20324.92 | H11: =V11 -> 0 | I11: =G11-H11 -> 0 | J11: =IF(G11=0,0,H11/G11) -> 0 | K11: 0 | L11: =D11-G11 -> 20324.92 | M11: =IF(L11<0,"-","ok") -> ok | N11: =IF(D11=0,0,IF(G11=0,0,IF(G11/D11<1,G11/D11,1))) -> 0 | O11: =IF(K11<>0,(G11/K11)-G11,D11*(1-K11)) -> 20324.92 | P11: =IF(D11=0,IF(G11=0,"-","ATTENZIONE"),IF(G11<D11,"ok","ATTENZIONE")) -> ok | Q11: =IF(D11=0,"-",IF(K11>=N11,"ok","ATTENZIONE")) -> ok | R11: =IF(D11=0,"-",IF(K11>=(H11/D11),"ok","ATTENZIONE")) -> ok | T11: =IF(K11=1,L11,D11-G11-O11) -> 0 | V11: =SUM(W11:Y11) -> 0
A12: ='SUMMARY COSTI'!B7 -> PACCHETTO DI COIBENTAZIONECOIBENTAZIONE TOTALE | B12: Totale costi previsti € | D12: ='SUMMARY COSTI'!D7 -> 9839.908 | H12: =V12 -> 0 | I12: =G12-H12 -> 0 | J12: =IF(G12=0,0,H12/G12) -> 0 | K12: 0 | L12: =D12-G12 -> 9839.908 | M12: =IF(L12<0,"-","ok") -> ok | N12: =IF(D12=0,0,IF(G12=0,0,IF(G12/D12<1,G12/D12,1))) -> 0 | O12: =IF(K12<>0,(G12/K12)-G12,D12*(1-K12)) -> 9839.908 | P12: =IF(D12=0,IF(G12=0,"-","ATTENZIONE"),IF(G12<D12,"ok","ATTENZIONE")) -> ok | Q12: =IF(D12=0,"-",IF(K12>=N12,"ok","ATTENZIONE")) -> ok | R12: =IF(D12=0,"-",IF(K12>=(H12/D12),"ok","ATTENZIONE")) -> ok | T12: =IF(K12=1,L12,D12-G12-O12) -> 0 | V12: =SUM(W12:Y12) -> 0
A13: ='SUMMARY COSTI'!B8 -> SISTEMA ALLUMINIO E ACCESSORI DI SISTEMA TOTALE | B13: Totale costi previsti € | D13: ='SUMMARY COSTI'!D8 -> 85329 | H13: =V13 -> 0 | I13: =G13-H13 -> 0 | J13: =IF(G13=0,0,H13/G13) -> 0 | K13: 0 | L13: =D13-G13 -> 85329 | M13: =IF(L13<0,"-","ok") -> ok | N13: =IF(D13=0,0,IF(G13=0,0,IF(G13/D13<1,G13/D13,1))) -> 0 | O13: =IF(K13<>0,(G13/K13)-G13,D13*(1-K13)) -> 85329 | P13: =IF(D13=0,IF(G13=0,"-","ATTENZIONE"),IF(G13<D13,"ok","ATTENZIONE")) -> ok | Q13: =IF(D13=0,"-",IF(K13>=N13,"ok","ATTENZIONE")) -> ok | R13: =IF(D13=0,"-",IF(K13>=(H13/D13),"ok","ATTENZIONE")) -> ok | T13: =IF(K13=1,L13,D13-G13-O13) -> 0 | V13: =SUM(W13:Y13) -> 0
A14: ='SUMMARY COSTI'!B9 -> SISTEMA ACCIAIO E ACCESSORI DI SISTEMA TOTALE | B14: Totale costi previsti € | D14: ='SUMMARY COSTI'!D9 -> 128084.99 | H14: =V14 -> 0 | I14: =G14-H14 -> 0 | J14: =IF(G14=0,0,H14/G14) -> 0 | K14: 0 | L14: =D14-G14 -> 128084.99 | M14: =IF(L14<0,"-","ok") -> ok | N14: =IF(D14=0,0,IF(G14=0,0,IF(G14/D14<1,G14/D14,1))) -> 0 | O14: =IF(K14<>0,(G14/K14)-G14,D14*(1-K14)) -> 128084.99 | P14: =IF(D14=0,IF(G14=0,"-","ATTENZIONE"),IF(G14<D14,"ok","ATTENZIONE")) -> ok | Q14: =IF(D14=0,"-",IF(K14>=N14,"ok","ATTENZIONE")) -> ok | R14: =IF(D14=0,"-",IF(K14>=(H14/D14),"ok","ATTENZIONE")) -> ok | T14: =IF(K14=1,L14,D14-G14-O14) -> 0 | V14: =SUM(W14:Y14) -> 0
A15: ='SUMMARY COSTI'!B10 -> Trasformazione Acciaio TOTALE | B15: Totale costi previsti € | D15: ='SUMMARY COSTI'!D10 -> 106630 | H15: =V15 -> 0 | I15: =G15-H15 -> 0 | J15: =IF(G15=0,0,H15/G15) -> 0 | K15: 0 | L15: =D15-G15 -> 106630 | M15: =IF(L15<0,"-","ok") -> ok | N15: =IF(D15=0,0,IF(G15=0,0,IF(G15/D15<1,G15/D15,1))) -> 0 | O15: =IF(K15<>0,(G15/K15)-G15,D15*(1-K15)) -> 106630 | P15: =IF(D15=0,IF(G15=0,"-","ATTENZIONE"),IF(G15<D15,"ok","ATTENZIONE")) -> ok | Q15: =IF(D15=0,"-",IF(K15>=N15,"ok","ATTENZIONE")) -> ok | R15: =IF(D15=0,"-",IF(K15>=(H15/D15),"ok","ATTENZIONE")) -> ok | T15: =IF(K15=1,L15,D15-G15-O15) -> 0 | V15: =SUM(W15:Y15) -> 0
A16: ='SUMMARY COSTI'!B11 -> Automatismo TOTALE | B16: Totale costi previsti € | D16: ='SUMMARY COSTI'!D11 -> 10620 | H16: =V16 -> 0 | I16: =G16-H16 -> 0 | J16: =IF(G16=0,0,H16/G16) -> 0 | K16: 0 | L16: =D16-G16 -> 10620 | M16: =IF(L16<0,"-","ok") -> ok | N16: =IF(D16=0,0,IF(G16=0,0,IF(G16/D16<1,G16/D16,1))) -> 0 | O16: =IF(K16<>0,(G16/K16)-G16,D16*(1-K16)) -> 10620 | P16: =IF(D16=0,IF(G16=0,"-","ATTENZIONE"),IF(G16<D16,"ok","ATTENZIONE")) -> ok | Q16: =IF(D16=0,"-",IF(K16>=N16,"ok","ATTENZIONE")) -> ok | R16: =IF(D16=0,"-",IF(K16>=(H16/D16),"ok","ATTENZIONE")) -> ok | T16: =IF(K16=1,L16,D16-G16-O16) -> 0 | V16: =SUM(W16:Y16) -> 0
A17: ='SUMMARY COSTI'!B12 -> Vetro TOTALE. | B17: Totale costi previsti € | D17: ='SUMMARY COSTI'!D12 -> 151038.32 | H17: =V17 -> 0 | I17: =G17-H17 -> 0 | J17: =IF(G17=0,0,H17/G17) -> 0 | K17: 0 | L17: =D17-G17 -> 151038.32 | M17: =IF(L17<0,"-","ok") -> ok | N17: =IF(D17=0,0,IF(G17=0,0,IF(G17/D17<1,G17/D17,1))) -> 0 | O17: =IF(K17<>0,(G17/K17)-G17,D17*(1-K17)) -> 151038.32 | P17: =IF(D17=0,IF(G17=0,"-","ATTENZIONE"),IF(G17<D17,"ok","ATTENZIONE")) -> ok | Q17: =IF(D17=0,"-",IF(K17>=N17,"ok","ATTENZIONE")) -> ok | R17: =IF(D17=0,"-",IF(K17>=(H17/D17),"ok","ATTENZIONE")) -> ok | T17: =IF(K17=1,L17,D17-G17-O17) -> 0 | V17: =SUM(W17:Y17) -> 0
A18: ='SUMMARY COSTI'!B13 -> Pannell TOTALE | B18: Totale costi previsti € | D18: ='SUMMARY COSTI'!D13 -> 0 | H18: =V18 -> 0 | I18: =G18-H18 -> 0 | J18: =IF(G18=0,0,H18/G18) -> 0 | K18: 0 | L18: =D18-G18 -> 0 | M18: =IF(L18<0,"-","ok") -> ok | N18: =IF(D18=0,0,IF(G18=0,0,IF(G18/D18<1,G18/D18,1))) -> 0 | O18: =IF(K18<>0,(G18/K18)-G18,D18*(1-K18)) -> 0 | P18: =IF(D18=0,IF(G18=0,"-","ATTENZIONE"),IF(G18<D18,"ok","ATTENZIONE")) -> - | Q18: =IF(D18=0,"-",IF(K18>=N18,"ok","ATTENZIONE")) -> - | R18: =IF(D18=0,"-",IF(K18>=(H18/D18),"ok","ATTENZIONE")) -> - | T18: =IF(K18=1,L18,D18-G18-O18) -> 0 | V18: =SUM(W18:Y18) -> 0
A19: ='SUMMARY COSTI'!B14 -> Controtelaio TOTALE. | B19: Totale costi previsti € | D19: ='SUMMARY COSTI'!D14 -> 32920.3 | H19: =V19 -> 0 | I19: =G19-H19 -> 0 | J19: =IF(G19=0,0,H19/G19) -> 0 | K19: 0 | L19: =D19-G19 -> 32920.3 | M19: =IF(L19<0,"-","ok") -> ok | N19: =IF(D19=0,0,IF(G19=0,0,IF(G19/D19<1,G19/D19,1))) -> 0 | O19: =IF(K19<>0,(G19/K19)-G19,D19*(1-K19)) -> 32920.3 | P19: =IF(D19=0,IF(G19=0,"-","ATTENZIONE"),IF(G19<D19,"ok","ATTENZIONE")) -> ok | Q19: =IF(D19=0,"-",IF(K19>=N19,"ok","ATTENZIONE")) -> ok | R19: =IF(D19=0,"-",IF(K19>=(H19/D19),"ok","ATTENZIONE")) -> ok | T19: =IF(K19=1,L19,D19-G19-O19) -> 0 | V19: =SUM(W19:Y19) -> 0
A20: VOCI AGGIUNTE DURANTE COMMESSA | B20: Totale costi previsti A1 - € | D20: =SUM(D8:D19) -> 596747.44 | H20: =V20 -> 0 | I20: =G20-H20 -> 0 | J20: =IF(G20=0,0,H20/G20) -> 0 | K20: 0 | L20: =D20-G20 -> 596747.44 | M20: =IF(L20<0,"-","ok") -> ok | N20: =IF(D20=0,0,IF(G20=0,0,IF(G20/D20<1,G20/D20,1))) -> 0 | O20: =IF(K20<>0,(G20/K20)-G20,D20*(1-K20)) -> 596747.44 | P20: =IF(D20=0,IF(G20=0,"-","ATTENZIONE"),IF(G20<D20,"ok","ATTENZIONE")) -> ok | Q20: =IF(D20=0,"-",IF(K20>=N20,"ok","ATTENZIONE")) -> ok | R20: =IF(D20=0,"-",IF(K20>=(H20/D20),"ok","ATTENZIONE")) -> ok | T20: =IF(K20=1,L20,D20-G20-O20) -> 0 | V20: =SUM(W20:Y20) -> 0
B21: Totale costi previsti € | D21: 0 | H21: =V21 -> 0 | I21: =G21-H21 -> 0 | J21: =IF(G21=0,0,H21/G21) -> 0 | K21: 0 | L21: =D21-G21 -> 0 | M21: =IF(L21<0,"-","ok") -> ok | N21: =IF(D21=0,0,IF(G21=0,0,IF(G21/D21<1,G21/D21,1))) -> 0 | O21: =IF(K21<>0,(G21/K21)-G21,D21*(1-K21)) -> 0 | P21: =IF(D21=0,IF(G21=0,"-","ATTENZIONE"),IF(G21<D21,"ok","ATTENZIONE")) -> - | Q21: =IF(D21=0,"-",IF(K21>=N21,"ok","ATTENZIONE")) -> - | R21: =IF(D21=0,"-",IF(K21>=(H21/D21),"ok","ATTENZIONE")) -> - | T21: =IF(K21=1,L21,D21-G21-O21) -> 0 | V21: =SUM(W21:Y21) -> 0
B22: Totale costi previsti € | D22: 0 | H22: =V22 -> 0 | I22: =G22-H22 -> 0 | J22: =IF(G22=0,0,H22/G22) -> 0 | K22: 0 | L22: =D22-G22 -> 0 | M22: =IF(L22<0,"-","ok") -> ok | N22: =IF(D22=0,0,IF(G22=0,0,IF(G22/D22<1,G22/D22,1))) -> 0 | O22: =IF(K22<>0,(G22/K22)-G22,D22*(1-K22)) -> 0 | P22: =IF(D22=0,IF(G22=0,"-","ATTENZIONE"),IF(G22<D22,"ok","ATTENZIONE")) -> - | Q22: =IF(D22=0,"-",IF(K22>=N22,"ok","ATTENZIONE")) -> - | R22: =IF(D22=0,"-",IF(K22>=(H22/D22),"ok","ATTENZIONE")) -> - | T22: =IF(K22=1,L22,D22-G22-O22) -> 0 | V22: =SUM(W22:Y22) -> 0
B23: Totale costi previsti € | D23: 0 | H23: =V23 -> 0 | I23: =G23-H23 -> 0 | J23: =IF(G23=0,0,H23/G23) -> 0 | K23: 0 | L23: =D23-G23 -> 0 | M23: =IF(L23<0,"-","ok") -> ok | N23: =IF(D23=0,0,IF(G23=0,0,IF(G23/D23<1,G23/D23,1))) -> 0 | O23: =IF(K23<>0,(G23/K23)-G23,D23*(1-K23)) -> 0 | P23: =IF(D23=0,IF(G23=0,"-","ATTENZIONE"),IF(G23<D23,"ok","ATTENZIONE")) -> - | Q23: =IF(D23=0,"-",IF(K23>=N23,"ok","ATTENZIONE")) -> - | R23: =IF(D23=0,"-",IF(K23>=(H23/D23),"ok","ATTENZIONE")) -> - | T23: =IF(K23=1,L23,D23-G23-O23) -> 0 | V23: =SUM(W23:Y23) -> 0
B24: Totale costi previsti € | D24: 0 | H24: =V24 -> 0 | I24: =G24-H24 -> 0 | J24: =IF(G24=0,0,H24/G24) -> 0 | K24: 0 | L24: =D24-G24 -> 0 | M24: =IF(L24<0,"-","ok") -> ok | N24: =IF(D24=0,0,IF(G24=0,0,IF(G24/D24<1,G24/D24,1))) -> 0 | O24: =IF(K24<>0,(G24/K24)-G24,D24*(1-K24)) -> 0 | P24: =IF(D24=0,IF(G24=0,"-","ATTENZIONE"),IF(G24<D24,"ok","ATTENZIONE")) -> - | Q24: =IF(D24=0,"-",IF(K24>=N24,"ok","ATTENZIONE")) -> - | R24: =IF(D24=0,"-",IF(K24>=(H24/D24),"ok","ATTENZIONE")) -> - | T24: =IF(K24=1,L24,D24-G24-O24) -> 0 | V24: =SUM(W24:Y24) -> 0
B25: Totale costi previsti € | D25: 0 | H25: =V25 -> 0 | I25: =G25-H25 -> 0 | J25: =IF(G25=0,0,H25/G25) -> 0 | K25: 0 | L25: =D25-G25 -> 0 | M25: =IF(L25<0,"-","ok") -> ok | N25: =IF(D25=0,0,IF(G25=0,0,IF(G25/D25<1,G25/D25,1))) -> 0 | O25: =IF(K25<>0,(G25/K25)-G25,D25*(1-K25)) -> 0 | P25: =IF(D25=0,IF(G25=0,"-","ATTENZIONE"),IF(G25<D25,"ok","ATTENZIONE")) -> - | Q25: =IF(D25=0,"-",IF(K25>=N25,"ok","ATTENZIONE")) -> - | R25: =IF(D25=0,"-",IF(K25>=(H25/D25),"ok","ATTENZIONE")) -> - | T25: =IF(K25=1,L25,D25-G25-O25) -> 0 | V25: =SUM(W25:Y25) -> 0
B26: Totale costi previsti € | D26: 0 | H26: =V26 -> 0 | I26: =G26-H26 -> 0 | J26: =IF(G26=0,0,H26/G26) -> 0 | K26: 0 | L26: =D26-G26 -> 0 | M26: =IF(L26<0,"-","ok") -> ok | N26: =IF(D26=0,0,IF(G26=0,0,IF(G26/D26<1,G26/D26,1))) -> 0 | O26: =IF(K26<>0,(G26/K26)-G26,D26*(1-K26)) -> 0 | P26: =IF(D26=0,IF(G26=0,"-","ATTENZIONE"),IF(G26<D26,"ok","ATTENZIONE")) -> - | Q26: =IF(D26=0,"-",IF(K26>=N26,"ok","ATTENZIONE")) -> - | R26: =IF(D26=0,"-",IF(K26>=(H26/D26),"ok","ATTENZIONE")) -> - | T26: =IF(K26=1,L26,D26-G26-O26) -> 0 | V26: =SUM(W26:Y26) -> 0
B27: Totale costi previsti € | D27: 0 | H27: =V27 -> 0 | I27: =G27-H27 -> 0 | J27: =IF(G27=0,0,H27/G27) -> 0 | K27: 0 | L27: =D27-G27 -> 0 | M27: =IF(L27<0,"-","ok") -> ok | N27: =IF(D27=0,0,IF(G27=0,0,IF(G27/D27<1,G27/D27,1))) -> 0 | O27: =IF(K27<>0,(G27/K27)-G27,D27*(1-K27)) -> 0 | P27: =IF(D27=0,IF(G27=0,"-","ATTENZIONE"),IF(G27<D27,"ok","ATTENZIONE")) -> - | Q27: =IF(D27=0,"-",IF(K27>=N27,"ok","ATTENZIONE")) -> - | R27: =IF(D27=0,"-",IF(K27>=(H27/D27),"ok","ATTENZIONE")) -> - | T27: =IF(K27=1,L27,D27-G27-O27) -> 0 | V27: =SUM(W27:Y27) -> 0
B28: Totale costi previsti € | D28: 0 | H28: =V28 -> 0 | I28: =G28-H28 -> 0 | J28: =IF(G28=0,0,H28/G28) -> 0 | K28: 0 | L28: =D28-G28 -> 0 | M28: =IF(L28<0,"-","ok") -> ok | N28: =IF(D28=0,0,IF(G28=0,0,IF(G28/D28<1,G28/D28,1))) -> 0 | O28: =IF(K28<>0,(G28/K28)-G28,D28*(1-K28)) -> 0 | P28: =IF(D28=0,IF(G28=0,"-","ATTENZIONE"),IF(G28<D28,"ok","ATTENZIONE")) -> - | Q28: =IF(D28=0,"-",IF(K28>=N28,"ok","ATTENZIONE")) -> - | R28: =IF(D28=0,"-",IF(K28>=(H28/D28),"ok","ATTENZIONE")) -> - | T28: =IF(K28=1,L28,D28-G28-O28) -> 0 | V28: =SUM(W28:Y28) -> 0
B29: Totale costi previsti € | D29: 0 | H29: =V29 -> 0 | I29: =G29-H29 -> 0 | J29: =IF(G29=0,0,H29/G29) -> 0 | K29: 0 | L29: =D29-G29 -> 0 | M29: =IF(L29<0,"-","ok") -> ok | N29: =IF(D29=0,0,IF(G29=0,0,IF(G29/D29<1,G29/D29,1))) -> 0 | O29: =IF(K29<>0,(G29/K29)-G29,D29*(1-K29)) -> 0 | P29: =IF(D29=0,IF(G29=0,"-","ATTENZIONE"),IF(G29<D29,"ok","ATTENZIONE")) -> - | Q29: =IF(D29=0,"-",IF(K29>=N29,"ok","ATTENZIONE")) -> - | R29: =IF(D29=0,"-",IF(K29>=(H29/D29),"ok","ATTENZIONE")) -> - | T29: =IF(K29=1,L29,D29-G29-O29) -> 0 | V29: =SUM(W29:Y29) -> 0
B30: Totale costi previsti € | D30: 0 | H30: =V30 -> 0 | I30: =G30-H30 -> 0 | J30: =IF(G30=0,0,H30/G30) -> 0 | K30: 0 | L30: =D30-G30 -> 0 | M30: =IF(L30<0,"-","ok") -> ok | N30: =IF(D30=0,0,IF(G30=0,0,IF(G30/D30<1,G30/D30,1))) -> 0 | O30: =IF(K30<>0,(G30/K30)-G30,D30*(1-K30)) -> 0 | P30: =IF(D30=0,IF(G30=0,"-","ATTENZIONE"),IF(G30<D30,"ok","ATTENZIONE")) -> - | Q30: =IF(D30=0,"-",IF(K30>=N30,"ok","ATTENZIONE")) -> - | R30: =IF(D30=0,"-",IF(K30>=(H30/D30),"ok","ATTENZIONE")) -> - | T30: =IF(K30=1,L30,D30-G30-O30) -> 0 | V30: =SUM(W30:Y30) -> 0
B31: Totale costi previsti € | D31: 0 | H31: =V31 -> 0 | I31: =G31-H31 -> 0 | J31: =IF(G31=0,0,H31/G31) -> 0 | K31: 0 | L31: =D31-G31 -> 0 | M31: =IF(L31<0,"-","ok") -> ok | N31: =IF(D31=0,0,IF(G31=0,0,IF(G31/D31<1,G31/D31,1))) -> 0 | O31: =IF(K31<>0,(G31/K31)-G31,D31*(1-K31)) -> 0 | P31: =IF(D31=0,IF(G31=0,"-","ATTENZIONE"),IF(G31<D31,"ok","ATTENZIONE")) -> - | Q31: =IF(D31=0,"-",IF(K31>=N31,"ok","ATTENZIONE")) -> - | R31: =IF(D31=0,"-",IF(K31>=(H31/D31),"ok","ATTENZIONE")) -> - | T31: =IF(K31=1,L31,D31-G31-O31) -> 0 | V31: =SUM(W31:Y31) -> 0
B32: Totale costi previsti € | D32: 0 | H32: =V32 -> 0 | I32: =G32-H32 -> 0 | J32: =IF(G32=0,0,H32/G32) -> 0 | K32: 0 | L32: =D32-G32 -> 0 | M32: =IF(L32<0,"-","ok") -> ok | N32: =IF(D32=0,0,IF(G32=0,0,IF(G32/D32<1,G32/D32,1))) -> 0 | O32: =IF(K32<>0,(G32/K32)-G32,D32*(1-K32)) -> 0 | P32: =IF(D32=0,IF(G32=0,"-","ATTENZIONE"),IF(G32<D32,"ok","ATTENZIONE")) -> - | Q32: =IF(D32=0,"-",IF(K32>=N32,"ok","ATTENZIONE")) -> - | R32: =IF(D32=0,"-",IF(K32>=(H32/D32),"ok","ATTENZIONE")) -> - | T32: =IF(K32=1,L32,D32-G32-O32) -> 0 | V32: =SUM(W32:Y32) -> 0
... B34: Totale costi previsti € | D34: 0 | H34: =V34 -> 0 | I34: =G34-H34 -> 0 | J34: =IF(G34=0,0,H34/G34) -> 0 | K34: 0 | L34: =D34-G34 -> 0 | M34: =IF(L34<0,"-","ok") -> ok | N34: =IF(D34=0,0,IF(G34=0,0,IF(G34/D34<1,G34/D34,1))) -> 0 | O34: =IF(K34<>0,(G34/K34)-G34,D34*(1-K34)) -> 0 | P34: =IF(D34=0,IF(G34=0,"-","ATTENZIONE"),IF(G34<D34,"ok","ATTENZIONE")) -> - | Q34: =IF(D34=0,"-",IF(K34>=N34,"ok","ATTENZIONE")) -> - | R34: =IF(D34=0,"-",IF(K34>=(H34/D34),"ok","ATTENZIONE")) -> - | T34: =IF(K34=1,L34,D34-G34-O34) -> 0 | V34: =SUM(W34:Y34) -> 0
C35: Totale costi previsti /Aggiunti A1 - € | D35: =SUM(D20:D34) -> 596747.44
A38: ='SUMMARY COSTI'!B15 -> Trasformazione Alluminio TOTALE. | B38: Totale costi previsti € | D38: ='SUMMARY COSTI'!D15 -> 102793.5 | H38: =V38 -> 0 | I38: =G38-H38 -> 0 | J38: =IF(G38=0,0,H38/G38) -> 0 | K38: 0 | L38: =D38-G38 -> 102793.5 | M38: =IF(L38<0,"-","ok") -> ok | N38: =IF(D38=0,0,IF(G38=0,0,IF(G38/D38<1,G38/D38,1))) -> 0 | O38: =IF(K38<>0,(G38/K38)-G38,D38*(1-K38)) -> 102793.5 | P38: =IF(D38=0,IF(G38=0,"-","ATTENZIONE"),IF(G38<D38,"ok","ATTENZIONE")) -> ok | Q38: =IF(D38=0,"-",IF(K38>=N38,"ok","ATTENZIONE")) -> ok | R38: =IF(D38=0,"-",IF(K38>=(H38/D38),"ok","ATTENZIONE")) -> ok | T38: =IF(K38=1,L38,D38-G38-O38) -> 0 | V38: =SUM(W38:Y38) -> 0
A39: ='SUMMARY COSTI'!B16 -> Posa SER e FAC.. TOTALE | B39: Totale costi previsti € | D39: ='SUMMARY COSTI'!D16 -> 133583.01 | H39: =V39 -> 0 | I39: =G39-H39 -> 0 | J39: =IF(G39=0,0,H39/G39) -> 0 | K39: 0 | L39: =D39-G39 -> 133583.01 | M39: =IF(L39<0,"-","ok") -> ok | N39: =IF(D39=0,0,IF(G39=0,0,IF(G39/D39<1,G39/D39,1))) -> 0 | O39: =IF(K39<>0,(G39/K39)-G39,D39*(1-K39)) -> 133583.01 | P39: =IF(D39=0,IF(G39=0,"-","ATTENZIONE"),IF(G39<D39,"ok","ATTENZIONE")) -> ok | Q39: =IF(D39=0,"-",IF(K39>=N39,"ok","ATTENZIONE")) -> ok | R39: =IF(D39=0,"-",IF(K39>=(H39/D39),"ok","ATTENZIONE")) -> ok | T39: =IF(K39=1,L39,D39-G39-O39) -> 0 | V39: =SUM(W39:Y39) -> 0
A40: ='SUMMARY COSTI'!B17 -> FW FINITA TOTALE | B40: Totale costi previsti € | D40: ='SUMMARY COSTI'!D17 -> 95000 | H40: =V40 -> 0 | I40: =G40-H40 -> 0 | J40: =IF(G40=0,0,H40/G40) -> 0 | K40: 0 | L40: =D40-G40 -> 95000 | M40: =IF(L40<0,"-","ok") -> ok | N40: =IF(D40=0,0,IF(G40=0,0,IF(G40/D40<1,G40/D40,1))) -> 0 | O40: =IF(K40<>0,(G40/K40)-G40,D40*(1-K40)) -> 95000 | P40: =IF(D40=0,IF(G40=0,"-","ATTENZIONE"),IF(G40<D40,"ok","ATTENZIONE")) -> ok | Q40: =IF(D40=0,"-",IF(K40>=N40,"ok","ATTENZIONE")) -> ok | R40: =IF(D40=0,"-",IF(K40>=(H40/D40),"ok","ATTENZIONE")) -> ok | T40: =IF(K40=1,L40,D40-G40-O40) -> 0 | V40: =SUM(W40:Y40) -> 0
A41: VOCI AGGIUNTE DURANTE COMMESSA | B41: Totale costi previsti € | H41: =V41 -> 0 | I41: =G41-H41 -> 0 | J41: =IF(G41=0,0,H41/G41) -> 0 | K41: 0 | L41: =D41-G41 -> 0 | M41: =IF(L41<0,"-","ok") -> ok | N41: =IF(D41=0,0,IF(G41=0,0,IF(G41/D41<1,G41/D41,1))) -> 0 | O41: =IF(K41<>0,(G41/K41)-G41,D41*(1-K41)) -> 0 | P41: =IF(D41=0,IF(G41=0,"-","ATTENZIONE"),IF(G41<D41,"ok","ATTENZIONE")) -> - | Q41: =IF(D41=0,"-",IF(K41>=N41,"ok","ATTENZIONE")) -> - | R41: =IF(D41=0,"-",IF(K41>=(H41/D41),"ok","ATTENZIONE")) -> - | T41: =IF(K41=1,L41,D41-G41-O41) -> 0 | V41: =SUM(W41:Y41) -> 0
C43: Totale costi previsti A2 - € | D43: =SUM(D37:D42) -> 331376.51
C45: TOTALE TIPO A € | D45: =D35+D43 -> 928123.95 | G45: =SUM(G7:G34)+SUM(G37:G42) -> 0 | H45: =SUM(H7:H34)+SUM(H37:H42) -> 0 | I45: =SUM(I7:I34)+SUM(I37:I42) -> 0 | J45: =IF(G45=0,0,H45/G45) -> 0 | L45: =IF(D45-G45=SUM(L8:L42),D45-G45,"attenzione!") -> attenzione! | N45: =IF(G45=0,0,G45/D45) -> 0 | O45: =SUM(O7:O34)+SUM(O37:O42) -> 1524871.4 | P45: =IF(D45=0,"ok",IF(G45<D45,"ok","ATTENZIONE")) -> ok | Q45: =IF(D45=0,"-",IF(L45>=O45,"ok","ATTENZIONE")) -> ok | R45: =IF(D45=0,"-",IF(N45>=(H45/D45),"ok","ATTENZIONE")) -> ok | T45: =IF(ROUND(L45-O45,2)=ROUND(SUM(T7:T42),2),SUM(T7:T42),"ATTENZIONE") -> #VALUE! | V45: =SUM(V8:V42) -> 0
A48: ='SUMMARY COSTI'!B20 -> sviluppo tecnico e PM TOTALE. | B48: Totale costi previsti € | D48: ='SUMMARY COSTI'!D20 -> 45000 | H48: =V48 -> 0 | I48: =G48-H48 -> 0 | J48: =IF(G48=0,0,H48/G48) -> 0 | K48: 0 | L48: =D48-G48 -> 45000 | M48: =IF(L48<0,"-","ok") -> ok | N48: =IF(D48=0,0,IF(G48=0,0,IF(G48/D48<1,G48/D48,1))) -> 0 | O48: =IF(K48<>0,(G48/K48)-G48,D48*(1-K48)) -> 45000 | P48: =IF(D48=0,IF(G48=0,"-","ATTENZIONE"),IF(G48<D48,"ok","ATTENZIONE")) -> ok | Q48: =IF(D48=0,"-",IF(K48>=N48,"ok","ATTENZIONE")) -> ok | R48: =IF(D48=0,"-",IF(K48>=(H48/D48),"ok","ATTENZIONE")) -> ok | T48: =IF(K48=1,L48,D48-G48-O48) -> 0 | V48: =SUM(W48:Y48) -> 0
A49: VOCI AGGIUNTE DURANTE COMMESSA | H49: =V49 -> 0 | I49: =G49-H49 -> 0 | J49: =IF(G49=0,0,H49/G49) -> 0 | K49: 0 | L49: =D49-G49 -> 0 | M49: =IF(L49<0,"-","ok") -> ok | N49: =IF(D49=0,0,IF(G49=0,0,IF(G49/D49<1,G49/D49,1))) -> 0 | O49: =IF(K49<>0,(G49/K49)-G49,D49*(1-K49)) -> 0 | P49: =IF(D49=0,IF(G49=0,"-","ATTENZIONE"),IF(G49<D49,"ok","ATTENZIONE")) -> - | Q49: =IF(D49=0,"-",IF(K49>=N49,"ok","ATTENZIONE")) -> - | R49: =IF(D49=0,"-",IF(K49>=(H49/D49),"ok","ATTENZIONE")) -> - | T49: =IF(K49=1,L49,D49-G49-O49) -> 0 | V49: =SUM(W49:Y49) -> 0
B50: Totale costi previsti € | H50: =V50 -> 0 | I50: =G50-H50 -> 0 | J50: =IF(G50=0,0,H50/G50) -> 0 | K50: 0 | L50: =D50-G50 -> 0 | M50: =IF(L50<0,"-","ok") -> ok | N50: =IF(D50=0,0,IF(G50=0,0,IF(G50/D50<1,G50/D50,1))) -> 0 | O50: =IF(K50<>0,(G50/K50)-G50,D50*(1-K50)) -> 0 | P50: =IF(D50=0,IF(G50=0,"-","ATTENZIONE"),IF(G50<D50,"ok","ATTENZIONE")) -> - | Q50: =IF(D50=0,"-",IF(K50>=N50,"ok","ATTENZIONE")) -> - | R50: =IF(D50=0,"-",IF(K50>=(H50/D50),"ok","ATTENZIONE")) -> - | T50: =IF(K50=1,L50,D50-G50-O50) -> 0 | V50: =SUM(W50:Y50) -> 0
B51: Totale costi previsti € | H51: =V51 -> 0 | I51: =G51-H51 -> 0 | J51: =IF(G51=0,0,H51/G51) -> 0 | K51: 0 | L51: =D51-G51 -> 0 | M51: =IF(L51<0,"-","ok") -> ok | N51: =IF(D51=0,0,IF(G51=0,0,IF(G51/D51<1,G51/D51,1))) -> 0 | O51: =IF(K51<>0,(G51/K51)-G51,D51*(1-K51)) -> 0 | P51: =IF(D51=0,IF(G51=0,"-","ATTENZIONE"),IF(G51<D51,"ok","ATTENZIONE")) -> - | Q51: =IF(D51=0,"-",IF(K51>=N51,"ok","ATTENZIONE")) -> - | R51: =IF(D51=0,"-",IF(K51>=(H51/D51),"ok","ATTENZIONE")) -> - | T51: =IF(K51=1,L51,D51-G51-O51) -> 0 | V51: =SUM(W51:Y51) -> 0
B52: Totale costi previsti € | H52: =V52 -> 0 | I52: =G52-H52 -> 0 | J52: =IF(G52=0,0,H52/G52) -> 0 | K52: 0 | L52: =D52-G52 -> 0 | M52: =IF(L52<0,"-","ok") -> ok | N52: =IF(D52=0,0,IF(G52=0,0,IF(G52/D52<1,G52/D52,1))) -> 0 | O52: =IF(K52<>0,(G52/K52)-G52,D52*(1-K52)) -> 0 | P52: =IF(D52=0,IF(G52=0,"-","ATTENZIONE"),IF(G52<D52,"ok","ATTENZIONE")) -> - | Q52: =IF(D52=0,"-",IF(K52>=N52,"ok","ATTENZIONE")) -> - | R52: =IF(D52=0,"-",IF(K52>=(H52/D52),"ok","ATTENZIONE")) -> - | T52: =IF(K52=1,L52,D52-G52-O52) -> 0 | V52: =SUM(W52:Y52) -> 0
B53: Totale costi previsti € | H53: =V53 -> 0 | I53: =G53-H53 -> 0 | J53: =IF(G53=0,0,H53/G53) -> 0 | K53: 0 | L53: =D53-G53 -> 0 | M53: =IF(L53<0,"-","ok") -> ok | N53: =IF(D53=0,0,IF(G53=0,0,IF(G53/D53<1,G53/D53,1))) -> 0 | O53: =IF(K53<>0,(G53/K53)-G53,D53*(1-K53)) -> 0 | P53: =IF(D53=0,IF(G53=0,"-","ATTENZIONE"),IF(G53<D53,"ok","ATTENZIONE")) -> - | Q53: =IF(D53=0,"-",IF(K53>=N53,"ok","ATTENZIONE")) -> - | R53: =IF(D53=0,"-",IF(K53>=(H53/D53),"ok","ATTENZIONE")) -> - | T53: =IF(K53=1,L53,D53-G53-O53) -> 0 | V53: =SUM(W53:Y53) -> 0
C55: Totale costi previsti B1 - € | D55: =SUM(D47:D54) -> 45000
A58: ='SUMMARY COSTI'!B19 -> Trasporto e Imballo TOT. | B58: Totale costi previsti € | D58: ='SUMMARY COSTI'!D19 -> 11137.487 | H58: =V58 -> 0 | I58: =G58-H58 -> 0 | J58: =IF(G58=0,0,H58/G58) -> 0 | K58: 0 | L58: =D58-G58 -> 11137.487 | M58: =IF(L58<0,"-","ok") -> ok | N58: =IF(D58=0,0,IF(G58=0,0,IF(G58/D58<1,G58/D58,1))) -> 0 | O58: =IF(K58<>0,(G58/K58)-G58,D58*(1-K58)) -> 11137.487 | P58: =IF(D58=0,IF(G58=0,"-","ATTENZIONE"),IF(G58<D58,"ok","ATTENZIONE")) -> ok | Q58: =IF(D58=0,"-",IF(K58>=N58,"ok","ATTENZIONE")) -> ok | R58: =IF(D58=0,"-",IF(K58>=(H58/D58),"ok","ATTENZIONE")) -> ok | T58: =IF(K58=1,L58,D58-G58-O58) -> 0 | V58: =SUM(W58:Y58) -> 0
C60: Totale costi previsti B2 - € | D60: =SUM(D58:D58) -> 11137.487
A63: ='SUMMARY COSTI'!B21 -> PRESIDIO CANTIERE SITE MNG NOLI CANTIERIZZAZIONE TOT. | B63: Totale costi previsti € | D63: ='SUMMARY COSTI'!C21 -> 4640.6198 | H63: =V63 -> 0 | I63: =G63-H63 -> 0 | J63: =IF(G63=0,0,H63/G63) -> 0 | K63: 0 | L63: =D63-G63 -> 4640.6198 | M63: =IF(L63<0,"-","ok") -> ok | N63: =IF(D63=0,0,IF(G63=0,0,IF(G63/D63<1,G63/D63,1))) -> 0 | O63: =IF(K63<>0,(G63/K63)-G63,D63*(1-K63)) -> 4640.6198 | P63: =IF(D63=0,IF(G63=0,"-","ATTENZIONE"),IF(G63<D63,"ok","ATTENZIONE")) -> ok | Q63: =IF(D63=0,"-",IF(K63>=N63,"ok","ATTENZIONE")) -> ok | R63: =IF(D63=0,"-",IF(K63>=(H63/D63),"ok","ATTENZIONE")) -> ok | T63: =IF(K63=1,L63,D63-G63-O63) -> 0 | V63: =SUM(W63:Y63) -> 0
A64: VOCI AGGIUNTE DURANTE COMMESSA | H64: =V64 -> 0 | I64: =G64-H64 -> 0 | J64: =IF(G64=0,0,H64/G64) -> 0 | K64: 0 | L64: =D64-G64 -> 0 | M64: =IF(L64<0,"-","ok") -> ok | N64: =IF(D64=0,0,IF(G64=0,0,IF(G64/D64<1,G64/D64,1))) -> 0 | O64: =IF(K64<>0,(G64/K64)-G64,D64*(1-K64)) -> 0 | P64: =IF(D64=0,IF(G64=0,"-","ATTENZIONE"),IF(G64<D64,"ok","ATTENZIONE")) -> - | Q64: =IF(D64=0,"-",IF(K64>=N64,"ok","ATTENZIONE")) -> - | R64: =IF(D64=0,"-",IF(K64>=(H64/D64),"ok","ATTENZIONE")) -> - | T64: =IF(K64=1,L64,D64-G64-O64) -> 0 | V64: =SUM(W64:Y64) -> 0
A65: ='SUMMARY COSTI'!B18 -> NOLO TOTALE | B65: Totale costi previsti € | D65: ='SUMMARY COSTI'!D18 -> 0 | H65: =V65 -> 0 | I65: =G65-H65 -> 0 | J65: =IF(G65=0,0,H65/G65) -> 0 | K65: 0 | L65: =D65-G65 -> 0 | M65: =IF(L65<0,"-","ok") -> ok | N65: =IF(D65=0,0,IF(G65=0,0,IF(G65/D65<1,G65/D65,1))) -> 0 | O65: =IF(K65<>0,(G65/K65)-G65,D65*(1-K65)) -> 0 | P65: =IF(D65=0,IF(G65=0,"-","ATTENZIONE"),IF(G65<D65,"ok","ATTENZIONE")) -> - | Q65: =IF(D65=0,"-",IF(K65>=N65,"ok","ATTENZIONE")) -> - | R65: =IF(D65=0,"-",IF(K65>=(H65/D65),"ok","ATTENZIONE")) -> - | T65: =IF(K65=1,L65,D65-G65-O65) -> 0 | V65: =SUM(W65:Y65) -> 0
C67: Totale costi previsti B3 - € | D67: =SUM(D62:D66) -> 4640.6198
C69: TOTALE TIPO B € | D69: =D55+D60+D67 -> 60778.107 | G69: =SUM(G47:G54)+SUM(G57:G59)+SUM(G62:G66) -> 0 | H69: =SUM(H47:H54)+SUM(H57:H59)+SUM(H62:H66) -> 0 | I69: =SUM(I47:I54)+SUM(I57:I59)+SUM(I62:I66) -> 0 | J69: =IF(G69=0,0,H69/G69) -> 0 | L69: =IF(D69-G69=SUM(L47:L66),D69-G69,"attenzione!") -> 60778.107 | N69: =IF(G69=0,0,G69/D69) -> 0 | O69: =SUM(O47:O54)+SUM(O57:O59)+SUM(O62:O66) -> 60778.107 | P69: =IF(D69=0,"ok",IF(G69<D69,"ok","ATTENZIONE")) -> ok | Q69: =IF(D69=0,"-",IF(L69>=O69,"ok","ATTENZIONE")) -> ok | R69: =IF(D69=0,"-",IF(N69>=(H69/D69),"ok","ATTENZIONE")) -> ok | T69: =IF(ROUND(L69-O69,2)=ROUND(SUM(T47:T66),2),SUM(T47:T66),"ATTENZIONE") -> 0 | V69: =SUM(V47:V66) -> 0
A72: Dazi e Cambio | B72: Totale costi previsti € | D72: 0 | H72: =V72 -> 0 | I72: =G72-H72 -> 0 | J72: =IF(G72=0,0,H72/G72) -> 0 | K72: 0 | L72: =D72-G72 -> 0 | M72: =IF(L72<0,"-","ok") -> ok | N72: =IF(D72=0,0,IF(G72=0,0,IF(G72/D72<1,G72/D72,1))) -> 0 | O72: =IF(K72<>0,(G72/K72)-G72,D72*(1-K72)) -> 0 | P72: =IF(D72=0,IF(G72=0,"-","ATTENZIONE"),IF(G72<D72,"ok","ATTENZIONE")) -> - | Q72: =IF(D72=0,"-",IF(K72>=N72,"ok","ATTENZIONE")) -> - | R72: =IF(D72=0,"-",IF(K72>=(H72/D72),"ok","ATTENZIONE")) -> - | T72: =IF(K72=1,L72,D72-G72-O72) -> 0 | V72: =SUM(W72:Y72) -> 0
C74: Totale costi previsti C1 - € | D74: =SUM(D72:D72) -> 0
A77: ='SUMMARY COSTI'!B24 -> COSTI INDUSTRIALI DA COSTI MATERIALE | B77: Totale costi previsti € | D77: ='SUMMARY COSTI'!D24 -> 0 | H77: =V77 -> 0 | I77: =G77-H77 -> 0 | J77: =IF(G77=0,0,H77/G77) -> 0 | K77: 0 | L77: =D77-G77 -> 0 | M77: =IF(L77<0,"-","ok") -> ok | N77: =IF(D77=0,0,IF(G77=0,0,IF(G77/D77<1,G77/D77,1))) -> 0 | O77: =IF(K77<>0,(G77/K77)-G77,D77*(1-K77)) -> 0 | P77: =IF(D77=0,IF(G77=0,"-","ATTENZIONE"),IF(G77<D77,"ok","ATTENZIONE")) -> - | Q77: =IF(D77=0,"-",IF(K77>=N77,"ok","ATTENZIONE")) -> - | R77: =IF(D77=0,"-",IF(K77>=(H77/D77),"ok","ATTENZIONE")) -> - | T77: =IF(K77=1,L77,D77-G77-O77) -> 0 | V77: =SUM(W77:Y77) -> 0
C79: Totale costi previsti B2 - € | D79: =SUM(D77:D77) -> 0
C81: TOTALE TIPO C € | D81: =D74+D79 -> 0 | G81: =SUM(G72:G72)+SUM(G77) -> 0 | H81: =V81 -> 0 | I81: =G81-H81 -> 0 | J81: =IF(G81=0,0,H81/G81) -> 0 | L81: =IF(D81-G81=SUM(L72:L77),D81-G81,"attenzione!") -> 0 | N81: =IF(G81=0,0,G81/D81) -> 0 | O81: =IF(K81<>0,(G81/K81)-G81,D81*(1-K81)) -> 0 | P81: =IF(D81=0,"ok",IF(G81<D81,"ok","ATTENZIONE")) -> ok | Q81: =IF(D81=0,"-",IF(L81>=O81,"ok","ATTENZIONE")) -> - | R81: =IF(D81=0,"-",IF(N81>=(H81/D81),"ok","ATTENZIONE")) -> - | T81: =IF(K81=1,L81,D81-G81-O81) -> 0 | V81: =SUM(V72:V79) -> 0
A83: in costi generali messi anche costi finanz assic
D84: BUDGET | G84: Ordini emessi | H84: Costi sostenuti | I84: Da evadere | J84: % pagati su ordine | L84: Disponibilità residua | N84: % su preventivato | O84: Ipotesi di ordine residuo | P84: CONTROLLO Budget/ordine | Q84: CONTROLLO Ordine/Residuo | R84: CONTROLLO pagamenti | T84: AVANZO
C86: TOTALE A+B+C € | D86: =D45+D69+D81 -> 988902.06 | G86: =G45+G69+G81 -> 0 | H86: =H45+H69+H81 -> 0 | I86: =I45+I69+I81 -> 0 | J86: =IF(G86=0,0,H86/G86) -> 0 | L86: =IF(D86-G86=L45+L69+L81,D86-G86,"attenzione!") -> #VALUE! | N86: =IF(G86=0,0,G86/D86) -> 0 | O86: =O45+O69+O81 -> 1585649.5 | P86: =IF(D86=0,"ok",IF(G86<D86,"ok","ATTENZIONE")) -> ok | Q86: =IF(D86=0,"-",IF(L86>=O86,"ok","ATTENZIONE")) -> #VALUE! | R86: =IF(D86=0,"-",IF(N86>=(H86/D86),"ok","ATTENZIONE")) -> ok | T86: =IF(ROUND(L86-O86,2)=ROUND(T45+T69+T81,2),SUM(T45+T69+T81),"ATTENZIONE") -> #VALUE! | V86: =V45+V69+V81 -> 0

Sheet Voci Contrattuali_SAL
B4: M.O. | CE4: CLIENTE
B5: SAL | F5: N° Comm. PXXXX_22 | H5: Commessa: XXXXXXXXXXXXX | CE5: =ANACO!C7 -> VASTINT ITALY s.r.l.
CE6: COMMESSA | CF6: =ANACO!C5 -> P1002_25_CON_REV03_P1 E EI ALLUMINIO
B8: =B15 -> ITEM | C8: Descrizione | D8: Q.tà | E8: Tot . Ml | F8: Mq | G8: Tot . Mq | H8: importo unit. | I8: Tot. € Contrattuali | CE8: Acconto alla firma contratto | CF8: Acconto Disegni costruttivi | CG8: Posa staffe, tubolari in ferro, lamiere per posa guaina e falsitelai | CJ8: Installazione completa reticoli e accessori per posa tamponamenti, telai per serramenti e porte | CM8: Tamponamenti visivi e pannellatura in genere | CP8: Scossaline, copertine e lamiere di finitura e finiture in genere | CS8: Avanzamento!! | CT8: MESE1 | CU8: MESE2 | CV8: MESE3 | CW8: MESE4 | CX8: MESE5 | CY8: MESE6 | CZ8: MESE7 | DA8: MESE8 | DB8: MESE9 | DC8: MESE10
CE9: Valore | CF9: Valore | CG9: Qty [n] | CH9: Qty [%] | CI9: Valore | CJ9: Qty [n] | CK9: Qty [%] | CL9: Valore | CM9: Qty [n] | CN9: Qty [%] | CO9: Valore | CP9: Qty [n] | CQ9: Qty [%] | CR9: Valore | CT9: SAL-1 | CU9: SAL-2 | CV9: SAL-3 | CW9: SAL-4 | CX9: SAL-5 | CY9: SAL-6 | CZ9: SAL-7 | DA9: SAL-8 | DB9: SAL-9 | DC9: SAL-10
CE10: 0 | CF10: 0 | CI10: 0.2 | CL10: 0.3 | CO10: 0.4 | CR10: 0.1
C11: REALIZZAZIONE MOCK-UP | D11: 1 | G11: 1 | I11: 0 | CG11: 0 | CH11: 0 | CI11: =+CH11*I11*$CI$10*CG11 -> 0 | CJ11: 0 | CK11: 0 | CL11: =+CK11*I11*$CL$10*CJ11 -> 0 | CM11: 0 | CN11: 0 | CO11: =+CN11*I11*$CO$10*CM11 -> 0 | CP11: 0 | CQ11: 0 | CR11: =+CQ11*I11*$CR$10*CP11 -> 0 | CS11: =SUM(CR11+CO11+CL11+CI11+CF11+CE11) -> 0
C12: Somme Totali | G12: =SUM(G11:G11) -> 1 | I12: =SUM(I11:I11) -> 0 | CS12: =SUM(CR12+CO12+CL12+CI12+CF12+CE12) -> 0
BF13: VETRI | BJ13: GRIGLIA/PAN | BK13: LAMIERA | CC13: FALSO TELAIO | CE13: Acconto alla firma contratto | CF13: Acconto Disegni costruttivi | CG13: Posa staffe, tubolari in ferro, lamiere per posa guaina e falsitelai | CJ13: Installazione completa reticoli e accessori per posa tamponamenti, telai per serramenti e porte | CM13: Tamponamenti visivi e pannellatura in genere | CP13: Scossaline, copertine e lamiere di finitura e finiture in genere | CT13: MESE1 | CU13: MESE2 | CV13: MESE3 | CW13: MESE4 | CX13: MESE5 | CY13: MESE6 | CZ13: MESE7 | DA13: MESE8 | DB13: MESE9 | DC13: MESE10
D14: Q.ta a contratto INIZIALI | J14: NOTE | K14: UNITA DI REALIZZO REALI | L14: PT | P14: P1 | T14: P2 | X14: P3 | AB14: P4 | AF14: P5 | AJ14: P6 | AN14: P7 | AR14: P8 | BF14: TIPO 1 | BG14: TIPO 2 | BH14: PIPO 3 | BI14: PIPO 4 | BK14: QTA | BL14: LUNGH | BM14: QTA | BN14: LUNGH | BO14: QTA | BP14: LUNGH | BQ14: QTA | BR14: LUNGH | BS14: QTA | BT14: LUNGH | BU14: QTA | BV14: LUNGH | BW14: QTA | BX14: LUNGH | BY14: QTA | BZ14: LUNGH | CA14: QTA | CB14: LUNGH | CC14: QTA | CD14: MT | CE14: Valore | CF14: Valore | CG14: Qty [n] | CH14: Qty [%] | CI14: Valore | CJ14: Qty [n] | CK14: Qty [%] | CL14: Valore | CM14: Qty [n] | CN14: Qty [%] | CO14: Valore | CP14: Qty [n] | CQ14: Qty [%] | CR14: Valore | CT14: SAL-1 | CU14: SAL-2 | CV14: SAL-3 | CW14: SAL-4 | CX14: SAL-5 | CY14: SAL-6 | CZ14: SAL-7 | DA14: SAL-8 | DB14: SAL-9 | DC14: SAL-10
B15: ITEM | C15: Descrizione | D15: Q.tà | E15: Tot . Ml | F15: Mq | G15: Tot . Mq | H15: importo unit. | I15: Tot. € Contrattuali | L15: NORD | M15: SUD | N15: OVEST | O15: EST | P15: NORD | Q15: SUD | R15: OVEST | S15: EST | T15: NORD | U15: SUD | V15: OVEST | W15: EST | X15: NORD | Y15: SUD | Z15: OVEST | AA15: EST | AB15: NORD | AC15: SUD | AD15: OVEST | AE15: EST | AF15: NORD | AG15: SUD | AH15: OVEST | AI15: EST | AJ15: NORD | AK15: SUD | AL15: OVEST | AM15: EST | AN15: NORD | AO15: SUD | AP15: OVEST | AQ15: EST | AR15: NORD | AS15: SUD | AT15: OVEST | AU15: EST | AV15: L1 | AW15: L2 | AX15: L | AY15: H1 | AZ15: H2 | BA15: H | BB15: mq tot DI REALIZZO | BC15: Unita di Misura considerata A CONTRATTO | BD15: Valore da contabilizzare SINGOLO MQ | BE15: Valore da contabilizzare TOTALE | BF15: DESC 1 | BG15: DESC 2 | BH15: DESC 3 | BI15: DESC 4 | BJ15: GRIGLIA | BK15: LA 01 | BM15: LA 02 | BO15: LA 03 | BQ15: LA 04 | BS15: LA 05 | BU15: LA 06 | BW15: LA 07 | BY15: LA 08 | CA15: LA 09 | CC15: L INTERNA FALSO IN LEGNO | CD15: H INTERNA FALSO IN LEGNO | CE15: 0 | CF15: 0 | CI15: 0.2 | CL15: 0.3 | CO15: 0.4 | CR15: 0.1
B16: =ANACO!B12 -> 0 | C16: =ANACO!C12 -> SERRAMENTI SERIE F | D16: =ANACO!H12 -> 0 | F16: =ANACO!G12 -> 0 | G16: =ANACO!I12 -> 0 | H16: =ANACO!BS12 -> 0 | I16: =ANACO!BT12 -> 0 | K16: =SUM(L16:AU16) -> 0 | L16: 0 | AX16: 0 | BA16: 0 | BB16: =K16*(AX16*BA16/1000000) -> 0 | BD16: =H16/(F16) -> #DIV/0! | BE16: =(BB16*BD16) -> #DIV/0! | CE16: 0 | CF16: 0 | CG16: 1 | CH16: 0 | CI16: =+CH16*BE16*$CI$10*CG16 -> #DIV/0! | CJ16: 1 | CK16: 0 | CL16: =+CK16*BE16*$CL$10*CJ16 -> #DIV/0! | CM16: 1 | CN16: 0 | CO16: =+CN16*BE16*$CO$10*CM16 -> #DIV/0! | CP16: 1 | CQ16: 0 | CR16: =+CQ16*BE16*$CR$10*CP16 -> #DIV/0! | CS16: =SUM(CR16+CO16+CL16+CI16+CF16+CE16) -> #DIV/0!
B17: =ANACO!B13 -> F1 | C17: =ANACO!C13 -> Serramento in legno doppia anta battente apertura interna e sopraluce curvo con apertura vasistas fissato solidamente ad un controtelaio in profili di legno adeguatamente trattato e isolato. Compreso controtelaio costituito da profili in legno sagomato a L, adeguatamente trattato per evitare formazione di muffe o deformazioni geometriche, ancorato alla struttura principale mediante adeguate zanche annegate nel muro o viti di fissaggio. Vetro: 66.2 COOL-LITE 70-33#2 INDURITI / 20mm (aria-argon 90%) / 55.2 int. RICOTTI Comprese lamiere di raccordo, memebrane e isolanti. | D17: =ANACO!H13 -> 10 | F17: =ANACO!G13 -> 2.167 | G17: =ANACO!I13 -> 21.67 | H17: =ANACO!BS13 -> 4443.0585 | I17: =ANACO!BT13 -> 44430.585 | K17: =SUM(L17:AU17) -> 0 | L17: 0 | AX17: 0 | BA17: 0 | BB17: =K17*(AX17*BA17/1000000) -> 0 | BD17: =H17/(F17) -> 2050.327 | BE17: =(BB17*BD17) -> 0 | CE17: 0 | CF17: 0 | CG17: 1 | CH17: 0 | CI17: =+CH17*BE17*$CI$10*CG17 -> 0 | CJ17: 1 | CK17: 0 | CL17: =+CK17*BE17*$CL$10*CJ17 -> 0 | CM17: 1 | CN17: 0 | CO17: =+CN17*BE17*$CO$10*CM17 -> 0 | CP17: 1 | CQ17: 0 | CR17: =+CQ17*BE17*$CR$10*CP17 -> 0 | CS17: =SUM(CR17+CO17+CL17+CI17+CF17+CE17) -> 0
B18: =ANACO!B14 -> F1a | C18: =ANACO!C14 -> Serramento in legno doppia anta battente apertura interna e sopraluce curvo con apertura vasistas fissato solidamente ad un controtelaio in profili di legno adeguatamente trattato e isolato. Compreso controtelaio costituito da profili in legno sagomato a L, adeguatamente trattato per evitare formazione di muffe o deformazioni geometriche, ancorato alla struttura principale mediante adeguate zanche annegate nel muro o viti di fissaggio. Vetro: 66.2 COOL-LITE 70-33#2 INDURITI / 20mm (aria-argon 90%) / 55.2 int. RICOTTI Comprese lamiere di raccordo, memebrane e isolanti. | D18: =ANACO!H14 -> 1 | F18: =ANACO!G14 -> 2.167 | G18: =ANACO!I14 -> 2.167 | H18: =ANACO!BS14 -> 4443.0585 | I18: =ANACO!BT14 -> 4443.0585 | K18: =SUM(L18:AU18) -> 0 | L18: 0 | AX18: 0 | BA18: 0 | BB18: =K18*(AX18*BA18/1000000) -> 0 | BD18: =H18/(F18) -> 2050.327 | BE18: =(BB18*BD18) -> 0 | CE18: 0 | CF18: 0 | CG18: 1 | CH18: 0 | CI18: =+CH18*BE18*$CI$10*CG18 -> 0 | CJ18: 1 | CK18: 0 | CL18: =+CK18*BE18*$CL$10*CJ18 -> 0 | CM18: 1 | CN18: 0 | CO18: =+CN18*BE18*$CO$10*CM18 -> 0 | CP18: 1 | CQ18: 0 | CR18: =+CQ18*BE18*$CR$10*CP18 -> 0 | CS18: =SUM(CR18+CO18+CL18+CI18+CF18+CE18) -> 0
B19: =ANACO!B15 -> F2 | C19: =ANACO!C15 -> Serramento in legno doppia anta battente apertura interna e sopraluce curvo fisso. Specchiature fisse laterali e superiori, fissato solidamente ad un controtelaio in profili di legno adeguatamente trattato e isolato e persiane a lamelle fisse esterne. Compreso controtelaio costituito da profili in legno sagomato a L, adeguatamente trattato per evitare formazione di muffe o deformazioni geometriche, ancorato alla struttura principale mediante adeguate zanche annegate nel muro o viti di fissaggio. Vetro: 66.2 COOL-LITE 70-33#2 INDURITI / 20mm (aria-argon 90%) / 55.2 int. RICOTTI Comprese lamiere di raccordo, memebrane e isolanti. | D19: =ANACO!H15 -> 5 | F19: =ANACO!G15 -> 6.3812 | G19: =ANACO!I15 -> 31.906 | H19: =ANACO!BS15 -> 9861.8457 | I19: =ANACO!BT15 -> 49309.228 | K19: =SUM(L19:AU19) -> 0 | L19: 0 | AX19: 0 | BA19: 0 | BB19: =K19*(AX19*BA19/1000000) -> 0 | BD19: =H19/(F19) -> 1545.4532 | BE19: =(BB19*BD19) -> 0 | CE19: 0 | CF19: 0 | CG19: 1 | CH19: 0 | CI19: =+CH19*BE19*$CI$10*CG19 -> 0 | CJ19: 1 | CK19: 0 | CL19: =+CK19*BE19*$CL$10*CJ19 -> 0 | CM19: 1 | CN19: 0 | CO19: =+CN19*BE19*$CO$10*CM19 -> 0 | CP19: 1 | CQ19: 0 | CR19: =+CQ19*BE19*$CR$10*CP19 -> 0 | CS19: =SUM(CR19+CO19+CL19+CI19+CF19+CE19) -> 0
B20: =ANACO!B16 -> F3 - EI60 Serramento in acciaio EI60 tipo Secco EBE85 | C20: =ANACO!C16 -> Serramento in legno fissa, serramento fissato solidamente ad un controtelaio in profili di legno adeguatamente trattato e isolato. Per questo serramento è richiesta una prestazione di resistenza all’incendio pari a EI60. SOSTITUITO CON ALLUMINIO Reynaers ConceptSystem 77-FP EI 60 (CS 77-FPEI60) Compreso controtelaio costituito da profili in legno sagomato a L, adeguatamente trattato per evitare formazione di muffe o deformazioni geometriche, ancorato alla struttura principale mediante adeguate zanche annegate nel muro o viti di fissaggio. Vetro: 66.2 COOL-LITE 70-33#2 / 14mm (aria-argon 90%) / 27 CF60-3. Comprese lamiere di raccordo, memebrane e isolanti. | D20: =ANACO!H16 -> 3 | F20: =ANACO!G16 -> 3.6 | G20: =ANACO!I16 -> 10.8 | H20: =ANACO!BS16 -> 8821.1292 | I20: =ANACO!BT16 -> 26463.388 | K20: =SUM(L20:AU20) -> 0 | L20: 0 | AX20: 0 | BA20: 0 | BB20: =K20*(AX20*BA20/1000000) -> 0 | BD20: =H20/(F20) -> 2450.3137 | BE20: =(BB20*BD20) -> 0 | CE20: 0 | CF20: 0 | CG20: 1 | CH20: 0 | CI20: =+CH20*BE20*$CI$10*CG20 -> 0 | CJ20: 1 | CK20: 0 | CL20: =+CK20*BE20*$CL$10*CJ20 -> 0 | CM20: 1 | CN20: 0 | CO20: =+CN20*BE20*$CO$10*CM20 -> 0 | CP20: 1 | CQ20: 0 | CR20: =+CQ20*BE20*$CR$10*CP20 -> 0 | CS20: =SUM(CR20+CO20+CL20+CI20+CF20+CE20) -> 0
B21: =ANACO!B17 -> F3a | C21: =ANACO!C17 -> Porta a doppio battente apertura interno dell’edificio con pushbar esterno e chiudiporta, presenza di sopraluce fisso è presente un ulteriore sopraluce curvo con presenza di lamelle di areazione. Il serramento presente una prestazione EI60 escluso la parte lamellata. SOSTITUITO CON ALLUMINIO Reynaers ConceptSystem 77-FP EI 60 (CS 77-FPEI60) Compreso controtelaio costituito da profili in legno sagomato a L, adeguatamente trattato per evitare formazione di muffe o deformazioni geometriche, ancorato alla struttura principale mediante adeguate zanche annegate nel muro o viti di fissaggio. Vetro: 66.2 COOL-LITE 70-33#2 / 14mm (aria-argon 90%) / 27 CF60-3. Comprese lamiere di raccordo, memebrane e isolanti. | D21: =ANACO!H17 -> 1 | F21: =ANACO!G17 -> 3.6 | G21: =ANACO!I17 -> 3.6 | H21: =ANACO!BS17 -> 6217.2576 | I21: =ANACO!BT17 -> 6217.2576 | K21: =SUM(L21:AU21) -> 0 | L21: 0 | AX21: 0 | BA21: 0 | BB21: =K21*(AX21*BA21/1000000) -> 0 | BD21: =H21/(F21) -> 1727.016 | BE21: =(BB21*BD21) -> 0 | CE21: 0 | CF21: 0 | CG21: 1 | CH21: 0 | CI21: =+CH21*BE21*$CI$10*CG21 -> 0 | CJ21: 1 | CK21: 0 | CL21: =+CK21*BE21*$CL$10*CJ21 -> 0 | CM21: 1 | CN21: 0 | CO21: =+CN21*BE21*$CO$10*CM21 -> 0 | CP21: 1 | CQ21: 0 | CR21: =+CQ21*BE21*$CR$10*CP21 -> 0 | CS21: =SUM(CR21+CO21+CL21+CI21+CF21+CE21) -> 0
B22: =ANACO!B18 -> F3b | C22: =ANACO!C18 -> Serramento con specchiature vision fisse è presente un ulteriore sopraluce curvo con presenza di lamelle di areazione. Il serramento presenta una prestazione EI60 escluso la parte lamellata.SOSTITUITO CON ALLUMINIO Reynaers ConceptSystem 77-FP EI 60 (CS 77-FPEI60) Compreso controtelaio costituito da profili in legno sagomato a L, adeguatamente trattato per evitare formazione di muffe o deformazioni geometriche, ancorato alla struttura principale mediante adeguate zanche annegate nel muro o viti di fissaggio. Vetro: 66.2 COOL-LITE 70-33#2 / 14mm (aria-argon 90%) / 27 CF60-3. Comprese lamiere di raccordo, memebrane e isolanti. | D22: =ANACO!H18 -> 2 | F22: =ANACO!G18 -> 3.6 | G22: =ANACO!I18 -> 7.2 | H22: =ANACO!BS18 -> 6217.2576 | I22: =ANACO!BT18 -> 12434.515 | K22: =SUM(L22:AU22) -> 0 | L22: 0 | AX22: 0 | BA22: 0 | BB22: =K22*(AX22*BA22/1000000) -> 0 | BD22: =H22/(F22) -> 1727.016 | BE22: =(BB22*BD22) -> 0 | CE22: 0 | CF22: 0 | CG22: 1 | CH22: 0 | CI22: =+CH22*BE22*$CI$10*CG22 -> 0 | CJ22: 1 | CK22: 0 | CL22: =+CK22*BE22*$CL$10*CJ22 -> 0 | CM22: 1 | CN22: 0 | CO22: =+CN22*BE22*$CO$10*CM22 -> 0 | CP22: 1 | CQ22: 0 | CR22: =+CQ22*BE22*$CR$10*CP22 -> 0 | CS22: =SUM(CR22+CO22+CL22+CI22+CF22+CE22) -> 0
B23: =ANACO!B19 -> F4a | C23: =ANACO!C19 -> Serramento in acciaio con volta circolare apribile a vasistas meccanizzato e automatico specchiatura inferiore con porta a doppio battente apertura esterna, sopraluce rettangolare fisso. SOSTITUITO CON ALLUMINIO Reynaers ConceptSystem 77-FP EI 60 (CS 77-FPEI60) Controtelaio composto da tubi rettangolari ancorato alla struttura principale mediante adeguate zanche annegate nel muro o viti di fissaggio, il telaio deve essere correttamente isolato e zincato per proteggerlo dalla corrosione. Vetro: 66.2 COOL-LITE 70-33#2 / 14mm (aria-argon 90%) / 27 CF60-3. Comprese lamiere di raccordo, memebrane e isolanti. | D23: =ANACO!H19 -> 1 | F23: =ANACO!G19 -> 3.9 | G23: =ANACO!I19 -> 3.9 | H23: =ANACO!BS19 -> 5827.2489 | I23: =ANACO!BT19 -> 5827.2489 | K23: =SUM(L23:AU23) -> 0 | L23: 0 | AX23: 0 | BA23: 0 | BB23: =K23*(AX23*BA23/1000000) -> 0 | BD23: =H23/(F23) -> 1494.1664 | BE23: =(BB23*BD23) -> 0 | CE23: 0 | CF23: 0 | CG23: 1 | CH23: 0 | CI23: =+CH23*BE23*$CI$10*CG23 -> 0 | CJ23: 1 | CK23: 0 | CL23: =+CK23*BE23*$CL$10*CJ23 -> 0 | CM23: 1 | CN23: 0 | CO23: =+CN23*BE23*$CO$10*CM23 -> 0 | CP23: 1 | CQ23: 0 | CR23: =+CQ23*BE23*$CR$10*CP23 -> 0 | CS23: =SUM(CR23+CO23+CL23+CI23+CF23+CE23) -> 0
B24: =ANACO!B20 -> F4b | C24: =ANACO!C20 -> Porta a doppio battente vetrata, apertura doppia anta verso l’esterno, sopraluce fisso. Compreso controtelaio costituito da profili in legno sagomato a L, adeguatamente trattato per evitare formazione di muffe o deformazioni geometriche, ancorato alla struttura principale mediante adeguate zanche annegate nel muro o viti di fissaggio. Vetro: 66.2 COOL-LITE 70-33#2 INDURITI / 20mm (aria-argon 90%) / 55.2 int. RICOTTI Comprese lamiere di raccordo, memebrane e isolanti. | D24: =ANACO!H20 -> 1 | F24: =ANACO!G20 -> 3.9 | G24: =ANACO!I20 -> 3.9 | H24: =ANACO!BS20 -> 8033.6889 | I24: =ANACO!BT20 -> 8033.6889 | K24: =SUM(L24:AU24) -> 0 | L24: 0 | AX24: 0 | BA24: 0 | BB24: =K24*(AX24*BA24/1000000) -> 0 | BD24: =H24/(F24) -> 2059.9202 | BE24: =(BB24*BD24) -> 0 | CE24: 0 | CF24: 0 | CG24: 1 | CH24: 0 | CI24: =+CH24*BE24*$CI$10*CG24 -> 0 | CJ24: 1 | CK24: 0 | CL24: =+CK24*BE24*$CL$10*CJ24 -> 0 | CM24: 1 | CN24: 0 | CO24: =+CN24*BE24*$CO$10*CM24 -> 0 | CP24: 1 | CQ24: 0 | CR24: =+CQ24*BE24*$CR$10*CP24 -> 0 | CS24: =SUM(CR24+CO24+CL24+CI24+CF24+CE24) -> 0
B25: =ANACO!B21 -> F5a - EI60 Serramento in acciaio EI60 tipo Secco EBE85 | C25: =ANACO!C21 -> Porta a doppio battente apertura interno dell’edificio con pushbar esterno e chiudiporta, presenza di sopraluce fisso è presente un ulteriore sopraluce curvo con presenza di lamelle di areazione. Il serramento presente una prestazione EI60 escluso la parte lamellata. SOSTITUITO CON ALLUMINIO Reynaers ConceptSystem 77-FP EI 60 (CS 77-FPEI60) Compreso controtelaio costituito da profili in legno sagomato a L, adeguatamente trattato per evitare formazione di muffe o deformazioni geometriche, ancorato alla struttura principale mediante adeguate zanche annegate nel muro o viti di fissaggio. Vetro: 66.2 COOL-LITE 70-33#2 / 14mm (aria-argon 90%) / 27 CF60-3. Comprese lamiere di raccordo, memebrane e isolanti. | D25: =ANACO!H21 -> 1 | F25: =ANACO!G21 -> 5.648 | G25: =ANACO!I21 -> 5.648 | H25: =ANACO!BS21 -> 20012.035 | I25: =ANACO!BT21 -> 20012.035 | K25: =SUM(L25:AU25) -> 0 | L25: 0 | AX25: 0 | BA25: 0 | BB25: =K25*(AX25*BA25/1000000) -> 0 | BD25: =H25/(F25) -> 3543.2073 | BE25: =(BB25*BD25) -> 0 | CE25: 0 | CF25: 0 | CG25: 1 | CH25: 0 | CI25: =+CH25*BE25*$CI$10*CG25 -> 0 | CJ25: 1 | CK25: 0 | CL25: =+CK25*BE25*$CL$10*CJ25 -> 0 | CM25: 1 | CN25: 0 | CO25: =+CN25*BE25*$CO$10*CM25 -> 0 | CP25: 1 | CQ25: 0 | CR25: =+CQ25*BE25*$CR$10*CP25 -> 0 | CS25: =SUM(CR25+CO25+CL25+CI25+CF25+CE25) -> 0
B26: =ANACO!B22 -> F5b - EI60 Serramento in acciaio EI60 tipo Secco EBE85 | C26: =ANACO!C22 -> Serramento con specchiature vision fisse è presente un ulteriore sopraluce curvo con presenza di lamelle di areazione. Il serramento presenta una prestazione EI60 escluso la parte lamellata.SOSTITUITO CON ALLUMINIO Reynaers ConceptSystem 77-FP EI 60 (CS 77-FPEI60) Compreso controtelaio costituito da profili in legno sagomato a L, adeguatamente trattato per evitare formazione di muffe o deformazioni geometriche, ancorato alla struttura principale mediante adeguate zanche annegate nel muro o viti di fissaggio. Vetro: 66.2 COOL-LITE 70-33#2 / 14mm (aria-argon 90%) / 27 CF60-3. Comprese lamiere di raccordo, memebrane e isolanti. | D26: =ANACO!H22 -> 1 | F26: =ANACO!G22 -> 5.648 | G26: =ANACO!I22 -> 5.648 | H26: =ANACO!BS22 -> 15793.921 | I26: =ANACO!BT22 -> 15793.921 | K26: =SUM(L26:AU26) -> 0 | L26: 0 | AX26: 0 | BA26: 0 | BB26: =K26*(AX26*BA26/1000000) -> 0 | BD26: =H26/(F26) -> 2796.3741 | BE26: =(BB26*BD26) -> 0 | CE26: 0 | CF26: 0 | CG26: 1 | CH26: 0 | CI26: =+CH26*BE26*$CI$10*CG26 -> 0 | CJ26: 1 | CK26: 0 | CL26: =+CK26*BE26*$CL$10*CJ26 -> 0 | CM26: 1 | CN26: 0 | CO26: =+CN26*BE26*$CO$10*CM26 -> 0 | CP26: 1 | CQ26: 0 | CR26: =+CQ26*BE26*$CR$10*CP26 -> 0 | CS26: =SUM(CR26+CO26+CL26+CI26+CF26+CE26) -> 0
B27: =ANACO!B23 -> F6 | C27: =ANACO!C23 -> Serramento portafinestra in legno doppia anta battente apertura interna fissato solidamente ad un controtelaio in profili di legno adeguatamente trattato e isolato. Compreso controtelaio costituito da profili in legno sagomato a L, adeguatamente trattato per evitare formazione di muffe o deformazioni geometriche, ancorato alla struttura principale mediante adeguate zanche annegate nel muro o viti di fissaggio. Vetro: 66.2 COOL-LITE 70-33#2 INDURITI / 20mm (aria-argon 90%) / 55.2 int. RICOTTI Comprese lamiere di raccordo, memebrane e isolanti. | D27: =ANACO!H23 -> 11 | F27: =ANACO!G23 -> 3.835 | G27: =ANACO!I23 -> 42.185 | H27: =ANACO!BS23 -> 6480.5492 | I27: =ANACO!BT23 -> 71286.041 | K27: =SUM(L27:AU27) -> 0 | L27: 0 | AX27: 0 | BA27: 0 | BB27: =K27*(AX27*BA27/1000000) -> 0 | BD27: =H27/(F27) -> 1689.8433 | BE27: =(BB27*BD27) -> 0 | CE27: 0 | CF27: 0 | CG27: 1 | CH27: 0 | CI27: =+CH27*BE27*$CI$10*CG27 -> 0 | CJ27: 1 | CK27: 0 | CL27: =+CK27*BE27*$CL$10*CJ27 -> 0 | CM27: 1 | CN27: 0 | CO27: =+CN27*BE27*$CO$10*CM27 -> 0 | CP27: 1 | CQ27: 0 | CR27: =+CQ27*BE27*$CR$10*CP27 -> 0 | CS27: =SUM(CR27+CO27+CL27+CI27+CF27+CE27) -> 0
... B156: =ANACO!B152 -> 0 | C156: =ANACO!C152 -> 0 | D156: =ANACO!H152 -> 0 | F156: =ANACO!G152 -> 0 | G156: =ANACO!I152 -> 0 | H156: =ANACO!BS152 -> 0 | I156: =ANACO!BT152 -> 0 | K156: =SUM(L156:AU156) -> 0 | L156: 0 | AX156: 0 | BA156: 0 | BB156: =K156*(AX156*BA156/1000000) -> 0 | BD156: =H156/(F156) -> #DIV/0! | BE156: =(BB156*BD156) -> #DIV/0! | CE156: 0 | CF156: 0 | CG156: 1 | CH156: 0 | CI156: =+CH156*BE156*$CI$10*CG156 -> #DIV/0! | CJ156: 1 | CK156: 0 | CL156: =+CK156*BE156*$CL$10*CJ156 -> #DIV/0! | CM156: 1 | CN156: 0 | CO156: =+CN156*BE156*$CO$10*CM156 -> #DIV/0! | CP156: 1 | CQ156: 0 | CR156: =+CQ156*BE156*$CR$10*CP156 -> #DIV/0! | CS156: =SUM(CR156+CO156+CL156+CI156+CF156+CE156) -> #DIV/0!
C157: Somme Totali | D157: =SUM(D119:D156) -> 0 | G157: =SUM(G16:G156) -> 630.434 | I157: =SUM(I16:I156) -> 1264104.8 | K157: =SUM(K16:K156) -> 0 | L157: =SUM(L16:L156) -> 0 | M157: =SUM(M16:M156) -> 0 | N157: =SUM(N16:N156) -> 0 | O157: =SUM(O16:O156) -> 0 | P157: =SUM(P16:P156) -> 0 | Q157: =SUM(Q16:Q156) -> 0 | R157: =SUM(R16:R156) -> 0 | ... AU157: =SUM(AU16:AU156) -> 0 | AX157: =SUM(AX16:AX156) -> 0 | BA157: =SUM(BA16:BA156) -> 0 | BB157: =SUM(BB16:BB156) -> 0 | BE157: =SUM(BE16:BE156) -> #DIV/0! | CI157: =SUM(CI16:CI156) -> #DIV/0! | CL157: =SUM(CL16:CL156) -> #DIV/0! | CO157: =SUM(CO16:CO156) -> #DIV/0! | CR157: =SUM(CR16:CR156) -> #DIV/0! | CS157: =SUM(CR157+CO157+CL157+CI157+CF157+CE157) -> #DIV/0!
D160: TOTALE CONTRATTO INIZIALE | I160: =I116+I157+#REF!+#REF! -> #REF!
D161: TOTALECONTRATTO REALE | I161: =BE157 -> #DIV/0!
B162: VARIANTI | BF162: VETRI | BJ162: GRIGLIA/PAN | BK162: LAMIERA | CC162: FALSO TELAIO | CE162: Acconto alla firma contratto | CF162: Acconto Disegni costruttivi | CG162: Posa staffe, tubolari in ferro, lamiere per posa guaina e falsitelai | CJ162: Installazione completa reticoli e accessori per posa tamponamenti, telai per serramenti e porte | CM162: Tamponamenti visivi e pannellatura in genere | CP162: Scossaline, copertine e lamiere di finitura e finiture in genere | CT162: MESE1 | CU162: MESE2 | CV162: MESE3 | CW162: MESE4 | CX162: MESE5 | CY162: MESE6 | CZ162: MESE7 | DA162: MESE8 | DB162: MESE9 | DC162: MESE10
D163: Q.ta a contratto INIZIALI | J163: NOTE | K163: UNITA DI REALIZZO REALI | L163: PT | P163: P1 | T163: P2 | X163: P3 | AB163: P4 | AF163: P5 | AJ163: P6 | AN163: P7 | AR163: P8 | BF163: TIPO 1 | BG163: TIPO 2 | BH163: PIPO 3 | BI163: PIPO 4 | BK163: QTA | BL163: LUNGH | BM163: QTA | BN163: LUNGH | BO163: QTA | BP163: LUNGH | BQ163: QTA | BR163: LUNGH | BS163: QTA | BT163: LUNGH | BU163: QTA | BV163: LUNGH | BW163: QTA | BX163: LUNGH | BY163: QTA | BZ163: LUNGH | CA163: QTA | CB163: LUNGH | CC163: QTA | CD163: MT | CE163: Valore | CF163: Valore | CG163: Qty [n] | CH163: Qty [%] | CI163: Valore | CJ163: Qty [n] | CK163: Qty [%] | CL163: Valore | CM163: Qty [n] | CN163: Qty [%] | CO163: Valore | CP163: Qty [n] | CQ163: Qty [%] | CR163: Valore | CT163: SAL-1 | CU163: SAL-2 | CV163: SAL-3 | CW163: SAL-4 | CX163: SAL-5 | CY163: SAL-6 | CZ163: SAL-7 | DA163: SAL-8 | DB163: SAL-9 | DC163: SAL-10
B164: ITEM | C164: Descrizione | D164: Q.tà | E164: Tot . Ml | F164: Mq | G164: Tot . Mq | H164: importo unit. | I164: Tot. € Contrattuali | L164: NORD | M164: SUD | N164: OVEST | O164: EST | P164: NORD | Q164: SUD | R164: OVEST | S164: EST | T164: NORD | U164: SUD | V164: OVEST | W164: EST | X164: NORD | Y164: SUD | Z164: OVEST | AA164: EST | AB164: NORD | AC164: SUD | AD164: OVEST | AE164: EST | AF164: NORD | AG164: SUD | AH164: OVEST | AI164: EST | AJ164: NORD | AK164: SUD | AL164: OVEST | AM164: EST | AN164: NORD | AO164: SUD | AP164: OVEST | AQ164: EST | AR164: NORD | AS164: SUD | AT164: OVEST | AU164: EST | AV164: L1 | AW164: L2 | AX164: L | AY164: H1 | AZ164: H2 | BA164: H | BB164: mq tot DI REALIZZO | BC164: Unita di Misura considerata A CONTRATTO | BD164: Valore da contabilizzare SINGOLO MQ | BE164: Valore da contabilizzare TOTALE | BF164: DESC 1 | BG164: DESC 2 | BH164: DESC 3 | BI164: DESC 4 | BJ164: GRIGLIA | BK164: LA 01 | BM164: LA 02 | BO164: LA 03 | BQ164: LA 04 | BS164: LA 05 | BU164: LA 06 | BW164: LA 07 | BY164: LA 08 | CA164: LA 09 | CC164: L INTERNA FALSO IN LEGNO | CD164: H INTERNA FALSO IN LEGNO | CE164: 0 | CF164: 0 | CI164: 0.2 | CL164: 0.3 | CO164: 0.4 | CR164: 0.1
B165: =ANACO!B161 -> 0 | K165: =SUM(L165:AU165) -> 0 | L165: 0 | AX165: 0 | BA165: 0 | BB165: =K165*(AX165*BA165/1000000) -> 0 | BD165: =H165/(F165) -> #DIV/0! | BE165: =(BB165*BD165) -> #DIV/0! | CE165: 0 | CF165: 0 | CG165: 1 | CH165: 0 | CI165: =+CH165*BE165*$CI$10*CG165 -> #DIV/0! | CJ165: 1 | CK165: 0 | CL165: =+CK165*BE165*$CL$10*CJ165 -> #DIV/0! | CM165: 1 | CN165: 0 | CO165: =+CN165*BE165*$CO$10*CM165 -> #DIV/0! | CP165: 1 | CQ165: 0 | CR165: =+CQ165*BE165*$CR$10*CP165 -> #DIV/0! | CS165: =SUM(CR165+CO165+CL165+CI165+CF165+CE165) -> #DIV/0!
B166: =ANACO!B162 -> 0 | K166: =SUM(L166:AU166) -> 0 | L166: 0 | AX166: 0 | BA166: 0 | BB166: =K166*(AX166*BA166/1000000) -> 0 | BD166: =H166/(F166) -> #DIV/0! | BE166: =(BB166*BD166) -> #DIV/0! | CE166: 0 | CF166: 0 | CG166: 1 | CH166: 0 | CI166: =+CH166*BE166*$CI$10*CG166 -> #DIV/0! | CJ166: 1 | CK166: 0 | CL166: =+CK166*BE166*$CL$10*CJ166 -> #DIV/0! | CM166: 1 | CN166: 0 | CO166: =+CN166*BE166*$CO$10*CM166 -> #DIV/0! | CP166: 1 | CQ166: 0 | CR166: =+CQ166*BE166*$CR$10*CP166 -> #DIV/0! | CS166: =SUM(CR166+CO166+CL166+CI166+CF166+CE166) -> #DIV/0!
B167: =ANACO!B163 -> 0 | K167: =SUM(L167:AU167) -> 0 | L167: 0 | AX167: 0 | BA167: 0 | BB167: =K167*(AX167*BA167/1000000) -> 0 | BD167: =H167/(F167) -> #DIV/0! | BE167: =(BB167*BD167) -> #DIV/0! | CE167: 0 | CF167: 0 | CG167: 1 | CH167: 0 | CI167: =+CH167*BE167*$CI$10*CG167 -> #DIV/0! | CJ167: 1 | CK167: 0 | CL167: =+CK167*BE167*$CL$10*CJ167 -> #DIV/0! | CM167: 1 | CN167: 0 | CO167: =+CN167*BE167*$CO$10*CM167 -> #DIV/0! | CP167: 1 | CQ167: 0 | CR167: =+CQ167*BE167*$CR$10*CP167 -> #DIV/0! | CS167: =SUM(CR167+CO167+CL167+CI167+CF167+CE167) -> #DIV/0!
B168: =ANACO!B164 -> 0 | K168: =SUM(L168:AU168) -> 0 | L168: 0 | AX168: 0 | BA168: 0 | BB168: =K168*(AX168*BA168/1000000) -> 0 | BD168: =H168/(F168) -> #DIV/0! | BE168: =(BB168*BD168) -> #DIV/0! | CE168: 0 | CF168: 0 | CG168: 1 | CH168: 0 | CI168: =+CH168*BE168*$CI$10*CG168 -> #DIV/0! | CJ168: 1 | CK168: 0 | CL168: =+CK168*BE168*$CL$10*CJ168 -> #DIV/0! | CM168: 1 | CN168: 0 | CO168: =+CN168*BE168*$CO$10*CM168 -> #DIV/0! | CP168: 1 | CQ168: 0 | CR168: =+CQ168*BE168*$CR$10*CP168 -> #DIV/0! | CS168: =SUM(CR168+CO168+CL168+CI168+CF168+CE168) -> #DIV/0!
B169: =ANACO!B165 -> 0 | K169: =SUM(L169:AU169) -> 0 | L169: 0 | AX169: 0 | BA169: 0 | BB169: =K169*(AX169*BA169/1000000) -> 0 | BD169: =H169/(F169) -> #DIV/0! | BE169: =(BB169*BD169) -> #DIV/0! | CE169: 0 | CF169: 0 | CG169: 1 | CH169: 0 | CI169: =+CH169*BE169*$CI$10*CG169 -> #DIV/0! | CJ169: 1 | CK169: 0 | CL169: =+CK169*BE169*$CL$10*CJ169 -> #DIV/0! | CM169: 1 | CN169: 0 | CO169: =+CN169*BE169*$CO$10*CM169 -> #DIV/0! | CP169: 1 | CQ169: 0 | CR169: =+CQ169*BE169*$CR$10*CP169 -> #DIV/0! | CS169: =SUM(CR169+CO169+CL169+CI169+CF169+CE169) -> #DIV/0!
B170: =ANACO!B166 -> 0 | K170: =SUM(L170:AU170) -> 0 | L170: 0 | AX170: 0 | BA170: 0 | BB170: =K170*(AX170*BA170/1000000) -> 0 | BD170: =H170/(F170) -> #DIV/0! | BE170: =(BB170*BD170) -> #DIV/0! | CE170: 0 | CF170: 0 | CG170: 1 | CH170: 0 | CI170: =+CH170*BE170*$CI$10*CG170 -> #DIV/0! | CJ170: 1 | CK170: 0 | CL170: =+CK170*BE170*$CL$10*CJ170 -> #DIV/0! | CM170: 1 | CN170: 0 | CO170: =+CN170*BE170*$CO$10*CM170 -> #DIV/0! | CP170: 1 | CQ170: 0 | CR170: =+CQ170*BE170*$CR$10*CP170 -> #DIV/0! | CS170: =SUM(CR170+CO170+CL170+CI170+CF170+CE170) -> #DIV/0!
B171: =ANACO!B167 -> 0 | K171: =SUM(L171:AU171) -> 0 | L171: 0 | AX171: 0 | BA171: 0 | BB171: =K171*(AX171*BA171/1000000) -> 0 | BD171: =H171/(F171) -> #DIV/0! | BE171: =(BB171*BD171) -> #DIV/0! | CE171: 0 | CF171: 0 | CG171: 1 | CH171: 0 | CI171: =+CH171*BE171*$CI$10*CG171 -> #DIV/0! | CJ171: 1 | CK171: 0 | CL171: =+CK171*BE171*$CL$10*CJ171 -> #DIV/0! | CM171: 1 | CN171: 0 | CO171: =+CN171*BE171*$CO$10*CM171 -> #DIV/0! | CP171: 1 | CQ171: 0 | CR171: =+CQ171*BE171*$CR$10*CP171 -> #DIV/0! | CS171: =SUM(CR171+CO171+CL171+CI171+CF171+CE171) -> #DIV/0!
B172: =ANACO!B168 -> 0 | K172: =SUM(L172:AU172) -> 0 | L172: 0 | AX172: 0 | BA172: 0 | BB172: =K172*(AX172*BA172/1000000) -> 0 | BD172: =H172/(F172) -> #DIV/0! | BE172: =(BB172*BD172) -> #DIV/0! | CE172: 0 | CF172: 0 | CG172: 1 | CH172: 0 | CI172: =+CH172*BE172*$CI$10*CG172 -> #DIV/0! | CJ172: 1 | CK172: 0 | CL172: =+CK172*BE172*$CL$10*CJ172 -> #DIV/0! | CM172: 1 | CN172: 0 | CO172: =+CN172*BE172*$CO$10*CM172 -> #DIV/0! | CP172: 1 | CQ172: 0 | CR172: =+CQ172*BE172*$CR$10*CP172 -> #DIV/0! | CS172: =SUM(CR172+CO172+CL172+CI172+CF172+CE172) -> #DIV/0!
B173: =ANACO!B169 -> 0 | K173: =SUM(L173:AU173) -> 0 | L173: 0 | AX173: 0 | BA173: 0 | BB173: =K173*(AX173*BA173/1000000) -> 0 | BD173: =H173/(F173) -> #DIV/0! | BE173: =(BB173*BD173) -> #DIV/0! | CE173: 0 | CF173: 0 | CG173: 1 | CH173: 0 | CI173: =+CH173*BE173*$CI$10*CG173 -> #DIV/0! | CJ173: 1 | CK173: 0 | CL173: =+CK173*BE173*$CL$10*CJ173 -> #DIV/0! | CM173: 1 | CN173: 0 | CO173: =+CN173*BE173*$CO$10*CM173 -> #DIV/0! | CP173: 1 | CQ173: 0 | CR173: =+CQ173*BE173*$CR$10*CP173 -> #DIV/0! | CS173: =SUM(CR173+CO173+CL173+CI173+CF173+CE173) -> #DIV/0!
B174: =ANACO!B170 -> 0 | K174: =SUM(L174:AU174) -> 0 | L174: 0 | AX174: 0 | BA174: 0 | BB174: =K174*(AX174*BA174/1000000) -> 0 | BD174: =H174/(F174) -> #DIV/0! | BE174: =(BB174*BD174) -> #DIV/0! | CE174: 0 | CF174: 0 | CG174: 1 | CH174: 0 | CI174: =+CH174*BE174*$CI$10*CG174 -> #DIV/0! | CJ174: 1 | CK174: 0 | CL174: =+CK174*BE174*$CL$10*CJ174 -> #DIV/0! | CM174: 1 | CN174: 0 | CO174: =+CN174*BE174*$CO$10*CM174 -> #DIV/0! | CP174: 1 | CQ174: 0 | CR174: =+CQ174*BE174*$CR$10*CP174 -> #DIV/0! | CS174: =SUM(CR174+CO174+CL174+CI174+CF174+CE174) -> #DIV/0!
B175: =ANACO!B171 -> 0 | K175: =SUM(L175:AU175) -> 0 | L175: 0 | AX175: 0 | BA175: 0 | BB175: =K175*(AX175*BA175/1000000) -> 0 | BD175: =H175/(F175) -> #DIV/0! | BE175: =(BB175*BD175) -> #DIV/0! | CE175: 0 | CF175: 0 | CG175: 1 | CH175: 0 | CI175: =+CH175*BE175*$CI$10*CG175 -> #DIV/0! | CJ175: 1 | CK175: 0 | CL175: =+CK175*BE175*$CL$10*CJ175 -> #DIV/0! | CM175: 1 | CN175: 0 | CO175: =+CN175*BE175*$CO$10*CM175 -> #DIV/0! | CP175: 1 | CQ175: 0 | CR175: =+CQ175*BE175*$CR$10*CP175 -> #DIV/0! | CS175: =SUM(CR175+CO175+CL175+CI175+CF175+CE175) -> #DIV/0!
